Workbook

Sheet HOME PAGE
A1: INVESTMENTS AND LOANS (FINANCIAL CALCULATOR)

Sheet Assignment1(Back End)
A1: Given Interest Rate | B1: ='Assignment1(User Interface)'!B3 -> 0 | D1: Requested
A2: Compunding Period Given | B2: ='Assignment1(User Interface)'!B4 -> 0 | D2: Compounding periods | E2: ='Assignment1(User Interface)'!G3 -> 0
A3: Years | B3: ='Assignment1(User Interface)'!B5 -> 0 | D3: Years | E3: ='Assignment1(User Interface)'!B5 -> 0
E6: From
E7: Simple | F7: Effective Annual rate | G7: Nominal | H7: Effective Periodic | I7: Continuous
C8: To | D8: Simple | E8: =(B1*B2*B3)/(E2*B3) -> #DIV/0! | F8: =((((1+B1)^B3))-1)/(E2) -> #DIV/0! | G8: =(((1+$B$1/$B$2))^($B$3*$B$2)-1)/$E$2*$B$3 -> #DIV/0! | H8: =(((1+B1))^(B3*B2)-1)/E2*B3 -> #DIV/0! | I8: =(EXP(B1*B3)-1)/(B3*B2) -> #DIV/0!
D9: Effective Annual rate | E9: =((1+B1*B3*B2)^(1/E2))-1 -> #DIV/0! | F9: =((1+B1)^(B3/E3))-1 -> #DIV/0! | G9: =((((1+(B1/B2))^(B2*B3)))^(1/E2))-1 -> #DIV/0! | H9: =(((1+(B1))^((B2*B3)/E3)))-1 -> #DIV/0! | I9: =(EXP(B1)-1) -> 0
D10: Nominal | E10: =((1+(B1*B3*B2))^(1/(E3*E2))-1)*E2 -> #DIV/0! | F10: =((((1+B1)^B3)^(1/E2*E3))-1)*E2 -> #DIV/0! | G10: =((((1+(B1/B2))^((B2*B3)/(E2*E3))))-1)*E2 -> #DIV/0! | H10: =(((1+(B1))^((B2*B3)/(E2*E3))-1))*E2 -> #DIV/0! | I10: =((EXP(B1/E2))-1)*E2 -> #DIV/0!
D11: Effective Periodic | E11: =((1+(B1*B3*B2))^(1/(E3*E2))-1) -> #DIV/0! | F11: =(((1+B1)^(B3))^(1/(E2*E3)))-1 -> #DIV/0! | G11: =((((1+(B1/B2))^((B2*B3)/(E2*E3))))-1) -> #DIV/0! | H11: =(((1+(B1))^(B2*B3))^(1/(E2*E3)))-1 -> #DIV/0! | I11: =((EXP(B1/E2))-1) -> #DIV/0!
D12: Continuous | E12: =(LN(1+B1*B3*B2))/E3 -> #DIV/0! | F12: =(LN((1+B1)^B3)) -> 0 | G12: =(LN((1+(B1/B2))^(B2*B3)))/E3 -> #DIV/0! | H12: =((LN((1+(B1/B2)^B3))))/E3 -> #DIV/0! | I12: =LN(EXP(B3*B1)) -> 0

Sheet Assignment1(User Interface)
A1: Givens | F1: Requested
A2: Given Type | B2: Continuous | F2: Requested Int Rate Type | G2: Effective periodic
A3: Given Interest Rate | F3: Requested compounding periods | N3: Simple
A4: Given Compound period | F4: The requested rate is: | G4: =IF(AND(B2=N3,G2=N3),'Assignment1(Back End)'!E8,IF(AND(B2=N3,G2=N4),'Assignment1(Back End)'!E9,IF(AND(B2=N3,G2=N5),'Assignment1(Back End)'!E10,IF(AND(B2=N3,G2=N6),'Assignment1(Back End)'!E11,IF(AND(B2=N3,G2=N7),'Assignment1(Back End)'!E12,IF(AND(B2=N4,G2=N3),'Assignment1(Back End)'!F8,IF(AND(B2=N4,G2=N4),'Assignment1(Back End)'!F9,IF(AND(B2=N4,G2=N5),'Assignment1(Back End)'!F10,IF(AND(B2=N4,G2=N6),'Assignment1(Back End)'!F11,IF(AND(B2=N4,G2=N7),'Assignment1(Back End)'!F12,IF(AND(B2=N5,G2=N3),'Assignment1(Back End)'!G8,IF(AND(B2=N5,G2=N4),'Assignment1(Back End)'!G9,IF(AND(B2=N5,G2=N5),'Assignment1(Back End)'!G10,IF(AND(B2=N5,G2=N6),'Assignment1(Back End)'!G11,IF(AND(B2=N5,G2=N7),'Assignment1(Back End)'!G12,IF(AND(B2=N6,G2=N3),'Assignment1(Back End)'!H8,IF(AND(B2=N6,G2=N4),'Assignment1(Back End)'!H9,IF(AND(B2=N6,G2=N5),'Assignment1(Back End)'!H10,IF(AND(B2=N6,G2=N6),'Assignment1(Back End)'!H11,IF(AND(B2=N6,G2=N7),'Assignment1(Back End)'!H12,IF(AND(B2=N7,G2=N3),'Assignment1(Back End)'!I8,IF(AND(B2=N7,G2=N4),'Assignment1(Back End)'!I9,IF(AND(B2=N7,G2=N5),'Assignment1(Back End)'!I10,IF(AND(B2=N7,G2=N6),'Assignment1(Back End)'!I11,IF(AND(B2=N7,G2=N7),'Assignment1(Back End)'!I12,"Still work to do"))))))))))))))))))))))))) -> #DIV/0! | N4: Effective annual
A5: Number of years | N5: Nominal
N6: Effective periodic
N7: Continuous

Sheet Assignment2 (Back End)
A1: Given
A2: Future value | B2: ='Assignment2(User Interface)'!B7 -> 0
A3: Present Value | B3: ='Assignment2(User Interface)'!B8 -> 0
A4: Number of years | B4: =IF('Assignment2(User Interface)'!B9='Assignment2(User Interface)'!W2,'Assignment2(User Interface)'!D12,IF('Assignment2(User Interface)'!B9='Assignment2(User Interface)'!W3,'Assignment2(User Interface)'!B12)) -> 8
A5: Interest | B5: ='Assignment2(User Interface)'!B10 -> 0
A6: Period | B6: ='Assignment2(User Interface)'!B11 -> 0
A7: years
B8: Find
A9: Rates | C9: Future Value | D9: Present Value | E9: Number of Years | F9: Interest | G9: Period | H9: Interest Earned
B10: Simple | C10: =((B3)*(1+(B5*B4*B6))) -> 0 | D10: =B2/(1+(B5*B6*B4)) -> 0 | E10: =((B2/B3)-1)/(B5*B6) -> #DIV/0! | F10: =((B2/B3)-1)/(B4*B6) -> #DIV/0! | G10: =((B2/B3)-1)/(B5*B4) -> #DIV/0! | H10: =C10-D10 -> 0
B11: Effective Annual | C11: =B3*(1+B5)^B4 -> 0 | D11: =B2/((1+B5)^B4) -> 0 | E11: =LOG((B2/B3), (1+B5)) -> #DIV/0! | F11: =((B2/B3)^(1/B4))-1 -> #DIV/0! | G11: 1 | H11: =C11-D11 -> 0
B12: Effective periodic | C12: =B3*(1+B5)^(B6*B4) -> 0 | D12: =B2/((1+B5)^(B4*B6)) -> 0 | E12: =LOG((B2/B3),(1+B5))/B4 -> #DIV/0! | F12: =((B2/B3)^(1/(B4*B6)))-1 -> #DIV/0! | G12: =LOG((B2/B3),(1+B5))/B4 -> #DIV/0! | H12: =C12-D12 -> 0
B13: Nominal | C13: =B3*((1+(B5/B6))^(B4*B6)) -> #DIV/0! | D13: =B2/((1+(B5/B6))^(B4*B6)) -> #DIV/0! | E13: =LOG((B2/B3), (1+(B5/B6)))/B6 -> #DIV/0! | F13: =(((B2/B3)^(1/(B4*B6)))-1)*B6 -> #DIV/0! | G13: =LOG((B2/B3), (1+(B5/B6)))/B4 -> #DIV/0! | H13: =C13-D13 -> #DIV/0!
B14: Continuous | C14: =B3*(EXP(B5*B4)) -> 0 | D14: =B3*(EXP(-B5*B4)) -> 0 | E14: =(LN(B2/B3))/B5 -> #DIV/0! | F14: =(LN(B2/B3))/B4 -> #DIV/0! | G14: =(LN(B2/B3))/B5 -> #DIV/0! | H14: =C14-D14 -> 0

Sheet Assignment2(User Interface)
A1: INVESTMENT CALCULATOR
U2: Simple | V2: Future value | W2: Exact years
A3: Interest RateType | B3: Effective periodic | D3: Unknown Variable | E3: Future value | U3: Effective Annual | V3: Present Value | W3: Dates
U4: Effective periodic | V4: Number of years
D5: Variable Value | E5: =IF(AND(B3=U2,E3=V2),'Assignment2 (Back End)'!C10,IF(AND(B3=U2,E3=V3),'Assignment2 (Back End)'!D10,IF(AND(B3=U2,E3=V4),'Assignment2 (Back End)'!E10,IF(AND(B3=U2,E3=V5),TEXT('Assignment2 (Back End)'!$F$10,"0.0000%"),IF(AND(B3=U2,E3=V6),'Assignment2 (Back End)'!G10,IF(AND(B3=U2,E3=V7),'Assignment2 (Back End)'!H10,IF(AND(B3=U3,E3=V2),'Assignment2 (Back End)'!C11,IF(AND(B3=U3,E3=V3),'Assignment2 (Back End)'!D10,IF(AND(B3=U3,E3=V4),'Assignment2 (Back End)'!E11,IF(AND(B3=U3,E3=V5),TEXT('Assignment2 (Back End)'!F11,"0.0000%"),IF(AND(B3=U3,E3=V6),'Assignment2 (Back End)'!G11,IF(AND(B3=U3,E3=V7),'Assignment2 (Back End)'!H11,IF(AND(B3=U4,E3=V2),'Assignment2 (Back End)'!C12,IF(AND(B3=U4,E3=V3),'Assignment2 (Back End)'!D11,IF(AND(B3=U4,E3=V4),'Assignment2 (Back End)'!E12,IF(AND(B3=U4,E3=V5),TEXT('Assignment2 (Back End)'!F12,"0.0000%"),IF(AND(B3=U4,E3=V6),'Assignment2 (Back End)'!G12,IF(AND(B3=U4,E3=V7),'Assignment2 (Back End)'!H12,IF(AND(B3=U5,E3=V2),'Assignment2 (Back End)'!C13,IF(AND(B3=U5,E3=V3),'Assignment2 (Back End)'!D13,IF(AND(B3=U5,E3=V4),'Assignment2 (Back End)'!E13,IF(AND(B3=U5,E3=V5),TEXT('Assignment2 (Back End)'!F13,"0.0000%"),IF(AND(B3=U5,E3=V6),'Assignment2 (Back End)'!G13,IF(AND(B3=U5,E3=V7),'Assignment2 (Back End)'!H13,IF(AND(B3=U6,E3=V2),'Assignment2 (Back End)'!C14,IF(AND(B3=U6,E3=V3),'Assignment2 (Back End)'!D14,IF(AND(B3=U6,E3=V5),TEXT('Assignment2 (Back End)'!F14,"0.0000%"),IF(AND(B3=U6,E3=V4),'Assignment2 (Back End)'!E14,IF(AND(B3=U6,E3=V6),'Assignment2 (Back End)'!G14,IF(AND(B3=U6,E3=V7),'Assignment2 (Back End)'!H14,"Not Applicable")))))))))))))))))))))))))))))) -> 0 | G5: Increasing Annuities | U5: Nominal | V5: Interest
A6: Given Variables: | U6: Continuous | V6: Period
A7: Future value | D7: Real Future value | E7: =IF(E3=V2,E5*(1+5%)^(-'Assignment2 (Back End)'!B4)," ") -> 0 | G7: Interest converter | V7: Interest Earned
A8: Present Value
A9: Final Number of years | B9: Exact years | G9: HOME
A10: Interest
A11: Period
A12: Number of years in date: | C12: Manualy Entered years: | D12: 8
A13: Start Date (yyyy/mm/dd):
A14: End Date (yyyy/mm/dd):
A15: INTEREST COMPARISON TABLES
A17: Interest Rate Option 1: | B17: Simple | D17: Interest Rate Option 2: | E17: Effective periodic
A19: Periods(Years) | B19: =B17 -> Simple | D19: Periods(Years) | E19: =E17 -> Effective periodic
A20: 1 | B20: =IF($B$17=$U$2,$B$8*(1+($B$10*1*$B$11)),IF($B$17=$U$3,$B$8*((1+$B$10)^1),IF($B$17=$U$4,$B$8*((1+$B$10)^(1*$B$11)),IF($B$17=$U$5,$B$8*((1+($B$10/$B$11))^(1*$B$11)),IF($B$17=$U$6,$B$8*EXP($B$10*1),"Not Applicable"))))) -> 0 | D20: 1 | E20: =IF($E$17=$U$2,$B$8*(1+($B$10*1*$B$11)),IF($E$17=$U$3,$B$8*((1+$B$10)^1),IF($E$17=$U$4,$B$8*((1+$B$10)^(1*$B$11)),IF($E$17=$U$5,$B$8*((1+($B$10/$B$11))^(1*$B$11)),"Not Applicable")))) -> 0
A21: 2 | B21: =IF($B$17=$U$2,$B$8*(1+($B$10*2*$B$11)),IF($B$17=$U$3,$B$8*((1+$B$10)^2),IF($B$17=$U$4,$B$8*((1+$B$10)^(2*$B$11)),IF($B$17=$U$5,$B$8*((1+($B$10/$B$11))^(2*$B$11)),IF($B$17=$U$6,$B$8*EXP($B$10*2),"Not Applicable"))))) -> 0 | D21: 2 | E21: =IF($E$17=$U$2,$B$8*(1+($B$10*2*$B$11)),IF($E$17=$U$3,$B$8*((1+$B$10)^2),IF($E$17=$U$4,$B$8*((1+$B$10)^(2*$B$11)),IF($E$17=$U$5,$B$8*((1+($B$10/$B$11))^(2*$B$11)),"Not Applicable")))) -> 0
A22: 3 | B22: =IF($B$17=$U$2,$B$8*(1+($B$10*3*$B$11)),IF($B$17=$U$3,$B$8*((1+$B$10)^3),IF($B$17=$U$4,$B$8*((1+$B$10)^(3*$B$11)),IF($B$17=$U$5,$B$8*((1+($B$10/$B$11))^(3*$B$11)),IF($B$17=$U$6,$B$8*EXP($B$10*3),"Not Applicable"))))) -> 0 | D22: 3 | E22: =IF($E$17=$U$2,$B$8*(1+($B$10*3*$B$11)),IF($E$17=$U$3,$B$8*((1+$B$10)^3),IF($E$17=$U$4,$B$8*((1+$B$10)^(3*$B$11)),IF($E$17=$U$5,$B$8*((1+($B$10/$B$11))^(3*$B$11)),"Not Applicable")))) -> 0
A23: 4 | B23: =IF($B$17=$U$2,$B$8*(1+($B$10*4*$B$11)),IF($B$17=$U$3,$B$8*((1+$B$10)^4),IF($B$17=$U$4,$B$8*((1+$B$10)^(4*$B$11)),IF($B$17=$U$5,$B$8*((1+($B$10/$B$11))^(4*$B$11)),IF($B$17=$U$6,$B$8*EXP($B$10*4),"Not Applicable"))))) -> 0 | D23: 4 | E23: =IF($E$17=$U$2,$B$8*(1+($B$10*4*$B$11)),IF($E$17=$U$3,$B$8*((1+$B$10)^4),IF($E$17=$U$4,$B$8*((1+$B$10)^(4*$B$11)),IF($E$17=$U$5,$B$8*((1+($B$10/$B$11))^(4*$B$11)),"Not Applicable")))) -> 0
A24: 5 | B24: =IF($B$17=$U$2,$B$8*(1+($B$10*5*$B$11)),IF($B$17=$U$3,$B$8*((1+$B$10)^5),IF($B$17=$U$4,$B$8*((1+$B$10)^(5*$B$11)),IF($B$17=$U$5,$B$8*((1+($B$10/$B$11))^(5*$B$11)),IF($B$17=$U$6,$B$8*EXP($B$10*5),"Not Applicable"))))) -> 0 | D24: 5 | E24: =IF($E$17=$U$2,$B$8*(1+($B$10*5*$B$11)),IF($E$17=$U$3,$B$8*((1+$B$10)^5),IF($E$17=$U$4,$B$8*((1+$B$10)^(5*$B$11)),IF($E$17=$U$5,$B$8*((1+($B$10/$B$11))^(5*$B$11)),"Not Applicable")))) -> 0
A25: 6 | B25: =IF($B$17=$U$2,$B$8*(1+($B$10*6*$B$11)),IF($B$17=$U$3,$B$8*((1+$B$10)^6),IF($B$17=$U$4,$B$8*((1+$B$10)^(6*$B$11)),IF($B$17=$U$5,$B$8*((1+($B$10/$B$11))^(6*$B$11)),IF($B$17=$U$6,$B$8*EXP($B$10*6),"Not Applicable"))))) -> 0 | D25: 6 | E25: =IF($E$17=$U$2,$B$8*(1+($B$10*6*$B$11)),IF($E$17=$U$3,$B$8*((1+$B$10)^6),IF($E$17=$U$4,$B$8*((1+$B$10)^(6*$B$11)),IF($E$17=$U$5,$B$8*((1+($B$10/$B$11))^(6*$B$11)),"Not Applicable")))) -> 0
A26: 7 | B26: =IF($B$17=$U$2,$B$8*(1+($B$10*7*$B$11)),IF($B$17=$U$3,$B$8*((1+$B$10)^7),IF($B$17=$U$4,$B$8*((1+$B$10)^(7*$B$11)),IF($B$17=$U$5,$B$8*((1+($B$10/$B$11))^(7*$B$11)),IF($B$17=$U$6,$B$8*EXP($B$10*7),"Not Applicable"))))) -> 0 | D26: 7 | E26: =IF($E$17=$U$2,$B$8*(1+($B$10*7*$B$11)),IF($E$17=$U$3,$B$8*((1+$B$10)^7),IF($E$17=$U$4,$B$8*((1+$B$10)^(7*$B$11)),IF($E$17=$U$5,$B$8*((1+($B$10/$B$11))^(7*$B$11)),"Not Applicable")))) -> 0
A27: 8 | B27: =IF($B$17=$U$2,$B$8*(1+($B$10*8*$B$11)),IF($B$17=$U$3,$B$8*((1+$B$10)^8),IF($B$17=$U$4,$B$8*((1+$B$10)^(8*$B$11)),IF($B$17=$U$5,$B$8*((1+($B$10/$B$11))^(8*$B$11)),IF($B$17=$U$6,$B$8*EXP($B$10*8),"Not Applicable"))))) -> 0 | D27: 8 | E27: =IF($E$17=$U$2,$B$8*(1+($B$10*8*$B$11)),IF($E$17=$U$3,$B$8*((1+$B$10)^8),IF($E$17=$U$4,$B$8*((1+$B$10)^(8*$B$11)),IF($E$17=$U$5,$B$8*((1+($B$10/$B$11))^(8*$B$11)),"Not Applicable")))) -> 0

Sheet Assignment3 (Back End)
A1: Given
A2: Future Value | B2: ='Assignment3 (User Interface)'!B8 -> 6600
A3: Present Value | B3: ='Assignment3 (User Interface)'!B9 -> 600
A4: Annuity | B4: ='Assignment3 (User Interface)'!B10 -> 600
A5: Period | B5: ='Assignment3 (User Interface)'!B11 -> 2.5
A6: Years | B6: ='Assignment3 (User Interface)'!B13 -> 18.737851
A7: Interest | B7: ='Assignment3 (User Interface)'!B17 -> 0.05
D9: Givens
D10: Future Value in Arrears | E10: Present Value in Arrears | F10: Future Value in Advance | G10: Present Value in advance | H10: Given Future value and Present value | I10: Continuous Future | J10: Continuous Present
B11: Uknowns | C11: Future Value | D11: =($B$4)*(((1+$B$7)^($B$6*$B$5))-1)/$B$7 -> 105973.93 | E11: =($B$4)*(((1+$B$7)^($B$6*$B$5))-1)/$B$7 -> 105973.93 | F11: =($B$4*(1+$B$7)*(((1+$B$7)^($B$6*$B$5))-1))/$B$7 -> 111272.63 | G11: =($B$4*(1+$B$7)*(((1+$B$7)^($B$6*$B$5))-1))/$B$7 -> 111272.63 | H11: =$B$3*((1+$B$7)^($B$6*$B$5)) -> 5898.6966 | I11: =(B4*(EXP(B7*B6)-1))/B7 -> 18624.465
C12: Present Vaue | D12: =$B$4*(((1-(1+$B$7)^(-$B$5*$B$6)))/$B$7) -> 10779.391 | E12: =$B$4*(((1-(1+$B$7)^(-$B$5*$B$6)))/$B$7) -> 10779.391 | F12: =($B$4*(1+$B$7)*(1-((1+$B$7)^(-$B$6*$B$5))))/$B$7 -> 11318.361 | G12: =($B$4*(1+$B$7)*(1-((1+$B$7)^(-$B$6*$B$5))))/$B$7 -> 11318.361 | H12: =B2/((1+$B$7)^($B$6*$B$5)) -> 671.33475 | I12: =B4*(1-EXP(-B7*B6))/B7 -> 7297.877 | J12: =B3 -> 600
C13: Anuuity | D13: =B2/(((1+B7)^(B6*B5)-1)/B7) -> 37.36768 | E13: =B3/((1-(1+B7)^(-B6*B5))/B7) -> 33.397062 | F13: =$B$2/((((1+$B$7)*(((1+$B$7)^($B$6*$B$5))-1))/$B$7)) -> 35.588267 | G13: =$B$3/(((1+$B$7)*(1-((1+$B$7)^(-$B$5*$B$6))))/$B$7) -> 31.806726 | H13: =B3/((1-(1+B7)^(-B6*B5))/B7) -> 33.397062 | I13: =B2/((EXP(B7*B6)-1)/B7) -> 212.62356 | J13: =B3/((1-(EXP(-B7*B6)))/B7) -> 49.329415
C14: Years | D14: =LOG(((B7*B2)/B4)+1, 1+B7)/B5 -> 3.5929777 | E14: =-LOG10(1-(B3*B7)/B4)/(B5*LOG10(1+B7)) -> 0.4205216 | F14: =(LOG((($B$2*$B$7)/($B$4*(1+$B$7)))+1, 1+$B$7))/B5 -> 3.4532654 | G14: =(LOG((1-(($B$3*$B$7)/($B$4*(1+$B$7)))), 1+$B$7))/-$B$5 -> 0.4 | H14: =(LOG(($B$2/$B$3), 1+$B$7))/$B$5 -> 19.658842 | I14: =(1/B7)*(LN(((B2*B7)/B4)+1)) -> 8.7650986 | J14: =(-1/B7)*((LN(1-((B3*B7)/B4)))) -> 1.0258659
C15: Periods | D15: =LOG(((B7*B2)/B4)+1, 1+B7)/B6 -> 0.47937431 | E15: =LOG((1-((B3*B7)/B4)), (1+B7))/-B6 -> 0.056105901 | F15: =(LOG((($B$2*$B$7)/($B$4*(1+$B$7)))+1, 1+$B$7))/B6 -> 0.46073392 | G15: =(LOG((1-(($B$3*$B$7)/($B$4*(1+$B$7)))), 1+$B$7))/-$B$6 -> 0.053367914 | H15: =(LOG(($B$2/$B$3), 1+$B$7))/$B$6 -> 2.6228784 | I15: =(1/B7)*(LN(((B2*B7)/B4)+1)) -> 8.7650986 | J15: =(-1/B7)*((LN(1-((B3*B7)/B4)))) -> 1.0258659
C16: Interest | D16: =D21 -> 0.05 | E16: =H21 -> 0.05 | F16: =L21 -> 0.05 | G16: =P21 -> 0.05 | H16: =T21 -> 0.05 | I16: =X21 -> 0.05 | J16: =AB21 -> 0.05
A19: Future Value in Arrears | E19: Present Value in Arrears | I19: Future Value in Advance | M19: Present Value in advance | Q19: Given Future value and Present value | U19: Continuous Future Value | Y19: Continuous Present Value
A20: Difference | C20: Future Value | D20: Interest: | E20: Difference | G20: Present Value | H20: Interest: | I20: Difference | K20: Future Value | L20: Interest: | M20: Difference | O20: Present Value | P20: Interest: | Q20: Difference | S20: FV | T20: Interest: | U20: Difference | W20: FV | X20: Interest: | Y20: Difference | AA20: PV | AB20: Interest:
A21: =ABS($D$11-C21) -> 77213.147 | B21: 0.001 | C21: =($B$4)*(((1+B21)^($B$6*$B$5))-1)/B21 -> 28760.786 | D21: =VLOOKUP(D23, A21:B1020,2,FALSE) -> 0.05 | E21: =ABS($E$12-G21) -> 16665.818 | F21: 0.001 | G21: =$B$4*(((1-(1+F21)^(-$B$5*$B$6)))/F21) -> 27445.209 | H21: =VLOOKUP(H23,E21:F1020, 2, FALSE) -> 0.05 | I21: =ABS($F$11-K21) -> 82483.083 | J21: 0.001 | K21: =($B$4*(1+J21)*(((1+J21)^($B$6*$B$5))-1))/J21 -> 28789.546 | L21: =VLOOKUP(L23, I21:J1020, 2, FALSE) -> 0.05 | M21: =ABS($G$12-O21) -> 16154.294 | N21: 0.001 | O21: =($B$4*(1+N21)*(1-((1+N21)^(-$B$6*$B$5))))/N21 -> 27472.655 | P21: =VLOOKUP(P23, M21:N1020, 2, FALSE) -> 0.05 | Q21: =ABS($H$11-S21) -> 5269.9358 | R21: 0.001 | S21: =$B$3*((1+R21)^($B$6*$B$5)) -> 628.76079 | T21: =VLOOKUP(T23, Q21:R1020, 2, FALSE) -> 0.05 | U21: =ABS($I$11-W21) -> 7275.7611 | V21: 0.001 | W21: =($B$4*(EXP(V21*$B$6)-1))/V21 -> 11348.704 | X21: =VLOOKUP(X23, U21:V1020, 2, FALSE) -> 0.05 | Y21: =ABS($I$12-AA21) -> 3840.1562 | Z21: 0.001 | AA21: =$B$4*(1-EXP(-Z21*$B$6))/Z21 -> 11138.033 | AB21: =VLOOKUP(AB23, Y21:Z1020, 2, FALSE) -> 0.05
A22: =ABS($D$11-C22) -> 76539.23 | B22: 0.002 | C22: =($B$4)*(((1+B22)^($B$6*$B$5))-1)/B22 -> 29434.703 | D22: Minimum: | E22: =ABS($E$12-G22) -> 16025.347 | F22: 0.002 | G22: =$B$4*(((1-(1+F22)^(-$B$5*$B$6)))/F22) -> 26804.738 | H22: Minimum: | I22: =ABS($F$11-K22) -> 81779.057 | J22: 0.002 | K22: =($B$4*(1+J22)*(((1+J22)^($B$6*$B$5))-1))/J22 -> 29493.572 | L22: Minimum: | M22: =ABS($G$12-O22) -> 15539.986 | N22: 0.002 | O22: =($B$4*(1+N22)*(1-((1+N22)^(-$B$6*$B$5))))/N22 -> 26858.347 | P22: Minimum: | Q22: =ABS($H$11-S22) -> 5239.8272 | R22: 0.002 | S22: =$B$3*((1+R22)^($B$6*$B$5)) -> 658.86941 | T22: Minimum: | U22: =ABS($I$11-W22) -> 7168.4335 | V22: 0.002 | W22: =($B$4*(EXP(V22*$B$6)-1))/V22 -> 11456.031 | X22: Minimum: | Y22: =ABS($I$12-AA22) -> 3736.7764 | Z22: 0.002 | AA22: =$B$4*(1-EXP(-Z22*$B$6))/Z22 -> 11034.653 | AB22: Minimum:
A23: =ABS($D$11-C23) -> 75844.738 | B23: 0.003 | C23: =($B$4)*(((1+B23)^($B$6*$B$5))-1)/B23 -> 30129.195 | D23: =MIN(A21:A1020) -> 0 | E23: =ABS($E$12-G23) -> 15405.2 | F23: 0.003 | G23: =$B$4*(((1-(1+F23)^(-$B$5*$B$6)))/F23) -> 26184.591 | H23: =MIN(E21:E1020) -> 0 | I23: =ABS($F$11-K23) -> 81053.047 | J23: 0.003 | K23: =($B$4*(1+J23)*(((1+J23)^($B$6*$B$5))-1))/J23 -> 30219.582 | L23: =MIN(I21:I1020) -> 0 | M23: =ABS($G$12-O23) -> 14944.784 | N23: 0.003 | O23: =($B$4*(1+N23)*(1-((1+N23)^(-$B$6*$B$5))))/N23 -> 26263.145 | P23: =MIN(M21:M1020) -> 0 | Q23: =ABS($H$11-S23) -> 5208.309 | R23: 0.003 | S23: =$B$3*((1+R23)^($B$6*$B$5)) -> 690.38758 | T23: =MIN(Q21:Q1020) -> 0 | U23: =ABS($I$11-W23) -> 7059.7526 | V23: 0.003 | W23: =($B$4*(EXP(V23*$B$6)-1))/V23 -> 11564.712 | X23: =MIN(U21:U1020) -> 0 | Y23: =ABS($I$12-AA23) -> 3634.6759 | Z23: 0.003 | AA23: =$B$4*(1-EXP(-Z23*$B$6))/Z23 -> 10932.553 | AB23: =MIN(Y21:Y1020) -> 0
A24: =ABS($D$11-C24) -> 75128.981 | B24: 0.004 | C24: =($B$4)*(((1+B24)^($B$6*$B$5))-1)/B24 -> 30844.951 | E24: =ABS($E$12-G24) -> 14804.639 | F24: 0.004 | G24: =$B$4*(((1-(1+F24)^(-$B$5*$B$6)))/F24) -> 25584.03 | I24: =ABS($F$11-K24) -> 80304.298 | J24: 0.004 | K24: =($B$4*(1+J24)*(((1+J24)^($B$6*$B$5))-1))/J24 -> 30968.331 | M24: =ABS($G$12-O24) -> 14368.005 | N24: 0.004 | O24: =($B$4*(1+N24)*(1-((1+N24)^(-$B$6*$B$5))))/N24 -> 25686.366 | Q24: =ABS($H$11-S24) -> 5175.3168 | R24: 0.004 | S24: =$B$3*((1+R24)^($B$6*$B$5)) -> 723.37981 | U24: =ABS($I$11-W24) -> 6949.6991 | V24: 0.004 | W24: =($B$4*(EXP(V24*$B$6)-1))/V24 -> 11674.766 | Y24: =ABS($I$12-AA24) -> 3533.8371 | Z24: 0.004 | AA24: =$B$4*(1-EXP(-Z24*$B$6))/Z24 -> 10831.714
A25: =ABS($D$11-C25) -> 74391.246 | B25: 0.005 | C25: =($B$4)*(((1+B25)^($B$6*$B$5))-1)/B25 -> 31582.687 | E25: =ABS($E$12-G25) -> 14222.952 | F25: 0.005 | G25: =$B$4*(((1-(1+F25)^(-$B$5*$B$6)))/F25) -> 25002.344 | I25: =ABS($F$11-K25) -> 79532.029 | J25: 0.005 | K25: =($B$4*(1+J25)*(((1+J25)^($B$6*$B$5))-1))/J25 -> 31740.6 | M25: =ABS($G$12-O25) -> 13808.994 | N25: 0.005 | O25: =($B$4*(1+N25)*(1-((1+N25)^(-$B$6*$B$5))))/N25 -> 25127.355 | Q25: =ABS($H$11-S25) -> 5140.7832 | R25: 0.005 | S25: =$B$3*((1+R25)^($B$6*$B$5)) -> 757.91343 | U25: =ABS($I$11-W25) -> 6838.2536 | V25: 0.005 | W25: =($B$4*(EXP(V25*$B$6)-1))/V25 -> 11786.211 | Y25: =ABS($I$12-AA25) -> 3434.2422 | Z25: 0.005 | AA25: =$B$4*(1-EXP(-Z25*$B$6))/Z25 -> 10732.119
A26: =ABS($D$11-C26) -> 73630.792 | B26: 0.006 | C26: =($B$4)*(((1+B26)^($B$6*$B$5))-1)/B26 -> 32343.141 | E26: =ABS($E$12-G26) -> 13659.458 | F26: 0.006 | G26: =$B$4*(((1-(1+F26)^(-$B$5*$B$6)))/F26) -> 24438.849 | I26: =ABS($F$11-K26) -> 78735.429 | J26: 0.006 | K26: =($B$4*(1+J26)*(((1+J26)^($B$6*$B$5))-1))/J26 -> 32537.2 | M26: =ABS($G$12-O26) -> 13267.122 | N26: 0.006 | O26: =($B$4*(1+N26)*(1-((1+N26)^(-$B$6*$B$5))))/N26 -> 24585.483 | Q26: =ABS($H$11-S26) -> 5104.6378 | R26: 0.006 | S26: =$B$3*((1+R26)^($B$6*$B$5)) -> 794.05885 | U26: =ABS($I$11-W26) -> 6725.3962 | V26: 0.006 | W26: =($B$4*(EXP(V26*$B$6)-1))/V26 -> 11899.068 | Y26: =ABS($I$12-AA26) -> 3335.8742 | Z26: 0.006 | AA26: =$B$4*(1-EXP(-Z26*$B$6))/Z26 -> 10633.751
A27: =ABS($D$11-C27) -> 72846.854 | B27: 0.007 | C27: =($B$4)*(((1+B27)^($B$6*$B$5))-1)/B27 -> 33127.078 | E27: =ABS($E$12-G27) -> 13113.501 | F27: 0.007 | G27: =$B$4*(((1-(1+F27)^(-$B$5*$B$6)))/F27) -> 23892.892 | I27: =ABS($F$11-K27) -> 77913.661 | J27: 0.007 | K27: =($B$4*(1+J27)*(((1+J27)^($B$6*$B$5))-1))/J27 -> 33358.968 | M27: =ABS($G$12-O27) -> 12741.781 | N27: 0.007 | O27: =($B$4*(1+N27)*(1-((1+N27)^(-$B$6*$B$5))))/N27 -> 24060.142 | Q27: =ABS($H$11-S27) -> 5066.8071 | R27: 0.007 | S27: =$B$3*((1+R27)^($B$6*$B$5)) -> 831.88955 | U27: =ABS($I$11-W27) -> 6611.1069 | V27: 0.007 | W27: =($B$4*(EXP(V27*$B$6)-1))/V27 -> 12013.358 | Y27: =ABS($I$12-AA27) -> 3238.7158 | Z27: 0.007 | AA27: =$B$4*(1-EXP(-Z27*$B$6))/Z27 -> 10536.593
A28: =ABS($D$11-C28) -> 72038.641 | B28: 0.008 | C28: =($B$4)*(((1+B28)^($B$6*$B$5))-1)/B28 -> 33935.291 | E28: =ABS($E$12-G28) -> 12584.45 | F28: 0.008 | G28: =$B$4*(((1-(1+F28)^(-$B$5*$B$6)))/F28) -> 23363.841 | I28: =ABS($F$11-K28) -> 77065.856 | J28: 0.008 | K28: =($B$4*(1+J28)*(((1+J28)^($B$6*$B$5))-1))/J28 -> 34206.774 | M28: =ABS($G$12-O28) -> 12232.391 | N28: 0.008 | O28: =($B$4*(1+N28)*(1-((1+N28)^(-$B$6*$B$5))))/N28 -> 23550.752 | Q28: =ABS($H$11-S28) -> 5027.2143 | R28: 0.008 | S28: =$B$3*((1+R28)^($B$6*$B$5)) -> 871.48233 | U28: =ABS($I$11-W28) -> 6495.3653 | V28: 0.008 | W28: =($B$4*(EXP(V28*$B$6)-1))/V28 -> 12129.099 | Y28: =ABS($I$12-AA28) -> 3142.7503 | Z28: 0.008 | AA28: =$B$4*(1-EXP(-Z28*$B$6))/Z28 -> 10440.627
A29: =ABS($D$11-C29) -> 71205.333 | B29: 0.009 | C29: =($B$4)*(((1+B29)^($B$6*$B$5))-1)/B29 -> 34768.599 | E29: =ABS($E$12-G29) -> 12071.701 | F29: 0.009 | G29: =$B$4*(((1-(1+F29)^(-$B$5*$B$6)))/F29) -> 22851.092 | I29: =ABS($F$11-K29) -> 76191.113 | J29: 0.009 | K29: =($B$4*(1+J29)*(((1+J29)^($B$6*$B$5))-1))/J29 -> 35081.517 | M29: =ABS($G$12-O29) -> 11738.391 | N29: 0.009 | O29: =($B$4*(1+N29)*(1-((1+N29)^(-$B$6*$B$5))))/N29 -> 23056.752 | Q29: =ABS($H$11-S29) -> 4985.7792 | R29: 0.009 | S29: =$B$3*((1+R29)^($B$6*$B$5)) -> 912.91739 | U29: =ABS($I$11-W29) -> 6378.1507 | V29: 0.009 | W29: =($B$4*(EXP(V29*$B$6)-1))/V29 -> 12246.314 | Y29: =ABS($I$12-AA29) -> 3047.9613 | Z29: 0.009 | AA29: =$B$4*(1-EXP(-Z29*$B$6))/Z29 -> 10345.838
A30: =ABS($D$11-C30) -> 70346.082 | B30: 0.01 | C30: =($B$4)*(((1+B30)^($B$6*$B$5))-1)/B30 -> 35627.85 | E30: =ABS($E$12-G30) -> 11574.672 | F30: 0.01 | G30: =$B$4*(((1-(1+F30)^(-$B$5*$B$6)))/F30) -> 22354.063 | I30: =ABS($F$11-K30) -> 75288.5 | J30: 0.01 | K30: =($B$4*(1+J30)*(((1+J30)^($B$6*$B$5))-1))/J30 -> 35984.129 | M30: =ABS($G$12-O30) -> 11259.243 | N30: 0.01 | O30: =($B$4*(1+N30)*(1-((1+N30)^(-$B$6*$B$5))))/N30 -> 22577.604 | Q30: =ABS($H$11-S30) -> 4942.4181 | R30: 0.01 | S30: =$B$3*((1+R30)^($B$6*$B$5)) -> 956.2785 | U30: =ABS($I$11-W30) -> 6259.442 | V30: 0.01 | W30: =($B$4*(EXP(V30*$B$6)-1))/V30 -> 12365.023 | Y30: =ABS($I$12-AA30) -> 2954.3323 | Z30: 0.01 | AA30: =$B$4*(1-EXP(-Z30*$B$6))/Z30 -> 10252.209
A31: =ABS($D$11-C31) -> 69460.01 | B31: 0.011 | C31: =($B$4)*(((1+B31)^($B$6*$B$5))-1)/B31 -> 36513.923 | E31: =ABS($E$12-G31) -> 11092.804 | F31: 0.011 | G31: =$B$4*(((1-(1+F31)^(-$B$5*$B$6)))/F31) -> 21872.196 | I31: =ABS($F$11-K31) -> 74357.053 | J31: 0.011 | K31: =($B$4*(1+J31)*(((1+J31)^($B$6*$B$5))-1))/J31 -> 36915.576 | M31: =ABS($G$12-O31) -> 10794.429 | N31: 0.011 | O31: =($B$4*(1+N31)*(1-((1+N31)^(-$B$6*$B$5))))/N31 -> 22112.79 | Q31: =ABS($H$11-S31) -> 4897.0435 | R31: 0.011 | S31: =$B$3*((1+R31)^($B$6*$B$5)) -> 1001.6532 | U31: =ABS($I$11-W31) -> 6139.218 | V31: 0.011 | W31: =($B$4*(EXP(V31*$B$6)-1))/V31 -> 12485.247 | Y31: =ABS($I$12-AA31) -> 2861.8474 | Z31: 0.011 | AA31: =$B$4*(1-EXP(-Z31*$B$6))/Z31 -> 10159.724
A32: =ABS($D$11-C32) -> 68546.207 | B32: 0.012 | C32: =($B$4)*(((1+B32)^($B$6*$B$5))-1)/B32 -> 37427.726 | E32: =ABS($E$12-G32) -> 10625.561 | F32: 0.012 | G32: =$B$4*(((1-(1+F32)^(-$B$5*$B$6)))/F32) -> 21404.952 | I32: =ABS($F$11-K32) -> 73395.771 | J32: 0.012 | K32: =($B$4*(1+J32)*(((1+J32)^($B$6*$B$5))-1))/J32 -> 37876.858 | M32: =ABS($G$12-O32) -> 10343.451 | N32: 0.012 | O32: =($B$4*(1+N32)*(1-((1+N32)^(-$B$6*$B$5))))/N32 -> 21661.812 | Q32: =ABS($H$11-S32) -> 4849.5639 | R32: 0.012 | S32: =$B$3*((1+R32)^($B$6*$B$5)) -> 1049.1327 | U32: =ABS($I$11-W32) -> 6017.4571 | V32: 0.012 | W32: =($B$4*(EXP(V32*$B$6)-1))/V32 -> 12607.008 | Y32: =ABS($I$12-AA32) -> 2770.4908 | Z32: 0.012 | AA32: =$B$4*(1-EXP(-Z32*$B$6))/Z32 -> 10068.368
A33: =ABS($D$11-C33) -> 67603.734 | B33: 0.013 | C33: =($B$4)*(((1+B33)^($B$6*$B$5))-1)/B33 -> 38370.199 | E33: =ABS($E$12-G33) -> 10172.425 | F33: 0.013 | G33: =$B$4*(((1-(1+F33)^(-$B$5*$B$6)))/F33) -> 20951.816 | I33: =ABS($F$11-K33) -> 72403.618 | J33: 0.013 | K33: =($B$4*(1+J33)*(((1+J33)^($B$6*$B$5))-1))/J33 -> 38869.012 | M33: =ABS($G$12-O33) -> 9905.8289 | N33: 0.013 | O33: =($B$4*(1+N33)*(1-((1+N33)^(-$B$6*$B$5))))/N33 -> 21224.19 | Q33: =ABS($H$11-S33) -> 4799.884 | R33: 0.013 | S33: =$B$3*((1+R33)^($B$6*$B$5)) -> 1098.8126 | U33: =ABS($I$11-W33) -> 5894.1371 | V33: 0.013 | W33: =($B$4*(EXP(V33*$B$6)-1))/V33 -> 12730.328 | Y33: =ABS($I$12-AA33) -> 2680.2469 | Z33: 0.013 | AA33: =$B$4*(1-EXP(-Z33*$B$6))/Z33 -> 9978.1239
A34: =ABS($D$11-C34) -> 66631.616 | B34: 0.014 | C34: =($B$4)*(((1+B34)^($B$6*$B$5))-1)/B34 -> 39342.317 | E34: =ABS($E$12-G34) -> 9732.9004 | F34: 0.014 | G34: =$B$4*(((1-(1+F34)^(-$B$5*$B$6)))/F34) -> 20512.292 | I34: =ABS($F$11-K34) -> 71379.52 | J34: 0.014 | K34: =($B$4*(1+J34)*(((1+J34)^($B$6*$B$5))-1))/J34 -> 39893.11 | M34: =ABS($G$12-O34) -> 9481.1029 | N34: 0.014 | O34: =($B$4*(1+N34)*(1-((1+N34)^(-$B$6*$B$5))))/N34 -> 20799.464 | Q34: =ABS($H$11-S34) -> 4747.9042 | R34: 0.014 | S34: =$B$3*((1+R34)^($B$6*$B$5)) -> 1150.7924 | U34: =ABS($I$11-W34) -> 5769.2358 | V34: 0.014 | W34: =($B$4*(EXP(V34*$B$6)-1))/V34 -> 12855.229 | Y34: =ABS($I$12-AA34) -> 2591.1003 | Z34: 0.014 | AA34: =$B$4*(1-EXP(-Z34*$B$6))/Z34 -> 9888.9773
A35: =ABS($D$11-C35) -> 65628.845 | B35: 0.015 | C35: =($B$4)*(((1+B35)^($B$6*$B$5))-1)/B35 -> 40345.088 | E35: =ABS($E$12-G35) -> 9306.51 | F35: 0.015 | G35: =$B$4*(((1-(1+F35)^(-$B$5*$B$6)))/F35) -> 20085.901 | I35: =ABS($F$11-K35) -> 70322.365 | J35: 0.015 | K35: =($B$4*(1+J35)*(((1+J35)^($B$6*$B$5))-1))/J35 -> 40950.264 | M35: =ABS($G$12-O35) -> 9068.8289 | N35: 0.015 | O35: =($B$4*(1+N35)*(1-((1+N35)^(-$B$6*$B$5))))/N35 -> 20387.19 | Q35: =ABS($H$11-S35) -> 4693.5203 | R35: 0.015 | S35: =$B$3*((1+R35)^($B$6*$B$5)) -> 1205.1763 | U35: =ABS($I$11-W35) -> 5642.7305 | V35: 0.015 | W35: =($B$4*(EXP(V35*$B$6)-1))/V35 -> 12981.734 | Y35: =ABS($I$12-AA35) -> 2503.036 | Z35: 0.015 | AA35: =$B$4*(1-EXP(-Z35*$B$6))/Z35 -> 9800.913
... A1020: =ABS($D$11-C1020) -> 7.5820929e+16 | B1020: 1 | C1020: =($B$4)*(((1+B1020)^($B$6*$B$5))-1)/B1020 -> 7.5820929e+16 | E1020: =ABS($E$12-G1020) -> 10179.391 | F1020: 1 | G1020: =$B$4*(((1-(1+F1020)^(-$B$5*$B$6)))/F1020) -> 600 | I1020: =ABS($F$11-K1020) -> 1.5164186e+17 | J1020: 1 | K1020: =($B$4*(1+J1020)*(((1+J1020)^($B$6*$B$5))-1))/J1020 -> 1.5164186e+17 | M1020: =ABS($G$12-O1020) -> 10118.361 | N1020: 1 | O1020: =($B$4*(1+N1020)*(1-((1+N1020)^(-$B$6*$B$5))))/N1020 -> 1200 | Q1020: =ABS($H$11-S1020) -> 7.5820929e+16 | R1020: 1 | S1020: =$B$3*((1+R1020)^($B$6*$B$5)) -> 7.5820929e+16 | U1020: =ABS($I$11-W1020) -> 8.2394144e+10 | V1020: 1 | W1020: =($B$4*(EXP(V1020*$B$6)-1))/V1020 -> 8.2394163e+10 | Y1020: =ABS($I$12-AA1020) -> 6697.877 | Z1020: 1 | AA1020: =$B$4*(1-EXP(-Z1020*$B$6))/Z1020 -> 600

Sheet Assignment3 (User Interface)
A1: ANNUITIES CALCULATOR | R1: Exact Year | S1: Future Value in Arrears | T1: Future Value
A2: Given: | B2: Continuous Future (normal) | I2: Requested Value: | J2: Future Value | R2: Dates | S2: Present Value in Arrears | T2: Present Value
S3: Future Value in Advance | T3: Annuity
I4: Value: | J4: =IF(AND(B2=S1,J2=T1),'Assignment3 (Back End)'!D11,IF(AND(B2=S1,J2=T2),'Assignment3 (Back End)'!D12,IF(AND(B2=S1,J2=T3),'Assignment3 (Back End)'!D13,IF(AND(B2=S1,J2=T4),'Assignment3 (Back End)'!D15,IF(AND(B2=S1,J2=T5),'Assignment3 (Back End)'!D14,IF(AND(B2=S1,J2=T6),TEXT('Assignment3 (Back End)'!D16,"0.0000%"),IF(AND(B2=S2,J2=T1),'Assignment3 (Back End)'!E11,IF(AND(B2=S2,J2=T2),'Assignment3 (Back End)'!E12,IF(AND(B2=S2,J2=T3),'Assignment3 (Back End)'!E13,IF(AND(B2=S2,J2=T4),'Assignment3 (Back End)'!E15,IF(AND(B2=S2,J2=T5),'Assignment3 (Back End)'!E14,IF(AND(B2=S2,J2=T6),TEXT('Assignment3 (Back End)'!E16,"0.0000%"),IF(AND(B2=S3,J2=T1),'Assignment3 (Back End)'!F11,IF(AND(B2=S3,J2=T2),'Assignment3 (Back End)'!F12,IF(AND(B2=S3,J2=T3),'Assignment3 (Back End)'!F13,IF(AND(B2=S3,J2=T4),'Assignment3 (Back End)'!F15,IF(AND(B2=S3,J2=T5),'Assignment3 (Back End)'!F14,IF(AND(B2=S3,J2=T6),TEXT('Assignment3 (Back End)'!F16,"0.0000%"),IF(AND(B2=S4,J2=T1),'Assignment3 (Back End)'!G11,IF(AND(B2=S4,J2=T2),'Assignment3 (Back End)'!G12,IF(AND(B2=S4,J2=T3),'Assignment3 (Back End)'!G13,IF(AND(B2=S4,J2=T4),'Assignment3 (Back End)'!G15,IF(AND(B2=S4,J2=T5),'Assignment3 (Back End)'!G14,IF(AND(B2=S4,J2=T6),TEXT('Assignment3 (Back End)'!G16,"0.0000%"),IF(AND(B2=S5,J2=T1),'Assignment3 (Back End)'!H11,IF(AND(B2=S5,J2=T2),'Assignment3 (Back End)'!H12,IF(AND(B2=S5,J2=T4),'Assignment3 (Back End)'!H15,IF(AND(B2=S5,J2=T5),'Assignment3 (Back End)'!H14,IF(AND(B2=S5,J2=T6),TEXT('Assignment3 (Back End)'!H16,"0.0000%"),IF(AND(B2=S6,J2=T1),'Assignment3 (Back End)'!I11,IF(AND(B2=S6,J2=T2),'Assignment3 (Back End)'!I12,IF(AND(B2=S6,J2=T3),'Assignment3 (Back End)'!I13,IF(AND(B2=S6,J2=T4),'Assignment3 (Back End)'!I15,IF(AND(B2=S6,J2=T5),'Assignment3 (Back End)'!I14,IF(AND(B2=S6,J2=T6),TEXT('Assignment3 (Back End)'!I16,"0.0000%"),IF(AND(B2=S7,J2=T1),'Assignment3 (Back End)'!I11,IF(AND(B2=S7,J2=T2),'Assignment3 (Back End)'!J12,IF(AND(B2=S7,J2=T3),'Assignment3 (Back End)'!J13,IF(AND(B2=S7,J2=T4),'Assignment3 (Back End)'!J15,IF(AND(B2=S7,J2=T5),'Assignment3 (Back End)'!J14,IF(AND(B2=S7,J2=T6),TEXT('Assignment3 (Back End)'!J16,"0.0000%"),"More work to b edone"))))))))))))))))))))))))))))))))))))))))) -> 18624.465 | S4: Present Value in advance | T4: Period
S5: Given Future value and Present value | T5: Years
I6: Real Future Value | J6: =IF(J2=T1, J4*(1+5%)^(-'Assignment3 (Back End)'!B6), " ") -> 7465.2073 | S6: Continuous Future (normal) | T6: Interest
A7: Given Values: | S7: Continuous Present
A8: Future Value | B8: 6600
A9: Present Value | B9: 600 | I9: To Convert Interest Rates:
A10: Annuity | B10: 600
A11: Period | B11: 2.5 | I11: For Single invetments
A12: Years By: | B12: Dates
A13: Years: | B13: =IF(B12=R1,D14,IF(B12=R2,B14)) -> 18.737851 | I13: Home
A14: Dates (yyyy/mm/dd): | B14: =(B16 - B15)/ 365.25 -> 18.737851 | C14: Exact Date: | D14: 3
A15: Start: | B15: 37327
A16: End: | B16: 44171
A17: Interest | B17: 0.05
A19: ANNUITY GRAPHS
AH20: Arrears Annuity
A21: Annuity Type: | B21: Arears Annuity | I21: Annuity Type: | J21: Advance Annuity | AH21: Continuous
A23: Periods(Years) | B23: Arrears Annuity | I23: Periods(Years) | J23: =J21 -> Advance Annuity
A24: 1 | B24: =($B$10)*(((1+$B$17)^(A24))-1)/$B$17 -> 600 | I24: 1 | J24: =($B$10*(1+$B$17)*(((1+$B$17)^(I24))-1))/$B$17 -> 630
A25: 2 | B25: =($B$10)*(((1+$B$17)^(A25))-1)/$B$17 -> 1230 | I25: 2 | J25: =($B$10*(1+$B$17)*(((1+$B$17)^(I25))-1))/$B$17 -> 1291.5
A26: 3 | B26: =($B$10)*(((1+$B$17)^(A26))-1)/$B$17 -> 1891.5 | I26: 3 | J26: =($B$10*(1+$B$17)*(((1+$B$17)^(I26))-1))/$B$17 -> 1986.075
A27: 4 | B27: =($B$10)*(((1+$B$17)^(A27))-1)/$B$17 -> 2586.075 | I27: 4 | J27: =($B$10*(1+$B$17)*(((1+$B$17)^(I27))-1))/$B$17 -> 2715.3787
A28: 5 | B28: =($B$10)*(((1+$B$17)^(A28))-1)/$B$17 -> 3315.3788 | I28: 5 | J28: =($B$10*(1+$B$17)*(((1+$B$17)^(I28))-1))/$B$17 -> 3481.1477
A29: 6 | B29: =($B$10)*(((1+$B$17)^(A29))-1)/$B$17 -> 4081.1477 | I29: 6 | J29: =($B$10*(1+$B$17)*(((1+$B$17)^(I29))-1))/$B$17 -> 4285.2051
A30: 7 | B30: =($B$10)*(((1+$B$17)^(A30))-1)/$B$17 -> 4885.2051 | I30: 7 | J30: =($B$10*(1+$B$17)*(((1+$B$17)^(I30))-1))/$B$17 -> 5129.4653
A31: 8 | B31: =($B$10)*(((1+$B$17)^(A31))-1)/$B$17 -> 5729.4653 | I31: 8 | J31: =($B$10*(1+$B$17)*(((1+$B$17)^(I31))-1))/$B$17 -> 6015.9386
A32: 9 | B32: =($B$10)*(((1+$B$17)^(A32))-1)/$B$17 -> 6615.9386 | I32: 9 | J32: =($B$10*(1+$B$17)*(((1+$B$17)^(I32))-1))/$B$17 -> 6946.7355
A33: 10 | B33: =($B$10)*(((1+$B$17)^(A33))-1)/$B$17 -> 7546.7355 | I33: 10 | J33: =($B$10*(1+$B$17)*(((1+$B$17)^(I33))-1))/$B$17 -> 7924.0723

Sheet Assignment4 (Back End)
A1: Givens
A2: Loan Amount | B2: ='Assignment4 (User Interface)'!B4 -> 70000
A3: Payment | B3: ='Assignment4 (User Interface)'!B5 -> 3950.1909
A4: Years | B4: ='Assignment4 (User Interface)'!B6 -> 9.5
A5: Periods per year | B5: ='Assignment4 (User Interface)'!B7 -> 2
A6: Effective Periodic or nominal interest rate | B6: ='Assignment4 (User Interface)'!B8 -> 0.0016515813 | G6: Arrears | H6: Advance
A7: Specific time (Year) | B7: ='Assignment4 (User Interface)'!B9*B5 -> 10 | F7: Loan amount | G7: =($B$3*(1-((1+$B$6)^(-$B$4*$B$5))))/$B$6 -> 73828.258 | H7: =(($B$3*(1+$B$6))*(1-((1+$B$6)^(-$B$4*$B$5))))/$B$6 -> 73950.191
A8: Pecific year in periods | B8: ='Assignment4 (User Interface)'!B10 -> 12 | F8: Payment | G8: =$B$2/((1-((1+$B$6)^(-$B$4*$B$5)))/$B$6) -> 3745.3595 | H8: =$B$2*(1+B6)/((1-((1+$B$6)^(-$B$4*$B$5)))/$B$6) -> 3751.5453
A9: Number of Payment (K) | B9: ='Assignment4 (User Interface)'!B11 -> 1 | F9: Period to repay | G9: =-LN(1-($B$2*$B$6)/$B$3)/LN(1+$B$6) -> 18 | H9: =-LN(1-($B$2*$B$6)/$B$3*(1+B6))/LN(1+$B$6) -> 18.030175
A10: Start Period (Interest/capital) | B10: ='Assignment4 (User Interface)'!B12 -> 1 | F10: Balance at specific time of the year | G10: =VLOOKUP(IF(B7=0, B8,B7),'Assignment4 (User Interface)'!A21:H532,6,FALSE) -> 31367.948 | H10: =VLOOKUP(IF(B7=0, B8,B7),'Assignment4 (User Interface)'!L21:T761,7,FALSE) -> 31302.221
A11: End Period (Interest/Capital) | B11: ='Assignment4 (User Interface)'!B13 -> 2 | F11: Interest component of payment k | G11: =VLOOKUP(B8,'Assignment4 (User Interface)'!A21:H1050,3,FALSE) -> 45.368219 | H11: =VLOOKUP(IF(B7=0, B8,B7), 'Assignment4 (User Interface)'!L21:T761,5,FALSE) -> 58.041121
F12: Capital component of payment k | G12: =VLOOKUP(IF(B7=0, B8,B7), 'Assignment4 (User Interface)'!A21:H891,5,FALSE) -> 3891.9563 | H12: =VLOOKUP(IF(B7=0, B8,B7), 'Assignment4 (User Interface)'!L21:T667,6,FALSE) -> 3892.1498
F13: Interest from payment X1 to X2 | G13: =SUM(INDEX('Assignment4 (User Interface)'!C22:C700, MATCH( 'Assignment4 (Back End)'!B10, 'Assignment4 (User Interface)'!A22:A607, 0)) : INDEX('Assignment4 (User Interface)'!C22:C607, MATCH('Assignment4 (Back End)'!B11, 'Assignment4 (User Interface)'!A22:A607, 0))) -> 224.88826 | H13: =SUM(INDEX('Assignment4 (User Interface)'!P22:P700, MATCH( 'Assignment4 (Back End)'!B10, 'Assignment4 (User Interface)'!L22:L607, 0)) : INDEX('Assignment4 (User Interface)'!P22:P607, MATCH('Assignment4 (Back End)'!B11, 'Assignment4 (User Interface)'!L22:L607, 0))) -> 109.08663
F14: Capital from payment X1 to X2 | G14: =SUM(INDEX('Assignment4 (User Interface)'!E22:E700, MATCH( 'Assignment4 (Back End)'!B10, 'Assignment4 (User Interface)'!A22:A607, 0)) : INDEX('Assignment4 (User Interface)'!E22:E607, MATCH('Assignment4 (Back End)'!B11, 'Assignment4 (User Interface)'!A22:A607, 0))) -> 7675.4936 | H14: =SUM(INDEX('Assignment4 (User Interface)'!Q22:Q700, MATCH( 'Assignment4 (Back End)'!B10, 'Assignment4 (User Interface)'!L22:L607, 0)) : INDEX('Assignment4 (User Interface)'!Q22:Q607, MATCH('Assignment4 (Back End)'!B11, 'Assignment4 (User Interface)'!L22:L607, 0))) -> 7791.2952
F15: Last payment | G15: =VLOOKUP(B4*B5, 'Assignment4 (User Interface)'!A22:H961,2,FALSE)*(1+B6) -> -8.1716414e-10 | H15: =VLOOKUP(B4*B5, 'Assignment4 (User Interface)'!L21:T767,4,FALSE) -> -4069.2872
F16: Total Interest | G16: {=LOOKUP(2, 1/('Assignment4 (User Interface)'!G22:G607), 'Assignment4 (User Interface)'!G22:G607)} -> 1103.4367 | H16: {=LOOKUP(2, 1/('Assignment4 (User Interface)'!S22:S607), 'Assignment4 (User Interface)'!S22:S607)} -> 984.34044
F17: Total Capital | G17: {=LOOKUP(2, 1/('Assignment4 (User Interface)'!H22:H607), 'Assignment4 (User Interface)'!H22:H607)} -> 73950.191 | H17: {=LOOKUP(2, 1/('Assignment4 (User Interface)'!T22:T607), 'Assignment4 (User Interface)'!T22:T607)} -> 74069.287

Sheet Assignment4 (User Interface)
A1: LOANS / WITHDRAWALS | M1: Comparison Graphs
AD2: Loan amount | AE2: Arrears
A3: Givens | E3: Unkowns | AD3: Payment | AE3: Advance
A4: Loan Amount | B4: 70000 | E4: Loan Type: | F4: Arrears | H4: Loan component(Variable): | I4: Period to repay | AD4: Period to repay
A5: Payment | B5: 3950.1909 | AD5: Balance at specific time of the year
A6: Years | B6: 9.5 | AD6: Interest component of payment k
A7: Periods per year | B7: 2 | AD7: Capital component of payment k
A8: Effective Periodic interest rate | B8: 0.0016515813 | H8: VALUE | I8: =IF(AND(F4=J26,I4=I26),'Assignment4 (Back End)'!G7,IF(AND(F4=J26,I4=I27),'Assignment4 (Back End)'!G8,IF(AND(F4=J26,I4=I28),'Assignment4 (Back End)'!G9,IF(AND(F4=J26,I4=I29),'Assignment4 (Back End)'!G10,IF(AND(F4=J26,I4=I30),'Assignment4 (Back End)'!G11,IF(AND(F4=J26,I4=I31),'Assignment4 (Back End)'!G12,IF(AND(F4=J26,I4=I32),'Assignment4 (Back End)'!G13,IF(AND(F4=J26,I4=I33),'Assignment4 (Back End)'!G14,IF(AND(F4=J26,I4=I34),'Assignment4 (Back End)'!G15,IF(AND(F4=J27,I4=I26),'Assignment4 (Back End)'!H7,IF(AND(F4=J27,I4=I27),'Assignment4 (Back End)'!H8,IF(AND(F4=J27,I4=I28),'Assignment4 (Back End)'!H9,IF(AND(F4=J27,I4=I29),'Assignment4 (Back End)'!H10,IF(AND(F4=J27,I4=I30),'Assignment4 (Back End)'!H11,IF(AND(F4=J27,I4=I31),'Assignment4 (Back End)'!H12,IF(AND(F4=J27,I4=I32),'Assignment4 (Back End)'!H13,IF(AND(F4=J27,I4=I33),'Assignment4 (Back End)'!H14,IF(AND(F4=J27,I4=I34),'Assignment4 (Back End)'!H15,"Not done yet")))))))))))))))))) -> 18 | AD8: Interest from payment X1 to X2
A9: Specific time (Year) | B9: 5 | AD9: Capital from payment X1 to X2
A10: Specific time (Periods) | B10: 12 | AD10: Last payment(Balance)
A11: Number of Payment (K) | B11: 1 | H11: Real Future Value | I11: =IF(I4=I24, I8*(1+5%)^(-B6), " ")
A12: Start period | B12: 1
A13: End period | B13: 2
E14: To Convert Interest Rates:
E16: Home
AF18: Arrears | AI18: Advance
AF19: Period | AG19: Balance at end | AI19: Period | AJ19: Balance at end
A20: Amortization table (Arrears) | L20: Amortization table (Advance) | AF20: 0 | AG20: =$B$22 -> 70000 | AI20: 0 | AJ20: =M22 -> 70000
A21: Period | B21: Balance at Start | C21: Interest | D21: Payment | E21: Capital | F21: Balance at end | G21: Interest so far | H21: Capital so far | L21: Period | M21: Balance at Start (Before payment) | N21: Payment | O21: Balance at start (after payment) | P21: Interest | Q21: Capital | R21: Balance at the end | S21: Interest so far | T21: Capital so far | AF21: 1 | AG21: =F22 -> 66165.42 | AI21: =L22 -> 1 | AJ21: =R22 -> 66158.896
A22: 1 | B22: =B4 -> 70000 | C22: =$B$8*B22 -> 115.61069 | D22: =$B$5 -> 3950.1909 | E22: =D22-C22 -> 3834.5802 | F22: =B22-E22 -> 66165.42 | G22: =C22 -> 115.61069 | H22: =E22 -> 3834.5802 | L22: 1 | M22: =B4 -> 70000 | N22: =$B$5 -> 3950.1909 | O22: =M22-N22 -> 66049.809 | P22: 0 | Q22: =N22-P22 -> 3950.1909 | R22: =O22*(1+$B$8) -> 66158.896 | S22: =P22 -> 0 | T22: =Q22 -> 3950.1909 | AF22: =IF(AF21<($B$6*$B$7),AF21+1,"") -> 2 | AG22: =F23 -> 62324.506 | AI22: =L23 -> 2 | AJ22: =R23 -> 62311.448
A23: =IF(A22<($B$6*$B$7),A22+1,"") -> 2 | B23: =IF(A23="","",F22) -> 66165.42 | C23: =IF(A23="","",(B23*$B$8)) -> 109.27757 | D23: =IF(A23="","", $B$5) -> 3950.1909 | E23: =IF(D23="","",(D23-C23)) -> 3840.9134 | F23: =IF(A23="","", B23-E23) -> 62324.506 | G23: =IF(A23="","", (G22+C23)) -> 224.88826 | H23: =IF(A23="","",(H22+E23)) -> 7675.4936 | L23: =IF(L22<($B$6*$B$7),L22+1,"") -> 2 | M23: =IF(L23="", "", R22) -> 66158.896 | N23: =IF(L23="","",$B$5) -> 3950.1909 | O23: =IF(L23="","",M23-N23) -> 62208.705 | P23: =IF(L23="","",O22*$B$8) -> 109.08663 | Q23: =IF(L23="","",N23-P23) -> 3841.1043 | R23: =IF(L23="","",O23*(1+$B$8)) -> 62311.448 | S23: =IF(L23="","",S22+P23) -> 109.08663 | T23: =IF(L23="","",Q23+T22) -> 7791.2952 | AF23: =IF(AF22<($B$6*$B$7),AF22+1,"") -> 3 | AG23: =F24 -> 58477.249 | AI23: =L24 -> 3 | AJ23: =R24 -> 58457.645
A24: =IF(A23<($B$6*$B$7),A23+1,"") -> 3 | B24: =IF(A24="","",F23) -> 62324.506 | C24: =IF(A24="","",(B24*$B$8)) -> 102.93399 | D24: =IF(A24="","", $B$5) -> 3950.1909 | E24: =IF(D24="","",(D24-C24)) -> 3847.2569 | F24: =IF(A24="","", B24-E24) -> 58477.249 | G24: =IF(A24="","", (G23+C24)) -> 327.82225 | H24: =IF(A24="","",(H23+E24)) -> 11522.751 | I24: Future | L24: =IF(L23<($B$6*$B$7),L23+1,"") -> 3 | M24: =IF(L24="", "", R23) -> 62311.448 | N24: =IF(L24="","",$B$5) -> 3950.1909 | O24: =IF(L24="","",M24-N24) -> 58361.257 | P24: =IF(L24="","",O23*$B$8) -> 102.74273 | Q24: =IF(L24="","",N24-P24) -> 3847.4482 | R24: =IF(L24="","",O24*(1+$B$8)) -> 58457.645 | S24: =IF(L24="","",S23+P24) -> 211.82936 | T24: =IF(L24="","",Q24+T23) -> 11638.743 | AF24: =IF(AF23<($B$6*$B$7),AF23+1,"") -> 4 | AG24: =F25 -> 54623.638 | AI24: =L25 -> 4 | AJ24: =R25 -> 54597.477
A25: =IF(A24<($B$6*$B$7),A24+1,"") -> 4 | B25: =IF(A25="","",F24) -> 58477.249 | C25: =IF(A25="","",(B25*$B$8)) -> 96.579932 | D25: =IF(A25="","", $B$5) -> 3950.1909 | E25: =IF(D25="","",(D25-C25)) -> 3853.611 | F25: =IF(A25="","", B25-E25) -> 54623.638 | G25: =IF(A25="","", (G24+C25)) -> 424.40218 | H25: =IF(A25="","",(H24+E25)) -> 15376.362 | L25: =IF(L24<($B$6*$B$7),L24+1,"") -> 4 | M25: =IF(L25="", "", R24) -> 58457.645 | N25: =IF(L25="","",$B$5) -> 3950.1909 | O25: =IF(L25="","",M25-N25) -> 54507.454 | P25: =IF(L25="","",O24*$B$8) -> 96.38836 | Q25: =IF(L25="","",N25-P25) -> 3853.8026 | R25: =IF(L25="","",O25*(1+$B$8)) -> 54597.477 | S25: =IF(L25="","",S24+P25) -> 308.21772 | T25: =IF(L25="","",Q25+T24) -> 15492.546 | AF25: =IF(AF24<($B$6*$B$7),AF24+1,"") -> 5 | AG25: =F26 -> 50763.663 | AI25: =L26 -> 5 | AJ25: =R26 -> 50730.935
A26: =IF(A25<($B$6*$B$7),A25+1,"") -> 5 | B26: =IF(A26="","",F25) -> 54623.638 | C26: =IF(A26="","",(B26*$B$8)) -> 90.21538 | D26: =IF(A26="","", $B$5) -> 3950.1909 | E26: =IF(D26="","",(D26-C26)) -> 3859.9755 | F26: =IF(A26="","", B26-E26) -> 50763.663 | G26: =IF(A26="","", (G25+C26)) -> 514.61756 | H26: =IF(A26="","",(H25+E26)) -> 19236.337 | I26: Loan amount | J26: Arrears | L26: =IF(L25<($B$6*$B$7),L25+1,"") -> 5 | M26: =IF(L26="", "", R25) -> 54597.477 | N26: =IF(L26="","",$B$5) -> 3950.1909 | O26: =IF(L26="","",M26-N26) -> 50647.287 | P26: =IF(L26="","",O25*$B$8) -> 90.023492 | Q26: =IF(L26="","",N26-P26) -> 3860.1674 | R26: =IF(L26="","",O26*(1+$B$8)) -> 50730.935 | S26: =IF(L26="","",S25+P26) -> 398.24122 | T26: =IF(L26="","",Q26+T25) -> 19352.713 | AF26: =IF(AF25<($B$6*$B$7),AF25+1,"") -> 6 | AG26: =F27 -> 46897.312 | AI26: =L27 -> 6 | AJ26: =R27 -> 46858.006
A27: =IF(A26<($B$6*$B$7),A26+1,"") -> 6 | B27: =IF(A27="","",F26) -> 50763.663 | C27: =IF(A27="","",(B27*$B$8)) -> 83.840316 | D27: =IF(A27="","", $B$5) -> 3950.1909 | E27: =IF(D27="","",(D27-C27)) -> 3866.3506 | F27: =IF(A27="","", B27-E27) -> 46897.312 | G27: =IF(A27="","", (G26+C27)) -> 598.45788 | H27: =IF(A27="","",(H26+E27)) -> 23102.688 | I27: Payment | J27: Advance | L27: =IF(L26<($B$6*$B$7),L26+1,"") -> 6 | M27: =IF(L27="", "", R26) -> 50730.935 | N27: =IF(L27="","",$B$5) -> 3950.1909 | O27: =IF(L27="","",M27-N27) -> 46780.744 | P27: =IF(L27="","",O26*$B$8) -> 83.648111 | Q27: =IF(L27="","",N27-P27) -> 3866.5428 | R27: =IF(L27="","",O27*(1+$B$8)) -> 46858.006 | S27: =IF(L27="","",S26+P27) -> 481.88933 | T27: =IF(L27="","",Q27+T26) -> 23219.256 | AF27: =IF(AF26<($B$6*$B$7),AF26+1,"") -> 7 | AG27: =F28 -> 43024.576 | AI27: =L28 -> 7 | AJ27: =R28 -> 42978.681
A28: =IF(A27<($B$6*$B$7),A27+1,"") -> 7 | B28: =IF(A28="","",F27) -> 46897.312 | C28: =IF(A28="","",(B28*$B$8)) -> 77.454724 | D28: =IF(A28="","", $B$5) -> 3950.1909 | E28: =IF(D28="","",(D28-C28)) -> 3872.7362 | F28: =IF(A28="","", B28-E28) -> 43024.576 | G28: =IF(A28="","", (G27+C28)) -> 675.9126 | H28: =IF(A28="","",(H27+E28)) -> 26975.424 | I28: Period to repay | L28: =IF(L27<($B$6*$B$7),L27+1,"") -> 7 | M28: =IF(L28="", "", R27) -> 46858.006 | N28: =IF(L28="","",$B$5) -> 3950.1909 | O28: =IF(L28="","",M28-N28) -> 42907.815 | P28: =IF(L28="","",O27*$B$8) -> 77.262202 | Q28: =IF(L28="","",N28-P28) -> 3872.9287 | R28: =IF(L28="","",O28*(1+$B$8)) -> 42978.681 | S28: =IF(L28="","",S27+P28) -> 559.15153 | T28: =IF(L28="","",Q28+T27) -> 27092.185 | AF28: =IF(AF27<($B$6*$B$7),AF27+1,"") -> 8 | AG28: =F29 -> 39145.444 | AI28: =L29 -> 8 | AJ28: =R29 -> 39092.949
A29: =IF(A28<($B$6*$B$7),A28+1,"") -> 8 | B29: =IF(A29="","",F28) -> 43024.576 | C29: =IF(A29="","",(B29*$B$8)) -> 71.058585 | D29: =IF(A29="","", $B$5) -> 3950.1909 | E29: =IF(D29="","",(D29-C29)) -> 3879.1323 | F29: =IF(A29="","", B29-E29) -> 39145.444 | G29: =IF(A29="","", (G28+C29)) -> 746.97119 | H29: =IF(A29="","",(H28+E29)) -> 30854.556 | I29: Balance at specific time of the year | L29: =IF(L28<($B$6*$B$7),L28+1,"") -> 8 | M29: =IF(L29="", "", R28) -> 42978.681 | N29: =IF(L29="","",$B$5) -> 3950.1909 | O29: =IF(L29="","",M29-N29) -> 39028.49 | P29: =IF(L29="","",O28*$B$8) -> 70.865745 | Q29: =IF(L29="","",N29-P29) -> 3879.3252 | R29: =IF(L29="","",O29*(1+$B$8)) -> 39092.949 | S29: =IF(L29="","",S28+P29) -> 630.01727 | T29: =IF(L29="","",Q29+T28) -> 30971.51 | AF29: =IF(AF28<($B$6*$B$7),AF28+1,"") -> 9 | AG29: =F30 -> 35259.905 | AI29: =L30 -> 9 | AJ29: =R30 -> 35200.799
A30: =IF(A29<($B$6*$B$7),A29+1,"") -> 9 | B30: =IF(A30="","",F29) -> 39145.444 | C30: =IF(A30="","",(B30*$B$8)) -> 64.651883 | D30: =IF(A30="","", $B$5) -> 3950.1909 | E30: =IF(D30="","",(D30-C30)) -> 3885.539 | F30: =IF(A30="","", B30-E30) -> 35259.905 | G30: =IF(A30="","", (G29+C30)) -> 811.62307 | H30: =IF(A30="","",(H29+E30)) -> 34740.095 | I30: Interest component of payment k | L30: =IF(L29<($B$6*$B$7),L29+1,"") -> 9 | M30: =IF(L30="", "", R29) -> 39092.949 | N30: =IF(L30="","",$B$5) -> 3950.1909 | O30: =IF(L30="","",M30-N30) -> 35142.758 | P30: =IF(L30="","",O29*$B$8) -> 64.458724 | Q30: =IF(L30="","",N30-P30) -> 3885.7322 | R30: =IF(L30="","",O30*(1+$B$8)) -> 35200.799 | S30: =IF(L30="","",S29+P30) -> 694.476 | T30: =IF(L30="","",Q30+T29) -> 34857.242 | AF30: =IF(AF29<($B$6*$B$7),AF29+1,"") -> 10 | AG30: =F31 -> 31367.948 | AI30: =L31 -> 10 | AJ30: =R31 -> 31302.221
A31: =IF(A30<($B$6*$B$7),A30+1,"") -> 10 | B31: =IF(A31="","",F30) -> 35259.905 | C31: =IF(A31="","",(B31*$B$8)) -> 58.234599 | D31: =IF(A31="","", $B$5) -> 3950.1909 | E31: =IF(D31="","",(D31-C31)) -> 3891.9563 | F31: =IF(A31="","", B31-E31) -> 31367.948 | G31: =IF(A31="","", (G30+C31)) -> 869.85767 | H31: =IF(A31="","",(H30+E31)) -> 38632.052 | I31: Capital component of payment k | L31: =IF(L30<($B$6*$B$7),L30+1,"") -> 10 | M31: =IF(L31="", "", R30) -> 35200.799 | N31: =IF(L31="","",$B$5) -> 3950.1909 | O31: =IF(L31="","",M31-N31) -> 31250.608 | P31: =IF(L31="","",O30*$B$8) -> 58.041121 | Q31: =IF(L31="","",N31-P31) -> 3892.1498 | R31: =IF(L31="","",O31*(1+$B$8)) -> 31302.221 | S31: =IF(L31="","",S30+P31) -> 752.51712 | T31: =IF(L31="","",Q31+T30) -> 38749.392 | AF31: =IF(AF30<($B$6*$B$7),AF30+1,"") -> 11 | AG31: =F32 -> 27469.564 | AI31: =L32 -> 11 | AJ31: =R32 -> 27397.204
A32: =IF(A31<($B$6*$B$7),A31+1,"") -> 11 | B32: =IF(A32="","",F31) -> 31367.948 | C32: =IF(A32="","",(B32*$B$8)) -> 51.806717 | D32: =IF(A32="","", $B$5) -> 3950.1909 | E32: =IF(D32="","",(D32-C32)) -> 3898.3842 | F32: =IF(A32="","", B32-E32) -> 27469.564 | G32: =IF(A32="","", (G31+C32)) -> 921.66439 | H32: =IF(A32="","",(H31+E32)) -> 42530.436 | I32: Interest from payment X1 to X2 | L32: =IF(L31<($B$6*$B$7),L31+1,"") -> 11 | M32: =IF(L32="", "", R31) -> 31302.221 | N32: =IF(L32="","",$B$5) -> 3950.1909 | O32: =IF(L32="","",M32-N32) -> 27352.03 | P32: =IF(L32="","",O31*$B$8) -> 51.61292 | Q32: =IF(L32="","",N32-P32) -> 3898.578 | R32: =IF(L32="","",O32*(1+$B$8)) -> 27397.204 | S32: =IF(L32="","",S31+P32) -> 804.13004 | T32: =IF(L32="","",Q32+T31) -> 42647.97 | AF32: =IF(AF31<($B$6*$B$7),AF31+1,"") -> 12 | AG32: =F33 -> 23564.741 | AI32: =L33 -> 12 | AJ32: =R33 -> 23485.738
A33: =IF(A32<($B$6*$B$7),A32+1,"") -> 12 | B33: =IF(A33="","",F32) -> 27469.564 | C33: =IF(A33="","",(B33*$B$8)) -> 45.368219 | D33: =IF(A33="","", $B$5) -> 3950.1909 | E33: =IF(D33="","",(D33-C33)) -> 3904.8227 | F33: =IF(A33="","", B33-E33) -> 23564.741 | G33: =IF(A33="","", (G32+C33)) -> 967.03261 | H33: =IF(A33="","",(H32+E33)) -> 46435.259 | I33: Capital from payment X1 to X2 | L33: =IF(L32<($B$6*$B$7),L32+1,"") -> 12 | M33: =IF(L33="", "", R32) -> 27397.204 | N33: =IF(L33="","",$B$5) -> 3950.1909 | O33: =IF(L33="","",M33-N33) -> 23447.013 | P33: =IF(L33="","",O32*$B$8) -> 45.174101 | Q33: =IF(L33="","",N33-P33) -> 3905.0168 | R33: =IF(L33="","",O33*(1+$B$8)) -> 23485.738 | S33: =IF(L33="","",S32+P33) -> 849.30414 | T33: =IF(L33="","",Q33+T32) -> 46552.987 | AF33: =IF(AF32<($B$6*$B$7),AF32+1,"") -> 13 | AG33: =F34 -> 19653.47 | AI33: =L34 -> 13 | AJ33: =R34 -> 19567.811
A34: =IF(A33<($B$6*$B$7),A33+1,"") -> 13 | B34: =IF(A34="","",F33) -> 23564.741 | C34: =IF(A34="","",(B34*$B$8)) -> 38.919086 | D34: =IF(A34="","", $B$5) -> 3950.1909 | E34: =IF(D34="","",(D34-C34)) -> 3911.2718 | F34: =IF(A34="","", B34-E34) -> 19653.47 | G34: =IF(A34="","", (G33+C34)) -> 1005.9517 | H34: =IF(A34="","",(H33+E34)) -> 50346.53 | I34: Last payment | L34: =IF(L33<($B$6*$B$7),L33+1,"") -> 13 | M34: =IF(L34="", "", R33) -> 23485.738 | N34: =IF(L34="","",$B$5) -> 3950.1909 | O34: =IF(L34="","",M34-N34) -> 19535.547 | P34: =IF(L34="","",O33*$B$8) -> 38.724648 | Q34: =IF(L34="","",N34-P34) -> 3911.4663 | R34: =IF(L34="","",O34*(1+$B$8)) -> 19567.811 | S34: =IF(L34="","",S33+P34) -> 888.02879 | T34: =IF(L34="","",Q34+T33) -> 50464.453 | AF34: =IF(AF33<($B$6*$B$7),AF33+1,"") -> 14 | AG34: =F35 -> 15735.738 | AI34: =L35 -> 14 | AJ34: =R35 -> 15643.414
A35: =IF(A34<($B$6*$B$7),A34+1,"") -> 14 | B35: =IF(A35="","",F34) -> 19653.47 | C35: =IF(A35="","",(B35*$B$8)) -> 32.459303 | D35: =IF(A35="","", $B$5) -> 3950.1909 | E35: =IF(D35="","",(D35-C35)) -> 3917.7316 | F35: =IF(A35="","", B35-E35) -> 15735.738 | G35: =IF(A35="","", (G34+C35)) -> 1038.411 | H35: =IF(A35="","",(H34+E35)) -> 54264.262 | L35: =IF(L34<($B$6*$B$7),L34+1,"") -> 14 | M35: =IF(L35="", "", R34) -> 19567.811 | N35: =IF(L35="","",$B$5) -> 3950.1909 | O35: =IF(L35="","",M35-N35) -> 15617.62 | P35: =IF(L35="","",O34*$B$8) -> 32.264544 | Q35: =IF(L35="","",N35-P35) -> 3917.9264 | R35: =IF(L35="","",O35*(1+$B$8)) -> 15643.414 | S35: =IF(L35="","",S34+P35) -> 920.29333 | T35: =IF(L35="","",Q35+T34) -> 54382.38 | AF35: =IF(AF34<($B$6*$B$7),AF34+1,"") -> 15 | AG35: =F36 -> 11811.536 | AI35: =L36 -> 15 | AJ35: =R36 -> 11712.535
A36: =IF(A35<($B$6*$B$7),A35+1,"") -> 15 | B36: =IF(A36="","",F35) -> 15735.738 | C36: =IF(A36="","",(B36*$B$8)) -> 25.988851 | D36: =IF(A36="","", $B$5) -> 3950.1909 | E36: =IF(D36="","",(D36-C36)) -> 3924.2021 | F36: =IF(A36="","", B36-E36) -> 11811.536 | G36: =IF(A36="","", (G35+C36)) -> 1064.3998 | H36: =IF(A36="","",(H35+E36)) -> 58188.464 | L36: =IF(L35<($B$6*$B$7),L35+1,"") -> 15 | M36: =IF(L36="", "", R35) -> 15643.414 | N36: =IF(L36="","",$B$5) -> 3950.1909 | O36: =IF(L36="","",M36-N36) -> 11693.223 | P36: =IF(L36="","",O35*$B$8) -> 25.79377 | Q36: =IF(L36="","",N36-P36) -> 3924.3972 | R36: =IF(L36="","",O36*(1+$B$8)) -> 11712.535 | S36: =IF(L36="","",S35+P36) -> 946.0871 | T36: =IF(L36="","",Q36+T35) -> 58306.777 | AF36: =IF(AF35<($B$6*$B$7),AF35+1,"") -> 16 | AG36: =F37 -> 7880.8527 | AI36: =L37 -> 16 | AJ36: =R37 -> 7775.1647
A37: =IF(A36<($B$6*$B$7),A36+1,"") -> 16 | B37: =IF(A37="","",F36) -> 11811.536 | C37: =IF(A37="","",(B37*$B$8)) -> 19.507712 | D37: =IF(A37="","", $B$5) -> 3950.1909 | E37: =IF(D37="","",(D37-C37)) -> 3930.6832 | F37: =IF(A37="","", B37-E37) -> 7880.8527 | G37: =IF(A37="","", (G36+C37)) -> 1083.9076 | H37: =IF(A37="","",(H36+E37)) -> 62119.147 | L37: =IF(L36<($B$6*$B$7),L36+1,"") -> 16 | M37: =IF(L37="", "", R36) -> 11712.535 | N37: =IF(L37="","",$B$5) -> 3950.1909 | O37: =IF(L37="","",M37-N37) -> 7762.3445 | P37: =IF(L37="","",O36*$B$8) -> 19.312309 | Q37: =IF(L37="","",N37-P37) -> 3930.8786 | R37: =IF(L37="","",O37*(1+$B$8)) -> 7775.1647 | S37: =IF(L37="","",S36+P37) -> 965.39941 | T37: =IF(L37="","",Q37+T36) -> 62237.655 | AF37: =IF(AF36<($B$6*$B$7),AF36+1,"") -> 17 | AG37: =F38 -> 3943.6776 | AI37: =L38 -> 17 | AJ37: =R38 -> 3831.291
A38: =IF(A37<($B$6*$B$7),A37+1,"") -> 17 | B38: =IF(A38="","",F37) -> 7880.8527 | C38: =IF(A38="","",(B38*$B$8)) -> 13.015869 | D38: =IF(A38="","", $B$5) -> 3950.1909 | E38: =IF(D38="","",(D38-C38)) -> 3937.1751 | F38: =IF(A38="","", B38-E38) -> 3943.6776 | G38: =IF(A38="","", (G37+C38)) -> 1096.9234 | H38: =IF(A38="","",(H37+E38)) -> 66056.322 | L38: =IF(L37<($B$6*$B$7),L37+1,"") -> 17 | M38: =IF(L38="", "", R37) -> 7775.1647 | N38: =IF(L38="","",$B$5) -> 3950.1909 | O38: =IF(L38="","",M38-N38) -> 3824.9738 | P38: =IF(L38="","",O37*$B$8) -> 12.820143 | Q38: =IF(L38="","",N38-P38) -> 3937.3708 | R38: =IF(L38="","",O38*(1+$B$8)) -> 3831.291 | S38: =IF(L38="","",S37+P38) -> 978.21955 | T38: =IF(L38="","",Q38+T37) -> 66175.026 | AF38: =IF(AF37<($B$6*$B$7),AF37+1,"") -> 18 | AG38: =F39 -> -8.1581675e-10 | AI38: =L39 -> 18 | AJ38: =R39 -> -119.0963
A39: =IF(A38<($B$6*$B$7),A38+1,"") -> 18 | B39: =IF(A39="","",F38) -> 3943.6776 | C39: =IF(A39="","",(B39*$B$8)) -> 6.5133042 | D39: =IF(A39="","", $B$5) -> 3950.1909 | E39: =IF(D39="","",(D39-C39)) -> 3943.6776 | F39: =IF(A39="","", B39-E39) -> -8.1581675e-10 | G39: =IF(A39="","", (G38+C39)) -> 1103.4367 | H39: =IF(A39="","",(H38+E39)) -> 70000 | L39: =IF(L38<($B$6*$B$7),L38+1,"") -> 18 | M39: =IF(L39="", "", R38) -> 3831.291 | N39: =IF(L39="","",$B$5) -> 3950.1909 | O39: =IF(L39="","",M39-N39) -> -118.89992 | P39: =IF(L39="","",O38*$B$8) -> 6.3172551 | Q39: =IF(L39="","",N39-P39) -> 3943.8737 | R39: =IF(L39="","",O39*(1+$B$8)) -> -119.0963 | S39: =IF(L39="","",S38+P39) -> 984.53681 | T39: =IF(L39="","",Q39+T38) -> 70118.9 | AF39: =IF(AF38<($B$6*$B$7),AF38+1,"") -> 19 | AG39: =F40 -> -3950.1909 | AI39: =L40 -> 19 | AJ39: =R40 -> -4076.008
A40: =IF(A39<($B$6*$B$7),A39+1,"") -> 19 | B40: =IF(A40="","",F39) -> -8.1581675e-10 | C40: =IF(A40="","",(B40*$B$8)) -> -1.3473877e-12 | D40: =IF(A40="","", $B$5) -> 3950.1909 | E40: =IF(D40="","",(D40-C40)) -> 3950.1909 | F40: =IF(A40="","", B40-E40) -> -3950.1909 | G40: =IF(A40="","", (G39+C40)) -> 1103.4367 | H40: =IF(A40="","",(H39+E40)) -> 73950.191 | L40: =IF(L39<($B$6*$B$7),L39+1,"") -> 19 | M40: =IF(L40="", "", R39) -> -119.0963 | N40: =IF(L40="","",$B$5) -> 3950.1909 | O40: =IF(L40="","",M40-N40) -> -4069.2872 | P40: =IF(L40="","",O39*$B$8) -> -0.19637289 | Q40: =IF(L40="","",N40-P40) -> 3950.3873 | R40: =IF(L40="","",O40*(1+$B$8)) -> -4076.008 | S40: =IF(L40="","",S39+P40) -> 984.34044 | T40: =IF(L40="","",Q40+T39) -> 74069.287 | AF40: =IF(AF39<($B$6*$B$7),AF39+1,"") | AG40: =F41 | AI40: =L41 | AJ40: =R41
A41: =IF(A40<($B$6*$B$7),A40+1,"") | B41: =IF(A41="","",F40) | C41: =IF(A41="","",(B41*$B$8)) | D41: =IF(A41="","", $B$5) | E41: =IF(D41="","",(D41-C41)) | F41: =IF(A41="","", B41-E41) | G41: =IF(A41="","", (G40+C41)) | H41: =IF(A41="","",(H40+E41)) | L41: =IF(L40<($B$6*$B$7),L40+1,"") | M41: =IF(L41="", "", R40) | N41: =IF(L41="","",$B$5) | O41: =IF(L41="","",M41-N41) | P41: =IF(L41="","",O40*$B$8) | Q41: =IF(L41="","",N41-P41) | R41: =IF(L41="","",O41*(1+$B$8)) | S41: =IF(L41="","",S40+P41) | T41: =IF(L41="","",Q41+T40) | AF41: =IF(AF40<($B$6*$B$7),AF40+1,"") | AG41: =F42 | AI41: =L42 | AJ41: =R42
A42: =IF(A41<($B$6*$B$7),A41+1,"") | B42: =IF(A42="","",F41) | C42: =IF(A42="","",(B42*$B$8)) | D42: =IF(A42="","", $B$5) | E42: =IF(D42="","",(D42-C42)) | F42: =IF(A42="","", B42-E42) | G42: =IF(A42="","", (G41+C42)) | H42: =IF(A42="","",(H41+E42)) | L42: =IF(L41<($B$6*$B$7),L41+1,"") | M42: =IF(L42="", "", R41) | N42: =IF(L42="","",$B$5) | O42: =IF(L42="","",M42-N42) | P42: =IF(L42="","",O41*$B$8) | Q42: =IF(L42="","",N42-P42) | R42: =IF(L42="","",O42*(1+$B$8)) | S42: =IF(L42="","",S41+P42) | T42: =IF(L42="","",Q42+T41) | AF42: =IF(AF41<($B$6*$B$7),AF41+1,"") | AG42: =F43 | AI42: =L43 | AJ42: =R43
A43: =IF(A42<($B$6*$B$7),A42+1,"") | B43: =IF(A43="","",F42) | C43: =IF(A43="","",(B43*$B$8)) | D43: =IF(A43="","", $B$5) | E43: =IF(D43="","",(D43-C43)) | F43: =IF(A43="","", B43-E43) | G43: =IF(A43="","", (G42+C43)) | H43: =IF(A43="","",(H42+E43)) | L43: =IF(L42<($B$6*$B$7),L42+1,"") | M43: =IF(L43="", "", R42) | N43: =IF(L43="","",$B$5) | O43: =IF(L43="","",M43-N43) | P43: =IF(L43="","",O42*$B$8) | Q43: =IF(L43="","",N43-P43) | R43: =IF(L43="","",O43*(1+$B$8)) | S43: =IF(L43="","",S42+P43) | T43: =IF(L43="","",Q43+T42) | AF43: =IF(AF42<($B$6*$B$7),AF42+1,"") | AG43: =F44 | AI43: =L44 | AJ43: =R44
A44: =IF(A43<($B$6*$B$7),A43+1,"") | B44: =IF(A44="","",F43) | C44: =IF(A44="","",(B44*$B$8)) | D44: =IF(A44="","", $B$5) | E44: =IF(D44="","",(D44-C44)) | F44: =IF(A44="","", B44-E44) | G44: =IF(A44="","", (G43+C44)) | H44: =IF(A44="","",(H43+E44)) | L44: =IF(L43<($B$6*$B$7),L43+1,"") | M44: =IF(L44="", "", R43) | N44: =IF(L44="","",$B$5) | O44: =IF(L44="","",M44-N44) | P44: =IF(L44="","",O43*$B$8) | Q44: =IF(L44="","",N44-P44) | R44: =IF(L44="","",O44*(1+$B$8)) | S44: =IF(L44="","",S43+P44) | T44: =IF(L44="","",Q44+T43) | AF44: =IF(AF43<($B$6*$B$7),AF43+1,"") | AG44: =F45 | AI44: =L45 | AJ44: =R45
A45: =IF(A44<($B$6*$B$7),A44+1,"") | B45: =IF(A45="","",F44) | C45: =IF(A45="","",(B45*$B$8)) | D45: =IF(A45="","", $B$5) | E45: =IF(D45="","",(D45-C45)) | F45: =IF(A45="","", B45-E45) | G45: =IF(A45="","", (G44+C45)) | H45: =IF(A45="","",(H44+E45)) | L45: =IF(L44<($B$6*$B$7),L44+1,"") | M45: =IF(L45="", "", R44) | N45: =IF(L45="","",$B$5) | O45: =IF(L45="","",M45-N45) | P45: =IF(L45="","",O44*$B$8) | Q45: =IF(L45="","",N45-P45) | R45: =IF(L45="","",O45*(1+$B$8)) | S45: =IF(L45="","",S44+P45) | T45: =IF(L45="","",Q45+T44) | AF45: =IF(AF44<($B$6*$B$7),AF44+1,"") | AG45: =F46 | AI45: =L46 | AJ45: =R46
A46: =IF(A45<($B$6*$B$7),A45+1,"") | B46: =IF(A46="","",F45) | C46: =IF(A46="","",(B46*$B$8)) | D46: =IF(A46="","", $B$5) | E46: =IF(D46="","",(D46-C46)) | F46: =IF(A46="","", B46-E46) | G46: =IF(A46="","", (G45+C46)) | H46: =IF(A46="","",(H45+E46)) | L46: =IF(L45<($B$6*$B$7),L45+1,"") | M46: =IF(L46="", "", R45) | N46: =IF(L46="","",$B$5) | O46: =IF(L46="","",M46-N46) | P46: =IF(L46="","",O45*$B$8) | Q46: =IF(L46="","",N46-P46) | R46: =IF(L46="","",O46*(1+$B$8)) | S46: =IF(L46="","",S45+P46) | T46: =IF(L46="","",Q46+T45) | AF46: =IF(AF45<($B$6*$B$7),AF45+1,"") | AG46: =F47 | AI46: =L47 | AJ46: =R47
... A50: =IF(A49<($B$6*$B$7),A49+1,"") | B50: =IF(A50="","",F49) | C50: =IF(A50="","",(B50*$B$8)) | D50: =IF(A50="","", $B$5) | E50: =IF(D50="","",(D50-C50)) | F50: =IF(A50="","", B50-E50) | G50: =IF(A50="","", (G49+C50)) | H50: =IF(A50="","",(H49+E50)) | L50: =IF(L49<($B$6*$B$7),L49+1,"") | M50: =IF(L50="", "", R49) | N50: =IF(L50="","",$B$5) | O50: =IF(L50="","",M50-N50) | P50: =IF(L50="","",O49*$B$8) | Q50: =IF(L50="","",N50-P50) | R50: =IF(L50="","",O50*(1+$B$8)) | S50: =IF(L50="","",S49+P50) | T50: =IF(L50="","",Q50+T49) | AF50: =IF(AF49<($B$6*$B$7),AF49+1,"") | AG50: =F51 | AI50: =L51 | AJ50: =R51
A51: =IF(A50<($B$6*$B$7),A50+1,"") | B51: =IF(A51="","",F50) | C51: =IF(A51="","",(B51*$B$8)) | D51: =IF(A51="","", $B$5) | E51: =IF(D51="","",(D51-C51)) | F51: =IF(A51="","", B51-E51) | G51: =IF(A51="","", (G50+C51)) | H51: =IF(A51="","",(H50+E51)) | L51: =IF(L50<($B$6*$B$7),L50+1,"") | M51: =IF(L51="", "", R50) | N51: =IF(L51="","",$B$5) | O51: =IF(L51="","",M51-N51) | P51: =IF(L51="","",O50*$B$8) | Q51: =IF(L51="","",N51-P51) | R51: =IF(L51="","",O51*(1+$B$8)) | S51: =IF(L51="","",S50+P51) | T51: =IF(L51="","",Q51+T50)
A52: =IF(A51<($B$6*$B$7),A51+1,"") | B52: =IF(A52="","",F51) | C52: =IF(A52="","",(B52*$B$8)) | D52: =IF(A52="","", $B$5) | E52: =IF(D52="","",(D52-C52)) | F52: =IF(A52="","", B52-E52) | G52: =IF(A52="","", (G51+C52)) | H52: =IF(A52="","",(H51+E52)) | L52: =IF(L51<($B$6*$B$7),L51+1,"") | M52: =IF(L52="", "", R51) | N52: =IF(L52="","",$B$5) | O52: =IF(L52="","",M52-N52) | P52: =IF(L52="","",O51*$B$8) | Q52: =IF(L52="","",N52-P52) | R52: =IF(L52="","",O52*(1+$B$8)) | S52: =IF(L52="","",S51+P52) | T52: =IF(L52="","",Q52+T51)
A53: =IF(A52<($B$6*$B$7),A52+1,"") | B53: =IF(A53="","",F52) | C53: =IF(A53="","",(B53*$B$8)) | D53: =IF(A53="","", $B$5) | E53: =IF(D53="","",(D53-C53)) | F53: =IF(A53="","", B53-E53) | G53: =IF(A53="","", (G52+C53)) | H53: =IF(A53="","",(H52+E53)) | L53: =IF(L52<($B$6*$B$7),L52+1,"") | M53: =IF(L53="", "", R52) | N53: =IF(L53="","",$B$5) | O53: =IF(L53="","",M53-N53) | P53: =IF(L53="","",O52*$B$8) | Q53: =IF(L53="","",N53-P53) | R53: =IF(L53="","",O53*(1+$B$8)) | S53: =IF(L53="","",S52+P53) | T53: =IF(L53="","",Q53+T52)
A54: =IF(A53<($B$6*$B$7),A53+1,"") | B54: =IF(A54="","",F53) | C54: =IF(A54="","",(B54*$B$8)) | D54: =IF(A54="","", $B$5) | E54: =IF(D54="","",(D54-C54)) | F54: =IF(A54="","", B54-E54) | G54: =IF(A54="","", (G53+C54)) | H54: =IF(A54="","",(H53+E54)) | L54: =IF(L53<($B$6*$B$7),L53+1,"") | M54: =IF(L54="", "", R53) | N54: =IF(L54="","",$B$5) | O54: =IF(L54="","",M54-N54) | P54: =IF(L54="","",O53*$B$8) | Q54: =IF(L54="","",N54-P54) | R54: =IF(L54="","",O54*(1+$B$8)) | S54: =IF(L54="","",S53+P54) | T54: =IF(L54="","",Q54+T53)
A55: =IF(A54<($B$6*$B$7),A54+1,"") | B55: =IF(A55="","",F54) | C55: =IF(A55="","",(B55*$B$8)) | D55: =IF(A55="","", $B$5) | E55: =IF(D55="","",(D55-C55)) | F55: =IF(A55="","", B55-E55) | G55: =IF(A55="","", (G54+C55)) | H55: =IF(A55="","",(H54+E55)) | L55: =IF(L54<($B$6*$B$7),L54+1,"") | M55: =IF(L55="", "", R54) | N55: =IF(L55="","",$B$5) | O55: =IF(L55="","",M55-N55) | P55: =IF(L55="","",O54*$B$8) | Q55: =IF(L55="","",N55-P55) | R55: =IF(L55="","",O55*(1+$B$8)) | S55: =IF(L55="","",S54+P55) | T55: =IF(L55="","",Q55+T54)
A56: =IF(A55<($B$6*$B$7),A55+1,"") | B56: =IF(A56="","",F55) | C56: =IF(A56="","",(B56*$B$8)) | D56: =IF(A56="","", $B$5) | E56: =IF(D56="","",(D56-C56)) | F56: =IF(A56="","", B56-E56) | G56: =IF(A56="","", (G55+C56)) | H56: =IF(A56="","",(H55+E56)) | L56: =IF(L55<($B$6*$B$7),L55+1,"") | M56: =IF(L56="", "", R55) | N56: =IF(L56="","",$B$5) | O56: =IF(L56="","",M56-N56) | P56: =IF(L56="","",O55*$B$8) | Q56: =IF(L56="","",N56-P56) | R56: =IF(L56="","",O56*(1+$B$8)) | S56: =IF(L56="","",S55+P56) | T56: =IF(L56="","",Q56+T55)
A57: =IF(A56<($B$6*$B$7),A56+1,"") | B57: =IF(A57="","",F56) | C57: =IF(A57="","",(B57*$B$8)) | D57: =IF(A57="","", $B$5) | E57: =IF(D57="","",(D57-C57)) | F57: =IF(A57="","", B57-E57) | G57: =IF(A57="","", (G56+C57)) | H57: =IF(A57="","",(H56+E57)) | L57: =IF(L56<($B$6*$B$7),L56+1,"") | M57: =IF(L57="", "", R56) | N57: =IF(L57="","",$B$5) | O57: =IF(L57="","",M57-N57) | P57: =IF(L57="","",O56*$B$8) | Q57: =IF(L57="","",N57-P57) | R57: =IF(L57="","",O57*(1+$B$8)) | S57: =IF(L57="","",S56+P57) | T57: =IF(L57="","",Q57+T56)
A58: =IF(A57<($B$6*$B$7),A57+1,"") | B58: =IF(A58="","",F57) | C58: =IF(A58="","",(B58*$B$8)) | D58: =IF(A58="","", $B$5) | E58: =IF(D58="","",(D58-C58)) | F58: =IF(A58="","", B58-E58) | G58: =IF(A58="","", (G57+C58)) | H58: =IF(A58="","",(H57+E58)) | L58: =IF(L57<($B$6*$B$7),L57+1,"") | M58: =IF(L58="", "", R57) | N58: =IF(L58="","",$B$5) | O58: =IF(L58="","",M58-N58) | P58: =IF(L58="","",O57*$B$8) | Q58: =IF(L58="","",N58-P58) | R58: =IF(L58="","",O58*(1+$B$8)) | S58: =IF(L58="","",S57+P58) | T58: =IF(L58="","",Q58+T57)
A59: =IF(A58<($B$6*$B$7),A58+1,"") | B59: =IF(A59="","",F58) | C59: =IF(A59="","",(B59*$B$8)) | D59: =IF(A59="","", $B$5) | E59: =IF(D59="","",(D59-C59)) | F59: =IF(A59="","", B59-E59) | G59: =IF(A59="","", (G58+C59)) | H59: =IF(A59="","",(H58+E59)) | L59: =IF(L58<($B$6*$B$7),L58+1,"") | M59: =IF(L59="", "", R58) | N59: =IF(L59="","",$B$5) | O59: =IF(L59="","",M59-N59) | P59: =IF(L59="","",O58*$B$8) | Q59: =IF(L59="","",N59-P59) | R59: =IF(L59="","",O59*(1+$B$8)) | S59: =IF(L59="","",S58+P59) | T59: =IF(L59="","",Q59+T58)
A60: =IF(A59<($B$6*$B$7),A59+1,"") | B60: =IF(A60="","",F59) | C60: =IF(A60="","",(B60*$B$8)) | D60: =IF(A60="","", $B$5) | E60: =IF(D60="","",(D60-C60)) | F60: =IF(A60="","", B60-E60) | G60: =IF(A60="","", (G59+C60)) | H60: =IF(A60="","",(H59+E60)) | L60: =IF(L59<($B$6*$B$7),L59+1,"") | M60: =IF(L60="", "", R59) | N60: =IF(L60="","",$B$5) | O60: =IF(L60="","",M60-N60) | P60: =IF(L60="","",O59*$B$8) | Q60: =IF(L60="","",N60-P60) | R60: =IF(L60="","",O60*(1+$B$8)) | S60: =IF(L60="","",S59+P60) | T60: =IF(L60="","",Q60+T59)
A61: =IF(A60<($B$6*$B$7),A60+1,"") | B61: =IF(A61="","",F60) | C61: =IF(A61="","",(B61*$B$8)) | D61: =IF(A61="","", $B$5) | E61: =IF(D61="","",(D61-C61)) | F61: =IF(A61="","", B61-E61) | G61: =IF(A61="","", (G60+C61)) | H61: =IF(A61="","",(H60+E61)) | L61: =IF(L60<($B$6*$B$7),L60+1,"") | M61: =IF(L61="", "", R60) | N61: =IF(L61="","",$B$5) | O61: =IF(L61="","",M61-N61) | P61: =IF(L61="","",O60*$B$8) | Q61: =IF(L61="","",N61-P61) | R61: =IF(L61="","",O61*(1+$B$8)) | S61: =IF(L61="","",S60+P61) | T61: =IF(L61="","",Q61+T60)
A62: =IF(A61<($B$6*$B$7),A61+1,"") | B62: =IF(A62="","",F61) | C62: =IF(A62="","",(B62*$B$8)) | D62: =IF(A62="","", $B$5) | E62: =IF(D62="","",(D62-C62)) | F62: =IF(A62="","", B62-E62) | G62: =IF(A62="","", (G61+C62)) | H62: =IF(A62="","",(H61+E62)) | L62: =IF(L61<($B$6*$B$7),L61+1,"") | M62: =IF(L62="", "", R61) | N62: =IF(L62="","",$B$5) | O62: =IF(L62="","",M62-N62) | P62: =IF(L62="","",O61*$B$8) | Q62: =IF(L62="","",N62-P62) | R62: =IF(L62="","",O62*(1+$B$8)) | S62: =IF(L62="","",S61+P62) | T62: =IF(L62="","",Q62+T61)
... A309: =IF(A308<($B$6*$B$7),A308+1,"") | B309: =IF(A309="","",F308) | C309: =IF(A309="","",(B309*$B$8)) | D309: =IF(A309="","", $B$5) | E309: =IF(D309="","",(D309-C309)) | F309: =IF(A309="","", B309-E309) | G309: =IF(A309="","", (G308+C309)) | H309: =IF(A309="","",(H308+E309)) | L309: =IF(L308<($B$6*$B$7),L308+1,"") | M309: =IF(L309="", "", R308) | N309: =IF(L309="","",$B$5) | O309: =IF(L309="","",M309-N309) | P309: =IF(L309="","",O308*$B$8) | Q309: =IF(L309="","",N309-P309) | R309: =IF(L309="","",O309*(1+$B$8)) | S309: =IF(L309="","",S308+P309) | T309: =IF(L309="","",Q309+T308)
A310: =IF(A309<($B$6*$B$7),A309+1,"") | B310: =IF(A310="","",F309) | C310: =IF(A310="","",(B310*$B$8)) | D310: =IF(A310="","", $B$5) | E310: =IF(D310="","",(D310-C310)) | F310: =IF(A310="","", B310-E310) | G310: =IF(A310="","", (G309+C310)) | H310: =IF(A310="","",(H309+E310)) | L310: =IF(L309<($B$6*$B$7),L309+1,"") | M310: =IF(L310="", "", R309) | N310: =IF(L310="","",$B$5) | O310: =IF(L310="","",M310-N310) | P310: =IF(L310="","",O309*$B$8) | Q310: =IF(L310="","",N310-P310) | R310: =IF(L310="","",O310*(1+$B$8)) | S310: =IF(L310="","",S309+P310) | T310: =IF(L310="","",Q310+T309) | AF310: =IF(AF309<($B$6*$B$7),AF309+1,"") -> 1 | AG310: =F311
A311: =IF(A310<($B$6*$B$7),A310+1,"") | B311: =IF(A311="","",F310) | C311: =IF(A311="","",(B311*$B$8)) | D311: =IF(A311="","", $B$5) | E311: =IF(D311="","",(D311-C311)) | F311: =IF(A311="","", B311-E311) | G311: =IF(A311="","", (G310+C311)) | H311: =IF(A311="","",(H310+E311)) | L311: =IF(L310<($B$6*$B$7),L310+1,"") | M311: =IF(L311="", "", R310) | N311: =IF(L311="","",$B$5) | O311: =IF(L311="","",M311-N311) | P311: =IF(L311="","",O310*$B$8) | Q311: =IF(L311="","",N311-P311) | R311: =IF(L311="","",O311*(1+$B$8)) | S311: =IF(L311="","",S310+P311) | T311: =IF(L311="","",Q311+T310) | AF311: =IF(AF310<($B$6*$B$7),AF310+1,"") -> 2 | AG311: =F312
A312: =IF(A311<($B$6*$B$7),A311+1,"") | B312: =IF(A312="","",F311) | C312: =IF(A312="","",(B312*$B$8)) | D312: =IF(A312="","", $B$5) | E312: =IF(D312="","",(D312-C312)) | F312: =IF(A312="","", B312-E312) | G312: =IF(A312="","", (G311+C312)) | H312: =IF(A312="","",(H311+E312)) | L312: =IF(L311<($B$6*$B$7),L311+1,"") | M312: =IF(L312="", "", R311) | N312: =IF(L312="","",$B$5) | O312: =IF(L312="","",M312-N312) | P312: =IF(L312="","",O311*$B$8) | Q312: =IF(L312="","",N312-P312) | R312: =IF(L312="","",O312*(1+$B$8)) | S312: =IF(L312="","",S311+P312) | T312: =IF(L312="","",Q312+T311) | AF312: =IF(AF311<($B$6*$B$7),AF311+1,"") -> 3 | AG312: =F313
A313: =IF(A312<($B$6*$B$7),A312+1,"") | B313: =IF(A313="","",F312) | C313: =IF(A313="","",(B313*$B$8)) | D313: =IF(A313="","", $B$5) | E313: =IF(D313="","",(D313-C313)) | F313: =IF(A313="","", B313-E313) | G313: =IF(A313="","", (G312+C313)) | H313: =IF(A313="","",(H312+E313)) | L313: =IF(L312<($B$6*$B$7),L312+1,"") | M313: =IF(L313="", "", R312) | N313: =IF(L313="","",$B$5) | O313: =IF(L313="","",M313-N313) | P313: =IF(L313="","",O312*$B$8) | Q313: =IF(L313="","",N313-P313) | R313: =IF(L313="","",O313*(1+$B$8)) | S313: =IF(L313="","",S312+P313) | T313: =IF(L313="","",Q313+T312) | AF313: =IF(AF312<($B$6*$B$7),AF312+1,"") -> 4 | AG313: =F314
A314: =IF(A313<($B$6*$B$7),A313+1,"") | B314: =IF(A314="","",F313) | C314: =IF(A314="","",(B314*$B$8)) | D314: =IF(A314="","", $B$5) | E314: =IF(D314="","",(D314-C314)) | F314: =IF(A314="","", B314-E314) | G314: =IF(A314="","", (G313+C314)) | H314: =IF(A314="","",(H313+E314)) | L314: =IF(L313<($B$6*$B$7),L313+1,"") | M314: =IF(L314="", "", R313) | N314: =IF(L314="","",$B$5) | O314: =IF(L314="","",M314-N314) | P314: =IF(L314="","",O313*$B$8) | Q314: =IF(L314="","",N314-P314) | R314: =IF(L314="","",O314*(1+$B$8)) | S314: =IF(L314="","",S313+P314) | T314: =IF(L314="","",Q314+T313) | AF314: =IF(AF313<($B$6*$B$7),AF313+1,"") -> 5 | AG314: =F315
A315: =IF(A314<($B$6*$B$7),A314+1,"") | B315: =IF(A315="","",F314) | C315: =IF(A315="","",(B315*$B$8)) | D315: =IF(A315="","", $B$5) | E315: =IF(D315="","",(D315-C315)) | F315: =IF(A315="","", B315-E315) | G315: =IF(A315="","", (G314+C315)) | H315: =IF(A315="","",(H314+E315)) | L315: =IF(L314<($B$6*$B$7),L314+1,"") | M315: =IF(L315="", "", R314) | N315: =IF(L315="","",$B$5) | O315: =IF(L315="","",M315-N315) | P315: =IF(L315="","",O314*$B$8) | Q315: =IF(L315="","",N315-P315) | R315: =IF(L315="","",O315*(1+$B$8)) | S315: =IF(L315="","",S314+P315) | T315: =IF(L315="","",Q315+T314) | AF315: =IF(AF314<($B$6*$B$7),AF314+1,"") -> 6 | AG315: =F316
A316: =IF(A315<($B$6*$B$7),A315+1,"") | B316: =IF(A316="","",F315) | C316: =IF(A316="","",(B316*$B$8)) | D316: =IF(A316="","", $B$5) | E316: =IF(D316="","",(D316-C316)) | F316: =IF(A316="","", B316-E316) | G316: =IF(A316="","", (G315+C316)) | H316: =IF(A316="","",(H315+E316)) | L316: =IF(L315<($B$6*$B$7),L315+1,"") | M316: =IF(L316="", "", R315) | N316: =IF(L316="","",$B$5) | O316: =IF(L316="","",M316-N316) | P316: =IF(L316="","",O315*$B$8) | Q316: =IF(L316="","",N316-P316) | R316: =IF(L316="","",O316*(1+$B$8)) | S316: =IF(L316="","",S315+P316) | T316: =IF(L316="","",Q316+T315) | AF316: =IF(AF315<($B$6*$B$7),AF315+1,"") -> 7 | AG316: =F317
A317: =IF(A316<($B$6*$B$7),A316+1,"") | B317: =IF(A317="","",F316) | C317: =IF(A317="","",(B317*$B$8)) | D317: =IF(A317="","", $B$5) | E317: =IF(D317="","",(D317-C317)) | F317: =IF(A317="","", B317-E317) | G317: =IF(A317="","", (G316+C317)) | H317: =IF(A317="","",(H316+E317)) | L317: =IF(L316<($B$6*$B$7),L316+1,"") | M317: =IF(L317="", "", R316) | N317: =IF(L317="","",$B$5) | O317: =IF(L317="","",M317-N317) | P317: =IF(L317="","",O316*$B$8) | Q317: =IF(L317="","",N317-P317) | R317: =IF(L317="","",O317*(1+$B$8)) | S317: =IF(L317="","",S316+P317) | T317: =IF(L317="","",Q317+T316) | AF317: =IF(AF316<($B$6*$B$7),AF316+1,"") -> 8 | AG317: =F318
A318: =IF(A317<($B$6*$B$7),A317+1,"") | B318: =IF(A318="","",F317) | C318: =IF(A318="","",(B318*$B$8)) | D318: =IF(A318="","", $B$5) | E318: =IF(D318="","",(D318-C318)) | F318: =IF(A318="","", B318-E318) | G318: =IF(A318="","", (G317+C318)) | H318: =IF(A318="","",(H317+E318)) | L318: =IF(L317<($B$6*$B$7),L317+1,"") | M318: =IF(L318="", "", R317) | N318: =IF(L318="","",$B$5) | O318: =IF(L318="","",M318-N318) | P318: =IF(L318="","",O317*$B$8) | Q318: =IF(L318="","",N318-P318) | R318: =IF(L318="","",O318*(1+$B$8)) | S318: =IF(L318="","",S317+P318) | T318: =IF(L318="","",Q318+T317) | AF318: =IF(AF317<($B$6*$B$7),AF317+1,"") -> 9 | AG318: =F319
A319: =IF(A318<($B$6*$B$7),A318+1,"") | B319: =IF(A319="","",F318) | C319: =IF(A319="","",(B319*$B$8)) | D319: =IF(A319="","", $B$5) | E319: =IF(D319="","",(D319-C319)) | F319: =IF(A319="","", B319-E319) | G319: =IF(A319="","", (G318+C319)) | H319: =IF(A319="","",(H318+E319)) | L319: =IF(L318<($B$6*$B$7),L318+1,"") | M319: =IF(L319="", "", R318) | N319: =IF(L319="","",$B$5) | O319: =IF(L319="","",M319-N319) | P319: =IF(L319="","",O318*$B$8) | Q319: =IF(L319="","",N319-P319) | R319: =IF(L319="","",O319*(1+$B$8)) | S319: =IF(L319="","",S318+P319) | T319: =IF(L319="","",Q319+T318) | AF319: =IF(AF318<($B$6*$B$7),AF318+1,"") -> 10 | AG319: =F320
A320: =IF(A319<($B$6*$B$7),A319+1,"") | B320: =IF(A320="","",F319) | C320: =IF(A320="","",(B320*$B$8)) | D320: =IF(A320="","", $B$5) | E320: =IF(D320="","",(D320-C320)) | F320: =IF(A320="","", B320-E320) | G320: =IF(A320="","", (G319+C320)) | H320: =IF(A320="","",(H319+E320)) | L320: =IF(L319<($B$6*$B$7),L319+1,"") | M320: =IF(L320="", "", R319) | N320: =IF(L320="","",$B$5) | O320: =IF(L320="","",M320-N320) | P320: =IF(L320="","",O319*$B$8) | Q320: =IF(L320="","",N320-P320) | R320: =IF(L320="","",O320*(1+$B$8)) | S320: =IF(L320="","",S319+P320) | T320: =IF(L320="","",Q320+T319) | AF320: =IF(AF319<($B$6*$B$7),AF319+1,"") -> 11 | AG320: =F321
A321: =IF(A320<($B$6*$B$7),A320+1,"") | B321: =IF(A321="","",F320) | C321: =IF(A321="","",(B321*$B$8)) | D321: =IF(A321="","", $B$5) | E321: =IF(D321="","",(D321-C321)) | F321: =IF(A321="","", B321-E321) | G321: =IF(A321="","", (G320+C321)) | H321: =IF(A321="","",(H320+E321)) | L321: =IF(L320<($B$6*$B$7),L320+1,"") | M321: =IF(L321="", "", R320) | N321: =IF(L321="","",$B$5) | O321: =IF(L321="","",M321-N321) | P321: =IF(L321="","",O320*$B$8) | Q321: =IF(L321="","",N321-P321) | R321: =IF(L321="","",O321*(1+$B$8)) | S321: =IF(L321="","",S320+P321) | T321: =IF(L321="","",Q321+T320) | AF321: =IF(AF320<($B$6*$B$7),AF320+1,"") -> 12 | AG321: =F322
... A740: =IF(A739<($B$6*$B$7),A739+1,"") | B740: =IF(A740="","",F739) | C740: =IF(A740="","",(B740*$B$8)) | D740: =IF(A740="","", $B$5) | E740: =IF(D740="","",(D740-C740)) | F740: =IF(A740="","", B740-E740) | G740: =IF(A740="","", (G739+C740)) | H740: =IF(A740="","",(H739+E740)) | L740: =IF(L739<($B$6*$B$7),L739+1,"") | M740: =IF(L740="", "", R739) | N740: =IF(L740="","",$B$5) | O740: =IF(L740="","",M740-N740) | P740: =IF(L740="","",O739*$B$8) | Q740: =IF(L740="","",N740-P740) | R740: =IF(L740="","",O740*(1+$B$8)) | S740: =IF(L740="","",S739+P740) | T740: =IF(L740="","",Q740+T739) | AF740: =IF(AF739<($B$6*$B$7),AF739+1,"") | AG740: =F741
A741: =IF(A740<($B$6*$B$7),A740+1,"") | B741: =IF(A741="","",F740) | C741: =IF(A741="","",(B741*$B$8)) | D741: =IF(A741="","", $B$5) | E741: =IF(D741="","",(D741-C741)) | F741: =IF(A741="","", B741-E741) | G741: =IF(A741="","", (G740+C741)) | H741: =IF(A741="","",(H740+E741)) | L741: =IF(L740<($B$6*$B$7),L740+1,"") | M741: =IF(L741="", "", R740) | N741: =IF(L741="","",$B$5) | O741: =IF(L741="","",M741-N741) | P741: =IF(L741="","",O740*$B$8) | Q741: =IF(L741="","",N741-P741) | R741: =IF(L741="","",O741*(1+$B$8)) | S741: =IF(L741="","",S740+P741) | T741: =IF(L741="","",Q741+T740) | AF741: =IF(AF740<($B$6*$B$7),AF740+1,"")
A742: =IF(A741<($B$6*$B$7),A741+1,"") | B742: =IF(A742="","",F741) | C742: =IF(A742="","",(B742*$B$8)) | D742: =IF(A742="","", $B$5) | E742: =IF(D742="","",(D742-C742)) | F742: =IF(A742="","", B742-E742) | G742: =IF(A742="","", (G741+C742)) | H742: =IF(A742="","",(H741+E742)) | L742: =IF(L741<($B$6*$B$7),L741+1,"") | M742: =IF(L742="", "", R741) | N742: =IF(L742="","",$B$5) | O742: =IF(L742="","",M742-N742) | P742: =IF(L742="","",O741*$B$8) | Q742: =IF(L742="","",N742-P742) | R742: =IF(L742="","",O742*(1+$B$8)) | S742: =IF(L742="","",S741+P742) | T742: =IF(L742="","",Q742+T741) | AF742: =IF(AF741<($B$6*$B$7),AF741+1,"")
A743: =IF(A742<($B$6*$B$7),A742+1,"") | B743: =IF(A743="","",F742) | C743: =IF(A743="","",(B743*$B$8)) | D743: =IF(A743="","", $B$5) | E743: =IF(D743="","",(D743-C743)) | F743: =IF(A743="","", B743-E743) | G743: =IF(A743="","", (G742+C743)) | H743: =IF(A743="","",(H742+E743)) | L743: =IF(L742<($B$6*$B$7),L742+1,"") | M743: =IF(L743="", "", R742) | N743: =IF(L743="","",$B$5) | O743: =IF(L743="","",M743-N743) | P743: =IF(L743="","",O742*$B$8) | Q743: =IF(L743="","",N743-P743) | R743: =IF(L743="","",O743*(1+$B$8)) | S743: =IF(L743="","",S742+P743) | T743: =IF(L743="","",Q743+T742) | AF743: =IF(AF742<($B$6*$B$7),AF742+1,"")
A744: =IF(A743<($B$6*$B$7),A743+1,"") | B744: =IF(A744="","",F743) | C744: =IF(A744="","",(B744*$B$8)) | D744: =IF(A744="","", $B$5) | E744: =IF(D744="","",(D744-C744)) | F744: =IF(A744="","", B744-E744) | G744: =IF(A744="","", (G743+C744)) | H744: =IF(A744="","",(H743+E744)) | L744: =IF(L743<($B$6*$B$7),L743+1,"") | M744: =IF(L744="", "", R743) | N744: =IF(L744="","",$B$5) | O744: =IF(L744="","",M744-N744) | P744: =IF(L744="","",O743*$B$8) | Q744: =IF(L744="","",N744-P744) | R744: =IF(L744="","",O744*(1+$B$8)) | S744: =IF(L744="","",S743+P744) | T744: =IF(L744="","",Q744+T743) | AF744: =IF(AF743<($B$6*$B$7),AF743+1,"")
A745: =IF(A744<($B$6*$B$7),A744+1,"") | B745: =IF(A745="","",F744) | C745: =IF(A745="","",(B745*$B$8)) | D745: =IF(A745="","", $B$5) | E745: =IF(D745="","",(D745-C745)) | F745: =IF(A745="","", B745-E745) | G745: =IF(A745="","", (G744+C745)) | H745: =IF(A745="","",(H744+E745)) | L745: =IF(L744<($B$6*$B$7),L744+1,"") | M745: =IF(L745="", "", R744) | N745: =IF(L745="","",$B$5) | O745: =IF(L745="","",M745-N745) | P745: =IF(L745="","",O744*$B$8) | Q745: =IF(L745="","",N745-P745) | R745: =IF(L745="","",O745*(1+$B$8)) | S745: =IF(L745="","",S744+P745) | T745: =IF(L745="","",Q745+T744) | AF745: =IF(AF744<($B$6*$B$7),AF744+1,"")
A746: =IF(A745<($B$6*$B$7),A745+1,"") | B746: =IF(A746="","",F745) | C746: =IF(A746="","",(B746*$B$8)) | D746: =IF(A746="","", $B$5) | E746: =IF(D746="","",(D746-C746)) | F746: =IF(A746="","", B746-E746) | G746: =IF(A746="","", (G745+C746)) | H746: =IF(A746="","",(H745+E746)) | L746: =IF(L745<($B$6*$B$7),L745+1,"") | M746: =IF(L746="", "", R745) | N746: =IF(L746="","",$B$5) | O746: =IF(L746="","",M746-N746) | P746: =IF(L746="","",O745*$B$8) | Q746: =IF(L746="","",N746-P746) | R746: =IF(L746="","",O746*(1+$B$8)) | S746: =IF(L746="","",S745+P746) | T746: =IF(L746="","",Q746+T745) | AF746: =IF(AF745<($B$6*$B$7),AF745+1,"")
A747: =IF(A746<($B$6*$B$7),A746+1,"") | B747: =IF(A747="","",F746) | C747: =IF(A747="","",(B747*$B$8)) | D747: =IF(A747="","", $B$5) | E747: =IF(D747="","",(D747-C747)) | F747: =IF(A747="","", B747-E747) | G747: =IF(A747="","", (G746+C747)) | H747: =IF(A747="","",(H746+E747)) | L747: =IF(L746<($B$6*$B$7),L746+1,"") | M747: =IF(L747="", "", R746) | N747: =IF(L747="","",$B$5) | O747: =IF(L747="","",M747-N747) | P747: =IF(L747="","",O746*$B$8) | Q747: =IF(L747="","",N747-P747) | R747: =IF(L747="","",O747*(1+$B$8)) | S747: =IF(L747="","",S746+P747) | T747: =IF(L747="","",Q747+T746) | AF747: =IF(AF746<($B$6*$B$7),AF746+1,"")
A748: =IF(A747<($B$6*$B$7),A747+1,"") | B748: =IF(A748="","",F747) | C748: =IF(A748="","",(B748*$B$8)) | D748: =IF(A748="","", $B$5) | E748: =IF(D748="","",(D748-C748)) | F748: =IF(A748="","", B748-E748) | G748: =IF(A748="","", (G747+C748)) | H748: =IF(A748="","",(H747+E748)) | L748: =IF(L747<($B$6*$B$7),L747+1,"") | M748: =IF(L748="", "", R747) | N748: =IF(L748="","",$B$5) | O748: =IF(L748="","",M748-N748) | P748: =IF(L748="","",O747*$B$8) | Q748: =IF(L748="","",N748-P748) | R748: =IF(L748="","",O748*(1+$B$8)) | S748: =IF(L748="","",S747+P748) | T748: =IF(L748="","",Q748+T747) | AF748: =IF(AF747<($B$6*$B$7),AF747+1,"")
A749: =IF(A748<($B$6*$B$7),A748+1,"") | B749: =IF(A749="","",F748) | C749: =IF(A749="","",(B749*$B$8)) | D749: =IF(A749="","", $B$5) | E749: =IF(D749="","",(D749-C749)) | F749: =IF(A749="","", B749-E749) | G749: =IF(A749="","", (G748+C749)) | H749: =IF(A749="","",(H748+E749)) | L749: =IF(L748<($B$6*$B$7),L748+1,"") | M749: =IF(L749="", "", R748) | N749: =IF(L749="","",$B$5) | O749: =IF(L749="","",M749-N749) | P749: =IF(L749="","",O748*$B$8) | Q749: =IF(L749="","",N749-P749) | R749: =IF(L749="","",O749*(1+$B$8)) | S749: =IF(L749="","",S748+P749) | T749: =IF(L749="","",Q749+T748) | AF749: =IF(AF748<($B$6*$B$7),AF748+1,"")
A750: =IF(A749<($B$6*$B$7),A749+1,"") | B750: =IF(A750="","",F749) | C750: =IF(A750="","",(B750*$B$8)) | D750: =IF(A750="","", $B$5) | E750: =IF(D750="","",(D750-C750)) | F750: =IF(A750="","", B750-E750) | G750: =IF(A750="","", (G749+C750)) | H750: =IF(A750="","",(H749+E750)) | L750: =IF(L749<($B$6*$B$7),L749+1,"") | M750: =IF(L750="", "", R749) | N750: =IF(L750="","",$B$5) | O750: =IF(L750="","",M750-N750) | P750: =IF(L750="","",O749*$B$8) | Q750: =IF(L750="","",N750-P750) | R750: =IF(L750="","",O750*(1+$B$8)) | S750: =IF(L750="","",S749+P750) | T750: =IF(L750="","",Q750+T749) | AF750: =IF(AF749<($B$6*$B$7),AF749+1,"")
A751: =IF(A750<($B$6*$B$7),A750+1,"") | B751: =IF(A751="","",F750) | C751: =IF(A751="","",(B751*$B$8)) | D751: =IF(A751="","", $B$5) | E751: =IF(D751="","",(D751-C751)) | F751: =IF(A751="","", B751-E751) | G751: =IF(A751="","", (G750+C751)) | H751: =IF(A751="","",(H750+E751)) | L751: =IF(L750<($B$6*$B$7),L750+1,"") | M751: =IF(L751="", "", R750) | N751: =IF(L751="","",$B$5) | O751: =IF(L751="","",M751-N751) | P751: =IF(L751="","",O750*$B$8) | Q751: =IF(L751="","",N751-P751) | R751: =IF(L751="","",O751*(1+$B$8)) | S751: =IF(L751="","",S750+P751) | T751: =IF(L751="","",Q751+T750) | AF751: =IF(AF750<($B$6*$B$7),AF750+1,"")
A752: =IF(A751<($B$6*$B$7),A751+1,"") | B752: =IF(A752="","",F751) | C752: =IF(A752="","",(B752*$B$8)) | D752: =IF(A752="","", $B$5) | E752: =IF(D752="","",(D752-C752)) | F752: =IF(A752="","", B752-E752) | G752: =IF(A752="","", (G751+C752)) | H752: =IF(A752="","",(H751+E752)) | L752: =IF(L751<($B$6*$B$7),L751+1,"") | M752: =IF(L752="", "", R751) | N752: =IF(L752="","",$B$5) | O752: =IF(L752="","",M752-N752) | P752: =IF(L752="","",O751*$B$8) | Q752: =IF(L752="","",N752-P752) | R752: =IF(L752="","",O752*(1+$B$8)) | S752: =IF(L752="","",S751+P752) | T752: =IF(L752="","",Q752+T751) | AF752: =IF(AF751<($B$6*$B$7),AF751+1,"")
... A769: =IF(A768<($B$6*$B$7),A768+1,"") | B769: =IF(A769="","",F768) | C769: =IF(A769="","",(B769*$B$8)) | D769: =IF(A769="","", $B$5) | E769: =IF(D769="","",(D769-C769)) | F769: =IF(A769="","", B769-E769) | G769: =IF(A769="","", (G768+C769)) | H769: =IF(A769="","",(H768+E769)) | L769: =IF(L768<($B$6*$B$7),L768+1,"") | M769: =IF(L769="", "", R768) | N769: =IF(L769="","",$B$5) | O769: =IF(L769="","",M769-N769) | P769: =IF(L769="","",O768*$B$8) | Q769: =IF(L769="","",N769-P769) | R769: =IF(L769="","",O769*(1+$B$8)) | S769: =IF(L769="","",S768+P769) | T769: =IF(L769="","",Q769+T768) | AF769: =IF(AF768<($B$6*$B$7),AF768+1,"")
A770: =IF(A769<($B$6*$B$7),A769+1,"") | B770: =IF(A770="","",F769) | C770: =IF(A770="","",(B770*$B$8)) | D770: =IF(A770="","", $B$5) | E770: =IF(D770="","",(D770-C770)) | F770: =IF(A770="","", B770-E770) | G770: =IF(A770="","", (G769+C770)) | H770: =IF(A770="","",(H769+E770)) | AF770: =IF(AF769<($B$6*$B$7),AF769+1,"")
A771: =IF(A770<($B$6*$B$7),A770+1,"") | B771: =IF(A771="","",F770) | C771: =IF(A771="","",(B771*$B$8)) | D771: =IF(A771="","", $B$5) | E771: =IF(D771="","",(D771-C771)) | F771: =IF(A771="","", B771-E771) | G771: =IF(A771="","", (G770+C771)) | H771: =IF(A771="","",(H770+E771)) | AF771: =IF(AF770<($B$6*$B$7),AF770+1,"")
A772: =IF(A771<($B$6*$B$7),A771+1,"") | B772: =IF(A772="","",F771) | C772: =IF(A772="","",(B772*$B$8)) | D772: =IF(A772="","", $B$5) | E772: =IF(D772="","",(D772-C772)) | F772: =IF(A772="","", B772-E772) | G772: =IF(A772="","", (G771+C772)) | H772: =IF(A772="","",(H771+E772)) | AF772: =IF(AF771<($B$6*$B$7),AF771+1,"")
A773: =IF(A772<($B$6*$B$7),A772+1,"") | B773: =IF(A773="","",F772) | C773: =IF(A773="","",(B773*$B$8)) | D773: =IF(A773="","", $B$5) | E773: =IF(D773="","",(D773-C773)) | F773: =IF(A773="","", B773-E773) | G773: =IF(A773="","", (G772+C773)) | H773: =IF(A773="","",(H772+E773)) | AF773: =IF(AF772<($B$6*$B$7),AF772+1,"")
A774: =IF(A773<($B$6*$B$7),A773+1,"") | B774: =IF(A774="","",F773) | C774: =IF(A774="","",(B774*$B$8)) | D774: =IF(A774="","", $B$5) | E774: =IF(D774="","",(D774-C774)) | F774: =IF(A774="","", B774-E774) | G774: =IF(A774="","", (G773+C774)) | H774: =IF(A774="","",(H773+E774)) | AF774: =IF(AF773<($B$6*$B$7),AF773+1,"")
A775: =IF(A774<($B$6*$B$7),A774+1,"") | B775: =IF(A775="","",F774) | C775: =IF(A775="","",(B775*$B$8)) | D775: =IF(A775="","", $B$5) | E775: =IF(D775="","",(D775-C775)) | F775: =IF(A775="","", B775-E775) | G775: =IF(A775="","", (G774+C775)) | H775: =IF(A775="","",(H774+E775)) | AF775: =IF(AF774<($B$6*$B$7),AF774+1,"")
A776: =IF(A775<($B$6*$B$7),A775+1,"") | B776: =IF(A776="","",F775) | C776: =IF(A776="","",(B776*$B$8)) | D776: =IF(A776="","", $B$5) | E776: =IF(D776="","",(D776-C776)) | F776: =IF(A776="","", B776-E776) | G776: =IF(A776="","", (G775+C776)) | H776: =IF(A776="","",(H775+E776)) | AF776: =IF(AF775<($B$6*$B$7),AF775+1,"")
A777: =IF(A776<($B$6*$B$7),A776+1,"") | B777: =IF(A777="","",F776) | C777: =IF(A777="","",(B777*$B$8)) | D777: =IF(A777="","", $B$5) | E777: =IF(D777="","",(D777-C777)) | F777: =IF(A777="","", B777-E777) | G777: =IF(A777="","", (G776+C777)) | H777: =IF(A777="","",(H776+E777)) | AF777: =IF(AF776<($B$6*$B$7),AF776+1,"")
A778: =IF(A777<($B$6*$B$7),A777+1,"") | B778: =IF(A778="","",F777) | C778: =IF(A778="","",(B778*$B$8)) | D778: =IF(A778="","", $B$5) | E778: =IF(D778="","",(D778-C778)) | F778: =IF(A778="","", B778-E778) | G778: =IF(A778="","", (G777+C778)) | H778: =IF(A778="","",(H777+E778)) | AF778: =IF(AF777<($B$6*$B$7),AF777+1,"")
A779: =IF(A778<($B$6*$B$7),A778+1,"") | B779: =IF(A779="","",F778) | C779: =IF(A779="","",(B779*$B$8)) | D779: =IF(A779="","", $B$5) | E779: =IF(D779="","",(D779-C779)) | F779: =IF(A779="","", B779-E779) | G779: =IF(A779="","", (G778+C779)) | H779: =IF(A779="","",(H778+E779)) | AF779: =IF(AF778<($B$6*$B$7),AF778+1,"")
A780: =IF(A779<($B$6*$B$7),A779+1,"") | B780: =IF(A780="","",F779) | C780: =IF(A780="","",(B780*$B$8)) | D780: =IF(A780="","", $B$5) | E780: =IF(D780="","",(D780-C780)) | F780: =IF(A780="","", B780-E780) | G780: =IF(A780="","", (G779+C780)) | H780: =IF(A780="","",(H779+E780)) | AF780: =IF(AF779<($B$6*$B$7),AF779+1,"")
A781: =IF(A780<($B$6*$B$7),A780+1,"") | B781: =IF(A781="","",F780) | C781: =IF(A781="","",(B781*$B$8)) | D781: =IF(A781="","", $B$5) | E781: =IF(D781="","",(D781-C781)) | F781: =IF(A781="","", B781-E781) | G781: =IF(A781="","", (G780+C781)) | H781: =IF(A781="","",(H780+E781)) | AF781: =IF(AF780<($B$6*$B$7),AF780+1,"")
... A829: =IF(A828<($B$6*$B$7),A828+1,"") | B829: =IF(A829="","",F828) | C829: =IF(A829="","",(B829*$B$8)) | D829: =IF(A829="","", $B$5) | E829: =IF(D829="","",(D829-C829)) | F829: =IF(A829="","", B829-E829) | G829: =IF(A829="","", (G828+C829)) | H829: =IF(A829="","",(H828+E829)) | AF829: =IF(AF828<($B$6*$B$7),AF828+1,"")
A830: =IF(A829<($B$6*$B$7),A829+1,"") | B830: =IF(A830="","",F829) | C830: =IF(A830="","",(B830*$B$8)) | D830: =IF(A830="","", $B$5) | E830: =IF(D830="","",(D830-C830)) | F830: =IF(A830="","", B830-E830) | G830: =IF(A830="","", (G829+C830)) | H830: =IF(A830="","",(H829+E830))
A831: =IF(A830<($B$6*$B$7),A830+1,"") | B831: =IF(A831="","",F830) | C831: =IF(A831="","",(B831*$B$8)) | D831: =IF(A831="","", $B$5) | E831: =IF(D831="","",(D831-C831)) | F831: =IF(A831="","", B831-E831) | G831: =IF(A831="","", (G830+C831)) | H831: =IF(A831="","",(H830+E831))
A832: =IF(A831<($B$6*$B$7),A831+1,"") | B832: =IF(A832="","",F831) | C832: =IF(A832="","",(B832*$B$8)) | D832: =IF(A832="","", $B$5) | E832: =IF(D832="","",(D832-C832)) | F832: =IF(A832="","", B832-E832) | G832: =IF(A832="","", (G831+C832)) | H832: =IF(A832="","",(H831+E832))
...

Sheet Investment(Single + Annuity)
A1: INVESTMENTS(Single + Annuity)
A3: Givens | E3: Unkowns | S3: Initial Single Investment | T3: Arrears
A4: Initial Single inestment | E4: Loan Type: | F4: Arrears | H4: Investment component(Variable): | I4: Present Value | S4: Payment | T4: Advance
A5: Annuity Cashflow | S5: Period per year
S6: Number of years
S7: Present Value
A8: Effective Periodic interest rate | H8: VALUE | I8: =IF(AND(F4=T3,I4=S3),'Investments back office'!I10,IF(AND(F4=T3,I4=S4),'Investments back office'!I11,IF(AND(F4=T3,I4=S5),'Investments back office'!I12,IF(AND(F4=T3,I4=S6),'Investments back office'!I13,IF(AND(F4=T3,I4=S7),'Investments back office'!I16,IF(AND(F4=T3,I4=S8),'Investments back office'!I17,IF(AND(F4=T3,I4=S9),'Investments back office'!I18,IF(AND(F4=T3,I4=S10),'Investments back office'!I19,IF(AND(F4=T4,I4=S3),'Investments back office'!J10,IF(AND(F4=T4,I4=S4),'Investments back office'!J11,IF(AND(F4=T4,I4=S5),'Investments back office'!J12,IF(AND(F4=T4,I4=S6),'Investments back office'!J13,IF(AND(F4=T4,I4=S7),'Investments back office'!J16,IF(AND(F4=T4,I4=S8),'Investments back office'!J17,IF(AND(F4=T4,I4=S9),'Investments back office'!J18,IF(AND(F4=T4,I4=S10),'Investments back office'!J19)))))))))))))))) -> 0 | S8: Total Interest
A9: Specific time (Year) | S9: Future Value
A10: Specific time (Periods) | S10: Total Periods
A11: Number of Payment (K) | H11: REAL FUTURE VALUE | I11: =IF(I4=I18,I8*(1+5%)^(-B9)," ")
A12: Start period (Interest)
A13: End period(Interest)
A14: Future Value | E14: To Convert Interest Rates:
E16: Home
I18: Future Value

Sheet Investments back office
A1: Givens
A2: Initial Single inestment | B2: ='Investment(Single + Annuity)'!B4 -> 0
A3: Annuity Cashflow | B3: ='Investment(Single + Annuity)'!B5 -> 0
A4: Years | B4: ='Investment(Single + Annuity)'!B6 -> 0
A6: Effective Periodic or nominal interest rate | B6: ='Investment(Single + Annuity)'!B8 -> 0
A7: Specific time (Year) | B7: ='Investment(Single + Annuity)'!B9 -> 0
A8: Pecific year in periods | B8: ='Investment(Single + Annuity)'!B10 -> 0
A9: Number of Payment (K) | B9: ='Assignment4 (User Interface)'!B11 -> 1 | I9: Arrears | J9: Advance
A10: Start Period (Interest) | B10: ='Assignment4 (User Interface)'!B12 -> 1 | H10: Initial Single Investment | I10: =(B12-(B3*(((1+B6)^(B7*B8)-1)/B6)))/((1+B6)^(B7*B8)) -> #DIV/0! | J10: =(B12-(B3*(1+B6)*(((1+B6)^(B7*B8)-1)/B6)))/((1+B6)^(B7*B8)) -> #DIV/0!
A11: End Period (Interest) | B11: ='Assignment4 (User Interface)'!B13 -> 2 | H11: Payment | I11: =((B12 - (B2*(1+B6)^(B7*B8)))*B6)/(((1+B6)^(B7*B8))-1) -> #DIV/0! | J11: =((B12 - (B2*(1+B6)^(B7*B8)))*B6)/((1+B6)*(((1+B6)^(B7*B8))-1)) -> #DIV/0!
A12: Future Value | B12: 1002573.1 | H12: Period to of investment | I12: =((LN((B12*B6+B3)/(B2*B6+B3)))/(LN(1+B6)))*(1/B7) -> #DIV/0! | J12: =((LN((B12 +( B3*(1+B6))/B6)/(B2 + (B3*(1+B6))/B6)))/(LN(1+B6)))*(1/B7) -> #DIV/0!
H13: Number of years | I13: =((LN((B12*B6+B3)/(B2*B6+B3)))/(LN(1+B6)))*(1/B8) -> #DIV/0! | J13: =((LN((B12 +( B3*(1+B6))/B6)/(B2 + (B3*(1+B6))/B6)))/(LN(1+B6)))*(1/B8) -> #DIV/0!
H16: Present Value | I16: =I18*(1+B6)^(-B7*B8) -> 0 | J16: =J18*(1+B6)^(-B7*B8) -> 0
H17: Total Interest | I17: {=LOOKUP(2, 1/(G22:G607<>""), G22:G607)} -> 0 | J17: {=LOOKUP(2, 1/(P22:P607<>""), P22:P607)} -> 0
H18: Future Value | I18: {=LOOKUP(2, 1/(F22:F607<>""), F22:F607)} -> 0 | J18: {=LOOKUP(2, 1/(O22:O607<>""), O22:O607)} -> 0
H19: Total Periods | I19: =((LN((B12*B6+B3)/(B2*B6+B3)))/(LN(1+B6))) -> #DIV/0! | J19: =((LN((B12 +( B3*(1+B6))/B6)/(B2 + (B3*(1+B6))/B6)))/(LN(1+B6))) -> #DIV/0!
A20: Amortization table (Arrears) | J20: Amortization table (Advance)
A21: Period | B21: Balance at Start | C21: Interest | D21: Payment | E21: Capital | F21: Balance at end | G21: Interest so far | J21: Period | K21: Balance at Start | L21: Interest | M21: Payment | N21: Capital | O21: Balance at end | P21: Interest so far
A22: 1 | B22: =B2 -> 0 | C22: =$B$6*B22 -> 0 | D22: =$B$3 -> 0 | E22: =D22-C22 -> 0 | F22: =B22+C22+D22 -> 0 | G22: =C22 -> 0 | J22: 1 | K22: =B2 -> 0 | L22: =$B$6 *( M22 + K22) -> 0 | M22: =$B$3 -> 0 | N22: =M22-L22 -> 0 | O22: =K22+L22+M22 -> 0 | P22: =L22 -> 0
A23: =IF(A22<($B$7*$B$8),A22+1,"") | B23: =IF(A23="","",F22) | C23: =IF(A23="","",(B23*$B$6)) | D23: =IF(A23="","", $B$3) | E23: =IF(D23="","",(D23-C23)) | F23: =IF(A23="","", B23+C23+D23) | G23: =IF(A23="","", (G22+C23)) | J23: =IF(J22<($B$7*$B$8),J22+1,"") | K23: =IF(J23="","",O22) | L23: =IF(J23="","",((K23 + M23)*$B$6)) | M23: =IF(J23="","", $B$3) | N23: =IF(M23="","",(M23-L23)) | O23: =IF(J23="","", K23+L23+M23) | P23: =IF(J23="","", (P22+L23))
A24: =IF(A23<($B$7*$B$8),A23+1,"") | B24: =IF(A24="","",F23) | C24: =IF(A24="","",(B24*$B$6)) | D24: =IF(A24="","", $B$3) | E24: =IF(D24="","",(D24-C24)) | F24: =IF(A24="","", B24+C24+D24) | G24: =IF(A24="","", (G23+C24)) | J24: =IF(J23<($B$7*$B$8),J23+1,"") | K24: =IF(J24="","",O23) | L24: =IF(J24="","",((K24 + M24)*$B$6)) | M24: =IF(J24="","", $B$3) | N24: =IF(M24="","",(M24-L24)) | O24: =IF(J24="","", K24+L24+M24) | P24: =IF(J24="","", (P23+L24))
A25: =IF(A24<($B$7*$B$8),A24+1,"") | B25: =IF(A25="","",F24) | C25: =IF(A25="","",(B25*$B$6)) | D25: =IF(A25="","", $B$3) | E25: =IF(D25="","",(D25-C25)) | F25: =IF(A25="","", B25+C25+D25) | G25: =IF(A25="","", (G24+C25)) | J25: =IF(J24<($B$7*$B$8),J24+1,"") | K25: =IF(J25="","",O24) | L25: =IF(J25="","",((K25 + M25)*$B$6)) | M25: =IF(J25="","", $B$3) | N25: =IF(M25="","",(M25-L25)) | O25: =IF(J25="","", K25+L25+M25) | P25: =IF(J25="","", (P24+L25))
A26: =IF(A25<($B$7*$B$8),A25+1,"") | B26: =IF(A26="","",F25) | C26: =IF(A26="","",(B26*$B$6)) | D26: =IF(A26="","", $B$3) | E26: =IF(D26="","",(D26-C26)) | F26: =IF(A26="","", B26+C26+D26) | G26: =IF(A26="","", (G25+C26)) | J26: =IF(J25<($B$7*$B$8),J25+1,"") | K26: =IF(J26="","",O25) | L26: =IF(J26="","",((K26 + M26)*$B$6)) | M26: =IF(J26="","", $B$3) | N26: =IF(M26="","",(M26-L26)) | O26: =IF(J26="","", K26+L26+M26) | P26: =IF(J26="","", (P25+L26))
A27: =IF(A26<($B$7*$B$8),A26+1,"") | B27: =IF(A27="","",F26) | C27: =IF(A27="","",(B27*$B$6)) | D27: =IF(A27="","", $B$3) | E27: =IF(D27="","",(D27-C27)) | F27: =IF(A27="","", B27+C27+D27) | G27: =IF(A27="","", (G26+C27)) | J27: =IF(J26<($B$7*$B$8),J26+1,"") | K27: =IF(J27="","",O26) | L27: =IF(J27="","",((K27 + M27)*$B$6)) | M27: =IF(J27="","", $B$3) | N27: =IF(M27="","",(M27-L27)) | O27: =IF(J27="","", K27+L27+M27) | P27: =IF(J27="","", (P26+L27))
A28: =IF(A27<($B$7*$B$8),A27+1,"") | B28: =IF(A28="","",F27) | C28: =IF(A28="","",(B28*$B$6)) | D28: =IF(A28="","", $B$3) | E28: =IF(D28="","",(D28-C28)) | F28: =IF(A28="","", B28+C28+D28) | G28: =IF(A28="","", (G27+C28)) | J28: =IF(J27<($B$7*$B$8),J27+1,"") | K28: =IF(J28="","",O27) | L28: =IF(J28="","",((K28 + M28)*$B$6)) | M28: =IF(J28="","", $B$3) | N28: =IF(M28="","",(M28-L28)) | O28: =IF(J28="","", K28+L28+M28) | P28: =IF(J28="","", (P27+L28))
A29: =IF(A28<($B$7*$B$8),A28+1,"") | B29: =IF(A29="","",F28) | C29: =IF(A29="","",(B29*$B$6)) | D29: =IF(A29="","", $B$3) | E29: =IF(D29="","",(D29-C29)) | F29: =IF(A29="","", B29+C29+D29) | G29: =IF(A29="","", (G28+C29)) | J29: =IF(J28<($B$7*$B$8),J28+1,"") | K29: =IF(J29="","",O28) | L29: =IF(J29="","",((K29 + M29)*$B$6)) | M29: =IF(J29="","", $B$3) | N29: =IF(M29="","",(M29-L29)) | O29: =IF(J29="","", K29+L29+M29) | P29: =IF(J29="","", (P28+L29))
A30: =IF(A29<($B$7*$B$8),A29+1,"") | B30: =IF(A30="","",F29) | C30: =IF(A30="","",(B30*$B$6)) | D30: =IF(A30="","", $B$3) | E30: =IF(D30="","",(D30-C30)) | F30: =IF(A30="","", B30+C30+D30) | G30: =IF(A30="","", (G29+C30)) | J30: =IF(J29<($B$7*$B$8),J29+1,"") | K30: =IF(J30="","",O29) | L30: =IF(J30="","",((K30 + M30)*$B$6)) | M30: =IF(J30="","", $B$3) | N30: =IF(M30="","",(M30-L30)) | O30: =IF(J30="","", K30+L30+M30) | P30: =IF(J30="","", (P29+L30))
A31: =IF(A30<($B$7*$B$8),A30+1,"") | B31: =IF(A31="","",F30) | C31: =IF(A31="","",(B31*$B$6)) | D31: =IF(A31="","", $B$3) | E31: =IF(D31="","",(D31-C31)) | F31: =IF(A31="","", B31+C31+D31) | G31: =IF(A31="","", (G30+C31)) | J31: =IF(J30<($B$7*$B$8),J30+1,"") | K31: =IF(J31="","",O30) | L31: =IF(J31="","",((K31 + M31)*$B$6)) | M31: =IF(J31="","", $B$3) | N31: =IF(M31="","",(M31-L31)) | O31: =IF(J31="","", K31+L31+M31) | P31: =IF(J31="","", (P30+L31))
A32: =IF(A31<($B$7*$B$8),A31+1,"") | B32: =IF(A32="","",F31) | C32: =IF(A32="","",(B32*$B$6)) | D32: =IF(A32="","", $B$3) | E32: =IF(D32="","",(D32-C32)) | F32: =IF(A32="","", B32+C32+D32) | G32: =IF(A32="","", (G31+C32)) | J32: =IF(J31<($B$7*$B$8),J31+1,"") | K32: =IF(J32="","",O31) | L32: =IF(J32="","",((K32 + M32)*$B$6)) | M32: =IF(J32="","", $B$3) | N32: =IF(M32="","",(M32-L32)) | O32: =IF(J32="","", K32+L32+M32) | P32: =IF(J32="","", (P31+L32))
A33: =IF(A32<($B$7*$B$8),A32+1,"") | B33: =IF(A33="","",F32) | C33: =IF(A33="","",(B33*$B$6)) | D33: =IF(A33="","", $B$3) | E33: =IF(D33="","",(D33-C33)) | F33: =IF(A33="","", B33+C33+D33) | G33: =IF(A33="","", (G32+C33)) | J33: =IF(J32<($B$7*$B$8),J32+1,"") | K33: =IF(J33="","",O32) | L33: =IF(J33="","",((K33 + M33)*$B$6)) | M33: =IF(J33="","", $B$3) | N33: =IF(M33="","",(M33-L33)) | O33: =IF(J33="","", K33+L33+M33) | P33: =IF(J33="","", (P32+L33))
A34: =IF(A33<($B$7*$B$8),A33+1,"") | B34: =IF(A34="","",F33) | C34: =IF(A34="","",(B34*$B$6)) | D34: =IF(A34="","", $B$3) | E34: =IF(D34="","",(D34-C34)) | F34: =IF(A34="","", B34+C34+D34) | G34: =IF(A34="","", (G33+C34)) | J34: =IF(J33<($B$7*$B$8),J33+1,"") | K34: =IF(J34="","",O33) | L34: =IF(J34="","",((K34 + M34)*$B$6)) | M34: =IF(J34="","", $B$3) | N34: =IF(M34="","",(M34-L34)) | O34: =IF(J34="","", K34+L34+M34) | P34: =IF(J34="","", (P33+L34))
... A565: =IF(A564<($B$7*$B$8),A564+1,"") | B565: =IF(A565="","",F564) | C565: =IF(A565="","",(B565*$B$6)) | D565: =IF(A565="","", $B$3) | E565: =IF(D565="","",(D565-C565)) | F565: =IF(A565="","", B565+C565+D565) | G565: =IF(A565="","", (G564+C565)) | J565: =IF(J564<($B$7*$B$8),J564+1,"") | K565: =IF(J565="","",O564) | L565: =IF(J565="","",((K565 + M565)*$B$6)) | M565: =IF(J565="","", $B$3) | N565: =IF(M565="","",(M565-L565)) | O565: =IF(J565="","", K565+L565+M565) | P565: =IF(J565="","", (P564+L565))
A566: =IF(A565<($B$6*$B$7),A565+1,"") | B566: =IF(A566="","",F565) | C566: =IF(A566="","",(B566*$B$6)) | D566: =IF(A566="","", $B$3) | E566: =IF(D566="","",(D566-C566)) | F566: =IF(A566="","", B566+C566+D566) | G566: =IF(A566="","", (G565+C566)) | J566: =IF(J565<($B$6*$B$7),J565+1,"") | K566: =IF(J566="","",O565) | L566: =IF(J566="","",((K566 + M566)*$B$6)) | M566: =IF(J566="","", $B$3) | N566: =IF(M566="","",(M566-L566)) | O566: =IF(J566="","", K566+L566+M566) | P566: =IF(J566="","", (P565+L566))
A567: =IF(A566<($B$6*$B$7),A566+1,"") | B567: =IF(A567="","",F566) | C567: =IF(A567="","",(B567*$B$6)) | D567: =IF(A567="","", $B$3) | E567: =IF(D567="","",(D567-C567)) | F567: =IF(A567="","", B567+C567+D567) | G567: =IF(A567="","", (G566+C567)) | J567: =IF(J566<($B$6*$B$7),J566+1,"") | K567: =IF(J567="","",O566) | L567: =IF(J567="","",((K567 + M567)*$B$6)) | M567: =IF(J567="","", $B$3) | N567: =IF(M567="","",(M567-L567)) | O567: =IF(J567="","", K567+L567+M567) | P567: =IF(J567="","", (P566+L567))
A568: =IF(A567<($B$6*$B$7),A567+1,"") | B568: =IF(A568="","",F567) | C568: =IF(A568="","",(B568*$B$6)) | D568: =IF(A568="","", $B$3) | E568: =IF(D568="","",(D568-C568)) | F568: =IF(A568="","", B568+C568+D568) | G568: =IF(A568="","", (G567+C568)) | J568: =IF(J567<($B$6*$B$7),J567+1,"") | K568: =IF(J568="","",O567) | L568: =IF(J568="","",((K568 + M568)*$B$6)) | M568: =IF(J568="","", $B$3) | N568: =IF(M568="","",(M568-L568)) | O568: =IF(J568="","", K568+L568+M568) | P568: =IF(J568="","", (P567+L568))
A569: =IF(A568<($B$6*$B$7),A568+1,"") | B569: =IF(A569="","",F568) | C569: =IF(A569="","",(B569*$B$6)) | D569: =IF(A569="","", $B$3) | E569: =IF(D569="","",(D569-C569)) | F569: =IF(A569="","", B569+C569+D569) | G569: =IF(A569="","", (G568+C569)) | J569: =IF(J568<($B$6*$B$7),J568+1,"") | K569: =IF(J569="","",O568) | L569: =IF(J569="","",((K569 + M569)*$B$6)) | M569: =IF(J569="","", $B$3) | N569: =IF(M569="","",(M569-L569)) | O569: =IF(J569="","", K569+L569+M569) | P569: =IF(J569="","", (P568+L569))
A570: =IF(A569<($B$6*$B$7),A569+1,"") | B570: =IF(A570="","",F569) | C570: =IF(A570="","",(B570*$B$6)) | D570: =IF(A570="","", $B$3) | E570: =IF(D570="","",(D570-C570)) | F570: =IF(A570="","", B570+C570+D570) | G570: =IF(A570="","", (G569+C570)) | J570: =IF(J569<($B$6*$B$7),J569+1,"") | K570: =IF(J570="","",O569) | L570: =IF(J570="","",((K570 + M570)*$B$6)) | M570: =IF(J570="","", $B$3) | N570: =IF(M570="","",(M570-L570)) | O570: =IF(J570="","", K570+L570+M570) | P570: =IF(J570="","", (P569+L570))
A571: =IF(A570<($B$6*$B$7),A570+1,"") | B571: =IF(A571="","",F570) | C571: =IF(A571="","",(B571*$B$6)) | D571: =IF(A571="","", $B$3) | E571: =IF(D571="","",(D571-C571)) | F571: =IF(A571="","", B571+C571+D571) | G571: =IF(A571="","", (G570+C571)) | J571: =IF(J570<($B$6*$B$7),J570+1,"") | K571: =IF(J571="","",O570) | L571: =IF(J571="","",((K571 + M571)*$B$6)) | M571: =IF(J571="","", $B$3) | N571: =IF(M571="","",(M571-L571)) | O571: =IF(J571="","", K571+L571+M571) | P571: =IF(J571="","", (P570+L571))
A572: =IF(A571<($B$6*$B$7),A571+1,"") | B572: =IF(A572="","",F571) | C572: =IF(A572="","",(B572*$B$6)) | D572: =IF(A572="","", $B$3) | E572: =IF(D572="","",(D572-C572)) | F572: =IF(A572="","", B572+C572+D572) | G572: =IF(A572="","", (G571+C572)) | J572: =IF(J571<($B$6*$B$7),J571+1,"") | K572: =IF(J572="","",O571) | L572: =IF(J572="","",((K572 + M572)*$B$6)) | M572: =IF(J572="","", $B$3) | N572: =IF(M572="","",(M572-L572)) | O572: =IF(J572="","", K572+L572+M572) | P572: =IF(J572="","", (P571+L572))
A573: =IF(A572<($B$6*$B$7),A572+1,"") | B573: =IF(A573="","",F572) | C573: =IF(A573="","",(B573*$B$6)) | D573: =IF(A573="","", $B$3) | E573: =IF(D573="","",(D573-C573)) | F573: =IF(A573="","", B573+C573+D573) | G573: =IF(A573="","", (G572+C573)) | J573: =IF(J572<($B$6*$B$7),J572+1,"") | K573: =IF(J573="","",O572) | L573: =IF(J573="","",((K573 + M573)*$B$6)) | M573: =IF(J573="","", $B$3) | N573: =IF(M573="","",(M573-L573)) | O573: =IF(J573="","", K573+L573+M573) | P573: =IF(J573="","", (P572+L573))
A574: =IF(A573<($B$6*$B$7),A573+1,"") | B574: =IF(A574="","",F573) | C574: =IF(A574="","",(B574*$B$6)) | D574: =IF(A574="","", $B$3) | E574: =IF(D574="","",(D574-C574)) | F574: =IF(A574="","", B574+C574+D574) | G574: =IF(A574="","", (G573+C574)) | J574: =IF(J573<($B$6*$B$7),J573+1,"") | K574: =IF(J574="","",O573) | L574: =IF(J574="","",((K574 + M574)*$B$6)) | M574: =IF(J574="","", $B$3) | N574: =IF(M574="","",(M574-L574)) | O574: =IF(J574="","", K574+L574+M574) | P574: =IF(J574="","", (P573+L574))
A575: =IF(A574<($B$6*$B$7),A574+1,"") | B575: =IF(A575="","",F574) | C575: =IF(A575="","",(B575*$B$6)) | D575: =IF(A575="","", $B$3) | E575: =IF(D575="","",(D575-C575)) | F575: =IF(A575="","", B575+C575+D575) | G575: =IF(A575="","", (G574+C575)) | J575: =IF(J574<($B$6*$B$7),J574+1,"") | K575: =IF(J575="","",O574) | L575: =IF(J575="","",((K575 + M575)*$B$6)) | M575: =IF(J575="","", $B$3) | N575: =IF(M575="","",(M575-L575)) | O575: =IF(J575="","", K575+L575+M575) | P575: =IF(J575="","", (P574+L575))
A576: =IF(A575<($B$6*$B$7),A575+1,"") | B576: =IF(A576="","",F575) | C576: =IF(A576="","",(B576*$B$6)) | D576: =IF(A576="","", $B$3) | E576: =IF(D576="","",(D576-C576)) | F576: =IF(A576="","", B576+C576+D576) | G576: =IF(A576="","", (G575+C576)) | J576: =IF(J575<($B$6*$B$7),J575+1,"") | K576: =IF(J576="","",O575) | L576: =IF(J576="","",((K576 + M576)*$B$6)) | M576: =IF(J576="","", $B$3) | N576: =IF(M576="","",(M576-L576)) | O576: =IF(J576="","", K576+L576+M576) | P576: =IF(J576="","", (P575+L576))
A577: =IF(A576<($B$6*$B$7),A576+1,"") | B577: =IF(A577="","",F576) | C577: =IF(A577="","",(B577*$B$6)) | D577: =IF(A577="","", $B$3) | E577: =IF(D577="","",(D577-C577)) | F577: =IF(A577="","", B577+C577+D577) | G577: =IF(A577="","", (G576+C577)) | J577: =IF(J576<($B$6*$B$7),J576+1,"") | K577: =IF(J577="","",O576) | L577: =IF(J577="","",((K577 + M577)*$B$6)) | M577: =IF(J577="","", $B$3) | N577: =IF(M577="","",(M577-L577)) | O577: =IF(J577="","", K577+L577+M577) | P577: =IF(J577="","", (P576+L577))
... A722: =IF(A721<($B$6*$B$7),A721+1,"") | B722: =IF(A722="","",F721) | C722: =IF(A722="","",(B722*$B$6)) | D722: =IF(A722="","", $B$3) | E722: =IF(D722="","",(D722-C722)) | F722: =IF(A722="","", B722+C722+D722) | G722: =IF(A722="","", (G721+C722)) | J722: =IF(J721<($B$6*$B$7),J721+1,"") | K722: =IF(J722="","",O721) | L722: =IF(J722="","",((K722 + M722)*$B$6)) | M722: =IF(J722="","", $B$3) | N722: =IF(M722="","",(M722-L722)) | O722: =IF(J722="","", K722+L722+M722) | P722: =IF(J722="","", (P721+L722))
A723: =IF(A722<($B$6*$B$7),A722+1,"") | B723: =IF(A723="","",F722) | C723: =IF(A723="","",(B723*$B$6)) | D723: =IF(A723="","", $B$3) | E723: =IF(D723="","",(D723-C723)) | F723: =IF(A723="","", B723-E723) | G723: =IF(A723="","", (G722+C723)) | J723: =IF(J722<($B$6*$B$7),J722+1,"") | K723: =IF(J723="","",O722) | L723: =IF(J723="","",((K723 + M723)*$B$6)) | M723: =IF(J723="","", $B$3) | N723: =IF(M723="","",(M723-L723)) | O723: =IF(J723="","", K723-N723) | P723: =IF(J723="","", (P722+L723))
A724: =IF(A723<($B$6*$B$7),A723+1,"") | B724: =IF(A724="","",F723) | C724: =IF(A724="","",(B724*$B$6)) | D724: =IF(A724="","", $B$3) | E724: =IF(D724="","",(D724-C724)) | F724: =IF(A724="","", B724-E724) | G724: =IF(A724="","", (G723+C724)) | J724: =IF(J723<($B$6*$B$7),J723+1,"") | K724: =IF(J724="","",O723) | L724: =IF(J724="","",((K724 + M724)*$B$6)) | M724: =IF(J724="","", $B$3) | N724: =IF(M724="","",(M724-L724)) | O724: =IF(J724="","", K724-N724) | P724: =IF(J724="","", (P723+L724))
A725: =IF(A724<($B$6*$B$7),A724+1,"") | B725: =IF(A725="","",F724) | C725: =IF(A725="","",(B725*$B$6)) | D725: =IF(A725="","", $B$3) | E725: =IF(D725="","",(D725-C725)) | F725: =IF(A725="","", B725-E725) | G725: =IF(A725="","", (G724+C725)) | J725: =IF(J724<($B$6*$B$7),J724+1,"") | K725: =IF(J725="","",O724) | L725: =IF(J725="","",((K725 + M725)*$B$6)) | M725: =IF(J725="","", $B$3) | N725: =IF(M725="","",(M725-L725)) | O725: =IF(J725="","", K725-N725) | P725: =IF(J725="","", (P724+L725))
A726: =IF(A725<($B$6*$B$7),A725+1,"") | B726: =IF(A726="","",F725) | C726: =IF(A726="","",(B726*$B$6)) | D726: =IF(A726="","", $B$3) | E726: =IF(D726="","",(D726-C726)) | F726: =IF(A726="","", B726-E726) | G726: =IF(A726="","", (G725+C726)) | J726: =IF(J725<($B$6*$B$7),J725+1,"") | K726: =IF(J726="","",O725) | L726: =IF(J726="","",((K726 + M726)*$B$6)) | M726: =IF(J726="","", $B$3) | N726: =IF(M726="","",(M726-L726)) | O726: =IF(J726="","", K726-N726) | P726: =IF(J726="","", (P725+L726))
A727: =IF(A726<($B$6*$B$7),A726+1,"") | B727: =IF(A727="","",F726) | C727: =IF(A727="","",(B727*$B$6)) | D727: =IF(A727="","", $B$3) | E727: =IF(D727="","",(D727-C727)) | F727: =IF(A727="","", B727-E727) | G727: =IF(A727="","", (G726+C727)) | J727: =IF(J726<($B$6*$B$7),J726+1,"") | K727: =IF(J727="","",O726) | L727: =IF(J727="","",((K727 + M727)*$B$6)) | M727: =IF(J727="","", $B$3) | N727: =IF(M727="","",(M727-L727)) | O727: =IF(J727="","", K727-N727) | P727: =IF(J727="","", (P726+L727))
A728: =IF(A727<($B$6*$B$7),A727+1,"") | B728: =IF(A728="","",F727) | C728: =IF(A728="","",(B728*$B$6)) | D728: =IF(A728="","", $B$3) | E728: =IF(D728="","",(D728-C728)) | F728: =IF(A728="","", B728-E728) | G728: =IF(A728="","", (G727+C728)) | J728: =IF(J727<($B$6*$B$7),J727+1,"") | K728: =IF(J728="","",O727) | L728: =IF(J728="","",((K728 + M728)*$B$6)) | M728: =IF(J728="","", $B$3) | N728: =IF(M728="","",(M728-L728)) | O728: =IF(J728="","", K728-N728) | P728: =IF(J728="","", (P727+L728))
A729: =IF(A728<($B$6*$B$7),A728+1,"") | B729: =IF(A729="","",F728) | C729: =IF(A729="","",(B729*$B$6)) | D729: =IF(A729="","", $B$3) | E729: =IF(D729="","",(D729-C729)) | F729: =IF(A729="","", B729-E729) | G729: =IF(A729="","", (G728+C729)) | J729: =IF(J728<($B$6*$B$7),J728+1,"") | K729: =IF(J729="","",O728) | L729: =IF(J729="","",((K729 + M729)*$B$6)) | M729: =IF(J729="","", $B$3) | N729: =IF(M729="","",(M729-L729)) | O729: =IF(J729="","", K729-N729) | P729: =IF(J729="","", (P728+L729))
A730: =IF(A729<($B$6*$B$7),A729+1,"") | B730: =IF(A730="","",F729) | C730: =IF(A730="","",(B730*$B$6)) | D730: =IF(A730="","", $B$3) | E730: =IF(D730="","",(D730-C730)) | F730: =IF(A730="","", B730-E730) | G730: =IF(A730="","", (G729+C730)) | J730: =IF(J729<($B$6*$B$7),J729+1,"") | K730: =IF(J730="","",O729) | L730: =IF(J730="","",((K730 + M730)*$B$6)) | M730: =IF(J730="","", $B$3) | N730: =IF(M730="","",(M730-L730)) | O730: =IF(J730="","", K730-N730) | P730: =IF(J730="","", (P729+L730))
A731: =IF(A730<($B$6*$B$7),A730+1,"") | B731: =IF(A731="","",F730) | C731: =IF(A731="","",(B731*$B$6)) | D731: =IF(A731="","", $B$3) | E731: =IF(D731="","",(D731-C731)) | F731: =IF(A731="","", B731-E731) | G731: =IF(A731="","", (G730+C731)) | J731: =IF(J730<($B$6*$B$7),J730+1,"") | K731: =IF(J731="","",O730) | L731: =IF(J731="","",((K731 + M731)*$B$6)) | M731: =IF(J731="","", $B$3) | N731: =IF(M731="","",(M731-L731)) | O731: =IF(J731="","", K731-N731) | P731: =IF(J731="","", (P730+L731))
A732: =IF(A731<($B$6*$B$7),A731+1,"") | B732: =IF(A732="","",F731) | C732: =IF(A732="","",(B732*$B$6)) | D732: =IF(A732="","", $B$3) | E732: =IF(D732="","",(D732-C732)) | F732: =IF(A732="","", B732-E732) | G732: =IF(A732="","", (G731+C732)) | J732: =IF(J731<($B$6*$B$7),J731+1,"") | K732: =IF(J732="","",O731) | L732: =IF(J732="","",((K732 + M732)*$B$6)) | M732: =IF(J732="","", $B$3) | N732: =IF(M732="","",(M732-L732)) | O732: =IF(J732="","", K732-N732) | P732: =IF(J732="","", (P731+L732))
A733: =IF(A732<($B$6*$B$7),A732+1,"") | B733: =IF(A733="","",F732) | C733: =IF(A733="","",(B733*$B$6)) | D733: =IF(A733="","", $B$3) | E733: =IF(D733="","",(D733-C733)) | F733: =IF(A733="","", B733-E733) | G733: =IF(A733="","", (G732+C733)) | J733: =IF(J732<($B$6*$B$7),J732+1,"") | K733: =IF(J733="","",O732) | L733: =IF(J733="","",((K733 + M733)*$B$6)) | M733: =IF(J733="","", $B$3) | N733: =IF(M733="","",(M733-L733)) | O733: =IF(J733="","", K733-N733) | P733: =IF(J733="","", (P732+L733))
A734: =IF(A733<($B$6*$B$7),A733+1,"") | B734: =IF(A734="","",F733) | C734: =IF(A734="","",(B734*$B$6)) | D734: =IF(A734="","", $B$3) | E734: =IF(D734="","",(D734-C734)) | F734: =IF(A734="","", B734-E734) | G734: =IF(A734="","", (G733+C734)) | J734: =IF(J733<($B$6*$B$7),J733+1,"") | K734: =IF(J734="","",O733) | L734: =IF(J734="","",((K734 + M734)*$B$6)) | M734: =IF(J734="","", $B$3) | N734: =IF(M734="","",(M734-L734)) | O734: =IF(J734="","", K734-N734) | P734: =IF(J734="","", (P733+L734))
... A739: =IF(A738<($B$6*$B$7),A738+1,"") | B739: =IF(A739="","",F738) | C739: =IF(A739="","",(B739*$B$6)) | D739: =IF(A739="","", $B$3) | E739: =IF(D739="","",(D739-C739)) | F739: =IF(A739="","", B739-E739) | G739: =IF(A739="","", (G738+C739)) | J739: =IF(J738<($B$6*$B$7),J738+1,"") | K739: =IF(J739="","",O738) | L739: =IF(J739="","",((K739 + M739)*$B$6)) | M739: =IF(J739="","", $B$3) | N739: =IF(M739="","",(M739-L739)) | O739: =IF(J739="","", K739-N739) | P739: =IF(J739="","", (P738+L739))
A740: =IF(A739<($B$6*$B$7),A739+1,"") | B740: =IF(A740="","",F739) | C740: =IF(A740="","",(B740*$B$6)) | D740: =IF(A740="","", $B$5) | E740: =IF(D740="","",(D740-C740)) | F740: =IF(A740="","", B740-E740) | G740: =IF(A740="","", (G739+C740)) | J740: =IF(J739<($B$6*$B$7),J739+1,"") | K740: =IF(J740="","",O739) | L740: =IF(J740="","",((K740 + M740)*$B$6)) | M740: =IF(J740="","", $B$5) | N740: =IF(M740="","",(M740-L740)) | O740: =IF(J740="","", K740-N740) | P740: =IF(J740="","", (P739+L740))
A741: =IF(A740<($B$6*$B$7),A740+1,"") | B741: =IF(A741="","",F740) | C741: =IF(A741="","",(B741*$B$6)) | D741: =IF(A741="","", $B$5) | E741: =IF(D741="","",(D741-C741)) | F741: =IF(A741="","", B741-E741) | G741: =IF(A741="","", (G740+C741)) | J741: =IF(J740<($B$6*$B$7),J740+1,"") | K741: =IF(J741="","",O740) | L741: =IF(J741="","",((K741 + M741)*$B$6)) | M741: =IF(J741="","", $B$5) | N741: =IF(M741="","",(M741-L741)) | O741: =IF(J741="","", K741-N741) | P741: =IF(J741="","", (P740+L741))
A742: =IF(A741<($B$6*$B$7),A741+1,"") | B742: =IF(A742="","",F741) | C742: =IF(A742="","",(B742*$B$6)) | D742: =IF(A742="","", $B$5) | E742: =IF(D742="","",(D742-C742)) | F742: =IF(A742="","", B742-E742) | G742: =IF(A742="","", (G741+C742)) | J742: =IF(J741<($B$6*$B$7),J741+1,"") | K742: =IF(J742="","",O741) | L742: =IF(J742="","",((K742 + M742)*$B$6)) | M742: =IF(J742="","", $B$5) | N742: =IF(M742="","",(M742-L742)) | O742: =IF(J742="","", K742-N742) | P742: =IF(J742="","", (P741+L742))
A743: =IF(A742<($B$6*$B$7),A742+1,"") | B743: =IF(A743="","",F742) | C743: =IF(A743="","",(B743*$B$6)) | D743: =IF(A743="","", $B$5) | E743: =IF(D743="","",(D743-C743)) | F743: =IF(A743="","", B743-E743) | G743: =IF(A743="","", (G742+C743)) | J743: =IF(J742<($B$6*$B$7),J742+1,"") | K743: =IF(J743="","",O742) | L743: =IF(J743="","",((K743 + M743)*$B$6)) | M743: =IF(J743="","", $B$5) | N743: =IF(M743="","",(M743-L743)) | O743: =IF(J743="","", K743-N743) | P743: =IF(J743="","", (P742+L743))
A744: =IF(A743<($B$6*$B$7),A743+1,"") | B744: =IF(A744="","",F743) | C744: =IF(A744="","",(B744*$B$6)) | D744: =IF(A744="","", $B$5) | E744: =IF(D744="","",(D744-C744)) | F744: =IF(A744="","", B744-E744) | G744: =IF(A744="","", (G743+C744)) | J744: =IF(J743<($B$6*$B$7),J743+1,"") | K744: =IF(J744="","",O743) | L744: =IF(J744="","",((K744 + M744)*$B$6)) | M744: =IF(J744="","", $B$5) | N744: =IF(M744="","",(M744-L744)) | O744: =IF(J744="","", K744-N744) | P744: =IF(J744="","", (P743+L744))
A745: =IF(A744<($B$6*$B$7),A744+1,"") | B745: =IF(A745="","",F744) | C745: =IF(A745="","",(B745*$B$6)) | D745: =IF(A745="","", $B$5) | E745: =IF(D745="","",(D745-C745)) | F745: =IF(A745="","", B745-E745) | G745: =IF(A745="","", (G744+C745)) | J745: =IF(J744<($B$6*$B$7),J744+1,"") | K745: =IF(J745="","",O744) | L745: =IF(J745="","",((K745 + M745)*$B$6)) | M745: =IF(J745="","", $B$5) | N745: =IF(M745="","",(M745-L745)) | O745: =IF(J745="","", K745-N745) | P745: =IF(J745="","", (P744+L745))
A746: =IF(A745<($B$6*$B$7),A745+1,"") | B746: =IF(A746="","",F745) | C746: =IF(A746="","",(B746*$B$6)) | D746: =IF(A746="","", $B$5) | E746: =IF(D746="","",(D746-C746)) | F746: =IF(A746="","", B746-E746) | G746: =IF(A746="","", (G745+C746)) | J746: =IF(J745<($B$6*$B$7),J745+1,"") | K746: =IF(J746="","",O745) | L746: =IF(J746="","",((K746 + M746)*$B$6)) | M746: =IF(J746="","", $B$5) | N746: =IF(M746="","",(M746-L746)) | O746: =IF(J746="","", K746-N746) | P746: =IF(J746="","", (P745+L746))
A747: =IF(A746<($B$6*$B$7),A746+1,"") | B747: =IF(A747="","",F746) | C747: =IF(A747="","",(B747*$B$6)) | D747: =IF(A747="","", $B$5) | E747: =IF(D747="","",(D747-C747)) | F747: =IF(A747="","", B747-E747) | G747: =IF(A747="","", (G746+C747)) | J747: =IF(J746<($B$6*$B$7),J746+1,"") | K747: =IF(J747="","",O746) | L747: =IF(J747="","",((K747 + M747)*$B$6)) | M747: =IF(J747="","", $B$5) | N747: =IF(M747="","",(M747-L747)) | O747: =IF(J747="","", K747-N747) | P747: =IF(J747="","", (P746+L747))
A748: =IF(A747<($B$6*$B$7),A747+1,"") | B748: =IF(A748="","",F747) | C748: =IF(A748="","",(B748*$B$6)) | D748: =IF(A748="","", $B$5) | E748: =IF(D748="","",(D748-C748)) | F748: =IF(A748="","", B748-E748) | G748: =IF(A748="","", (G747+C748)) | J748: =IF(J747<($B$6*$B$7),J747+1,"") | K748: =IF(J748="","",O747) | L748: =IF(J748="","",((K748 + M748)*$B$6)) | M748: =IF(J748="","", $B$5) | N748: =IF(M748="","",(M748-L748)) | O748: =IF(J748="","", K748-N748) | P748: =IF(J748="","", (P747+L748))
A749: =IF(A748<($B$6*$B$7),A748+1,"") | B749: =IF(A749="","",F748) | C749: =IF(A749="","",(B749*$B$6)) | D749: =IF(A749="","", $B$5) | E749: =IF(D749="","",(D749-C749)) | F749: =IF(A749="","", B749-E749) | G749: =IF(A749="","", (G748+C749)) | J749: =IF(J748<($B$6*$B$7),J748+1,"") | K749: =IF(J749="","",O748) | L749: =IF(J749="","",((K749 + M749)*$B$6)) | M749: =IF(J749="","", $B$5) | N749: =IF(M749="","",(M749-L749)) | O749: =IF(J749="","", K749-N749) | P749: =IF(J749="","", (P748+L749))
A750: =IF(A749<($B$6*$B$7),A749+1,"") | B750: =IF(A750="","",F749) | C750: =IF(A750="","",(B750*$B$6)) | D750: =IF(A750="","", $B$5) | E750: =IF(D750="","",(D750-C750)) | F750: =IF(A750="","", B750-E750) | G750: =IF(A750="","", (G749+C750)) | J750: =IF(J749<($B$6*$B$7),J749+1,"") | K750: =IF(J750="","",O749) | L750: =IF(J750="","",((K750 + M750)*$B$6)) | M750: =IF(J750="","", $B$5) | N750: =IF(M750="","",(M750-L750)) | O750: =IF(J750="","", K750-N750) | P750: =IF(J750="","", (P749+L750))
A751: =IF(A750<($B$6*$B$7),A750+1,"") | B751: =IF(A751="","",F750) | C751: =IF(A751="","",(B751*$B$6)) | D751: =IF(A751="","", $B$5) | E751: =IF(D751="","",(D751-C751)) | F751: =IF(A751="","", B751-E751) | G751: =IF(A751="","", (G750+C751)) | J751: =IF(J750<($B$6*$B$7),J750+1,"") | K751: =IF(J751="","",O750) | L751: =IF(J751="","",((K751 + M751)*$B$6)) | M751: =IF(J751="","", $B$5) | N751: =IF(M751="","",(M751-L751)) | O751: =IF(J751="","", K751-N751) | P751: =IF(J751="","", (P750+L751))
... A812: =IF(A811<($B$6*$B$7),A811+1,"") | B812: =IF(A812="","",F811) | C812: =IF(A812="","",(B812*$B$6)) | D812: =IF(A812="","", $B$5) | E812: =IF(D812="","",(D812-C812)) | F812: =IF(A812="","", B812-E812) | G812: =IF(A812="","", (G811+C812)) | J812: =IF(J811<($B$6*$B$7),J811+1,"") | K812: =IF(J812="","",O811) | L812: =IF(J812="","",((K812 + M812)*$B$6)) | M812: =IF(J812="","", $B$5) | N812: =IF(M812="","",(M812-L812)) | O812: =IF(J812="","", K812-N812) | P812: =IF(J812="","", (P811+L812))
A813: =IF(A812<($B$6*$B$7),A812+1,"") | B813: =IF(A813="","",F812) | C813: =IF(A813="","",(B813*$B$6)) | D813: =IF(A813="","", $B$5) | E813: =IF(D813="","",(D813-C813)) | F813: =IF(A813="","", B813-E813) | G813: =IF(A813="","", (G812+C813)) | J813: =IF(J812<($B$6*$B$7),J812+1,"") | K813: =IF(J813="","",O812) | L813: =IF(J813="","",(K813*$B$6)) | M813: =IF(J813="","", $B$5) | N813: =IF(M813="","",(M813-L813)) | O813: =IF(J813="","", K813-N813) | P813: =IF(J813="","", (P812+L813))
A814: =IF(A813<($B$6*$B$7),A813+1,"") | B814: =IF(A814="","",F813) | C814: =IF(A814="","",(B814*$B$6)) | D814: =IF(A814="","", $B$5) | E814: =IF(D814="","",(D814-C814)) | F814: =IF(A814="","", B814-E814) | G814: =IF(A814="","", (G813+C814)) | J814: =IF(J813<($B$6*$B$7),J813+1,"") | K814: =IF(J814="","",O813) | L814: =IF(J814="","",(K814*$B$6)) | M814: =IF(J814="","", $B$5) | N814: =IF(M814="","",(M814-L814)) | O814: =IF(J814="","", K814-N814) | P814: =IF(J814="","", (P813+L814))
A815: =IF(A814<($B$6*$B$7),A814+1,"") | B815: =IF(A815="","",F814) | C815: =IF(A815="","",(B815*$B$6)) | D815: =IF(A815="","", $B$5) | E815: =IF(D815="","",(D815-C815)) | F815: =IF(A815="","", B815-E815) | G815: =IF(A815="","", (G814+C815)) | J815: =IF(J814<($B$6*$B$7),J814+1,"") | K815: =IF(J815="","",O814) | L815: =IF(J815="","",(K815*$B$6)) | M815: =IF(J815="","", $B$5) | N815: =IF(M815="","",(M815-L815)) | O815: =IF(J815="","", K815-N815) | P815: =IF(J815="","", (P814+L815))
A816: =IF(A815<($B$6*$B$7),A815+1,"") | B816: =IF(A816="","",F815) | C816: =IF(A816="","",(B816*$B$6)) | D816: =IF(A816="","", $B$5) | E816: =IF(D816="","",(D816-C816)) | F816: =IF(A816="","", B816-E816) | G816: =IF(A816="","", (G815+C816)) | J816: =IF(J815<($B$6*$B$7),J815+1,"") | K816: =IF(J816="","",O815) | L816: =IF(J816="","",(K816*$B$6)) | M816: =IF(J816="","", $B$5) | N816: =IF(M816="","",(M816-L816)) | O816: =IF(J816="","", K816-N816) | P816: =IF(J816="","", (P815+L816))
A817: =IF(A816<($B$6*$B$7),A816+1,"") | B817: =IF(A817="","",F816) | C817: =IF(A817="","",(B817*$B$6)) | D817: =IF(A817="","", $B$5) | E817: =IF(D817="","",(D817-C817)) | F817: =IF(A817="","", B817-E817) | G817: =IF(A817="","", (G816+C817)) | J817: =IF(J816<($B$6*$B$7),J816+1,"") | K817: =IF(J817="","",O816) | L817: =IF(J817="","",(K817*$B$6)) | M817: =IF(J817="","", $B$5) | N817: =IF(M817="","",(M817-L817)) | O817: =IF(J817="","", K817-N817) | P817: =IF(J817="","", (P816+L817))
A818: =IF(A817<($B$6*$B$7),A817+1,"") | B818: =IF(A818="","",F817) | C818: =IF(A818="","",(B818*$B$8)) | D818: =IF(A818="","", $B$5) | E818: =IF(D818="","",(D818-C818)) | F818: =IF(A818="","", B818-E818) | G818: =IF(A818="","", (G817+C818)) | J818: =IF(J817<($B$6*$B$7),J817+1,"") | K818: =IF(J818="","",O817) | L818: =IF(J818="","",(K818*$B$8)) | M818: =IF(J818="","", $B$5) | N818: =IF(M818="","",(M818-L818)) | O818: =IF(J818="","", K818-N818) | P818: =IF(J818="","", (P817+L818))
A819: =IF(A818<($B$6*$B$7),A818+1,"") | B819: =IF(A819="","",F818) | C819: =IF(A819="","",(B819*$B$8)) | D819: =IF(A819="","", $B$5) | E819: =IF(D819="","",(D819-C819)) | F819: =IF(A819="","", B819-E819) | G819: =IF(A819="","", (G818+C819)) | J819: =IF(J818<($B$6*$B$7),J818+1,"") | K819: =IF(J819="","",O818) | L819: =IF(J819="","",(K819*$B$8)) | M819: =IF(J819="","", $B$5) | N819: =IF(M819="","",(M819-L819)) | O819: =IF(J819="","", K819-N819) | P819: =IF(J819="","", (P818+L819))
A820: =IF(A819<($B$6*$B$7),A819+1,"") | B820: =IF(A820="","",F819) | C820: =IF(A820="","",(B820*$B$8)) | D820: =IF(A820="","", $B$5) | E820: =IF(D820="","",(D820-C820)) | F820: =IF(A820="","", B820-E820) | G820: =IF(A820="","", (G819+C820)) | J820: =IF(J819<($B$6*$B$7),J819+1,"") | K820: =IF(J820="","",O819) | L820: =IF(J820="","",(K820*$B$8)) | M820: =IF(J820="","", $B$5) | N820: =IF(M820="","",(M820-L820)) | O820: =IF(J820="","", K820-N820) | P820: =IF(J820="","", (P819+L820))
A821: =IF(A820<($B$6*$B$7),A820+1,"") | B821: =IF(A821="","",F820) | C821: =IF(A821="","",(B821*$B$8)) | D821: =IF(A821="","", $B$5) | E821: =IF(D821="","",(D821-C821)) | F821: =IF(A821="","", B821-E821) | G821: =IF(A821="","", (G820+C821)) | J821: =IF(J820<($B$6*$B$7),J820+1,"") | K821: =IF(J821="","",O820) | L821: =IF(J821="","",(K821*$B$8)) | M821: =IF(J821="","", $B$5) | N821: =IF(M821="","",(M821-L821)) | O821: =IF(J821="","", K821-N821) | P821: =IF(J821="","", (P820+L821))
A822: =IF(A821<($B$6*$B$7),A821+1,"") | B822: =IF(A822="","",F821) | C822: =IF(A822="","",(B822*$B$8)) | D822: =IF(A822="","", $B$5) | E822: =IF(D822="","",(D822-C822)) | F822: =IF(A822="","", B822-E822) | G822: =IF(A822="","", (G821+C822)) | J822: =IF(J821<($B$6*$B$7),J821+1,"") | K822: =IF(J822="","",O821) | L822: =IF(J822="","",(K822*$B$8)) | M822: =IF(J822="","", $B$5) | N822: =IF(M822="","",(M822-L822)) | O822: =IF(J822="","", K822-N822) | P822: =IF(J822="","", (P821+L822))
A823: =IF(A822<($B$6*$B$7),A822+1,"") | B823: =IF(A823="","",F822) | C823: =IF(A823="","",(B823*$B$8)) | D823: =IF(A823="","", $B$5) | E823: =IF(D823="","",(D823-C823)) | F823: =IF(A823="","", B823-E823) | G823: =IF(A823="","", (G822+C823)) | J823: =IF(J822<($B$6*$B$7),J822+1,"") | K823: =IF(J823="","",O822) | L823: =IF(J823="","",(K823*$B$8)) | M823: =IF(J823="","", $B$5) | N823: =IF(M823="","",(M823-L823)) | O823: =IF(J823="","", K823-N823) | P823: =IF(J823="","", (P822+L823))
A824: =IF(A823<($B$6*$B$7),A823+1,"") | B824: =IF(A824="","",F823) | C824: =IF(A824="","",(B824*$B$8)) | D824: =IF(A824="","", $B$5) | E824: =IF(D824="","",(D824-C824)) | F824: =IF(A824="","", B824-E824) | G824: =IF(A824="","", (G823+C824)) | J824: =IF(J823<($B$6*$B$7),J823+1,"") | K824: =IF(J824="","",O823) | L824: =IF(J824="","",(K824*$B$8)) | M824: =IF(J824="","", $B$5) | N824: =IF(M824="","",(M824-L824)) | O824: =IF(J824="","", K824-N824) | P824: =IF(J824="","", (P823+L824))
A825: =IF(A824<($B$6*$B$7),A824+1,"") | B825: =IF(A825="","",F824) | C825: =IF(A825="","",(B825*$B$8)) | D825: =IF(A825="","", $B$5) | E825: =IF(D825="","",(D825-C825)) | F825: =IF(A825="","", B825-E825) | G825: =IF(A825="","", (G824+C825)) | J825: =IF(J824<($B$6*$B$7),J824+1,"") | K825: =IF(J825="","",O824) | L825: =IF(J825="","",(K825*$B$8)) | M825: =IF(J825="","", $B$5) | N825: =IF(M825="","",(M825-L825)) | O825: =IF(J825="","", K825-N825) | P825: =IF(J825="","", (P824+L825))
A826: =IF(A825<($B$6*$B$7),A825+1,"") | B826: =IF(A826="","",F825) | C826: =IF(A826="","",(B826*$B$8)) | D826: =IF(A826="","", $B$5) | E826: =IF(D826="","",(D826-C826)) | F826: =IF(A826="","", B826-E826) | G826: =IF(A826="","", (G825+C826)) | J826: =IF(J825<($B$6*$B$7),J825+1,"") | K826: =IF(J826="","",O825) | L826: =IF(J826="","",(K826*$B$8)) | M826: =IF(J826="","", $B$5) | N826: =IF(M826="","",(M826-L826)) | O826: =IF(J826="","", K826-N826) | P826: =IF(J826="","", (P825+L826))
A827: =IF(A826<($B$6*$B$7),A826+1,"") | B827: =IF(A827="","",F826) | C827: =IF(A827="","",(B827*$B$8)) | D827: =IF(A827="","", $B$5) | E827: =IF(D827="","",(D827-C827)) | F827: =IF(A827="","", B827-E827) | G827: =IF(A827="","", (G826+C827)) | J827: =IF(J826<($B$6*$B$7),J826+1,"") | K827: =IF(J827="","",O826) | L827: =IF(J827="","",(K827*$B$8)) | M827: =IF(J827="","", $B$5) | N827: =IF(M827="","",(M827-L827)) | O827: =IF(J827="","", K827-N827) | P827: =IF(J827="","", (P826+L827))
A828: =IF(A827<($B$6*$B$7),A827+1,"") | B828: =IF(A828="","",F827) | C828: =IF(A828="","",(B828*$B$8)) | D828: =IF(A828="","", $B$5) | E828: =IF(D828="","",(D828-C828)) | F828: =IF(A828="","", B828-E828) | G828: =IF(A828="","", (G827+C828)) | J828: =IF(J827<($B$6*$B$7),J827+1,"") | K828: =IF(J828="","",O827) | L828: =IF(J828="","",(K828*$B$8)) | M828: =IF(J828="","", $B$5) | N828: =IF(M828="","",(M828-L828)) | O828: =IF(J828="","", K828-N828) | P828: =IF(J828="","", (P827+L828))
A829: =IF(A828<($B$6*$B$7),A828+1,"") | B829: =IF(A829="","",F828) | C829: =IF(A829="","",(B829*$B$8)) | D829: =IF(A829="","", $B$5) | E829: =IF(D829="","",(D829-C829)) | F829: =IF(A829="","", B829-E829) | G829: =IF(A829="","", (G828+C829)) | J829: =IF(J828<($B$6*$B$7),J828+1,"") | K829: =IF(J829="","",O828) | L829: =IF(J829="","",(K829*$B$8)) | M829: =IF(J829="","", $B$5) | N829: =IF(M829="","",(M829-L829)) | O829: =IF(J829="","", K829-N829) | P829: =IF(J829="","", (P828+L829))
... A877: =IF(A876<($B$6*$B$7),A876+1,"") | B877: =IF(A877="","",F876) | C877: =IF(A877="","",(B877*$B$8)) | D877: =IF(A877="","", $B$5) | E877: =IF(D877="","",(D877-C877)) | F877: =IF(A877="","", B877-E877) | G877: =IF(A877="","", (G876+C877)) | J877: =IF(J876<($B$6*$B$7),J876+1,"") | K877: =IF(J877="","",O876) | L877: =IF(J877="","",(K877*$B$8)) | M877: =IF(J877="","", $B$5) | N877: =IF(M877="","",(M877-L877)) | O877: =IF(J877="","", K877-N877) | P877: =IF(J877="","", (P876+L877))
A878: =IF(A877<($B$6*$B$7),A877+1,"") | B878: =IF(A878="","",F877) | C878: =IF(A878="","",(B878*$B$8)) | D878: =IF(A878="","", $B$5) | E878: =IF(D878="","",(D878-C878)) | F878: =IF(A878="","", B878-E878) | G878: =IF(A878="","", (G877+C878)) | H878: =IF(A878="","",(H877+E878)) | J878: =IF(J877<($B$6*$B$7),J877+1,"") | K878: =IF(J878="","",O877) | L878: =IF(J878="","",(K878*$B$8)) | M878: =IF(J878="","", $B$5) | N878: =IF(M878="","",(M878-L878)) | O878: =IF(J878="","", K878-N878) | P878: =IF(J878="","", (P877+L878)) | Q878: =IF(J878="","",(Q877+N878))
A879: =IF(A878<($B$6*$B$7),A878+1,"") | B879: =IF(A879="","",F878) | C879: =IF(A879="","",(B879*$B$8)) | D879: =IF(A879="","", $B$5) | E879: =IF(D879="","",(D879-C879)) | F879: =IF(A879="","", B879-E879) | G879: =IF(A879="","", (G878+C879)) | H879: =IF(A879="","",(H878+E879)) | J879: =IF(J878<($B$6*$B$7),J878+1,"") | K879: =IF(J879="","",O878) | L879: =IF(J879="","",(K879*$B$8)) | M879: =IF(J879="","", $B$5) | N879: =IF(M879="","",(M879-L879)) | O879: =IF(J879="","", K879-N879) | P879: =IF(J879="","", (P878+L879)) | Q879: =IF(J879="","",(Q878+N879))
A880: =IF(A879<($B$6*$B$7),A879+1,"") | B880: =IF(A880="","",F879) | C880: =IF(A880="","",(B880*$B$8)) | D880: =IF(A880="","", $B$5) | E880: =IF(D880="","",(D880-C880)) | F880: =IF(A880="","", B880-E880) | G880: =IF(A880="","", (G879+C880)) | H880: =IF(A880="","",(H879+E880)) | J880: =IF(J879<($B$6*$B$7),J879+1,"") | K880: =IF(J880="","",O879) | L880: =IF(J880="","",(K880*$B$8)) | M880: =IF(J880="","", $B$5) | N880: =IF(M880="","",(M880-L880)) | O880: =IF(J880="","", K880-N880) | P880: =IF(J880="","", (P879+L880)) | Q880: =IF(J880="","",(Q879+N880))
A881: =IF(A880<($B$6*$B$7),A880+1,"") | B881: =IF(A881="","",F880) | C881: =IF(A881="","",(B881*$B$8)) | D881: =IF(A881="","", $B$5) | E881: =IF(D881="","",(D881-C881)) | F881: =IF(A881="","", B881-E881) | G881: =IF(A881="","", (G880+C881)) | H881: =IF(A881="","",(H880+E881))
A882: =IF(A881<($B$6*$B$7),A881+1,"") | B882: =IF(A882="","",F881) | C882: =IF(A882="","",(B882*$B$8)) | D882: =IF(A882="","", $B$5) | E882: =IF(D882="","",(D882-C882)) | F882: =IF(A882="","", B882-E882) | G882: =IF(A882="","", (G881+C882)) | H882: =IF(A882="","",(H881+E882))
A883: =IF(A882<($B$6*$B$7),A882+1,"") | B883: =IF(A883="","",F882) | C883: =IF(A883="","",(B883*$B$8)) | D883: =IF(A883="","", $B$5) | E883: =IF(D883="","",(D883-C883)) | F883: =IF(A883="","", B883-E883) | G883: =IF(A883="","", (G882+C883)) | H883: =IF(A883="","",(H882+E883))
A884: =IF(A883<($B$6*$B$7),A883+1,"") | B884: =IF(A884="","",F883) | C884: =IF(A884="","",(B884*$B$8)) | D884: =IF(A884="","", $B$5) | E884: =IF(D884="","",(D884-C884)) | F884: =IF(A884="","", B884-E884) | G884: =IF(A884="","", (G883+C884)) | H884: =IF(A884="","",(H883+E884))
A885: =IF(A884<($B$6*$B$7),A884+1,"") | B885: =IF(A885="","",F884) | C885: =IF(A885="","",(B885*$B$8)) | D885: =IF(A885="","", $B$5) | E885: =IF(D885="","",(D885-C885)) | F885: =IF(A885="","", B885-E885) | G885: =IF(A885="","", (G884+C885)) | H885: =IF(A885="","",(H884+E885))
A886: =IF(A885<($B$6*$B$7),A885+1,"") | B886: =IF(A886="","",F885) | C886: =IF(A886="","",(B886*$B$8)) | D886: =IF(A886="","", $B$5) | E886: =IF(D886="","",(D886-C886)) | F886: =IF(A886="","", B886-E886) | G886: =IF(A886="","", (G885+C886)) | H886: =IF(A886="","",(H885+E886))
A887: =IF(A886<($B$6*$B$7),A886+1,"") | B887: =IF(A887="","",F886) | C887: =IF(A887="","",(B887*$B$8)) | D887: =IF(A887="","", $B$5) | E887: =IF(D887="","",(D887-C887)) | F887: =IF(A887="","", B887-E887) | G887: =IF(A887="","", (G886+C887)) | H887: =IF(A887="","",(H886+E887))
A888: =IF(A887<($B$6*$B$7),A887+1,"") | B888: =IF(A888="","",F887) | C888: =IF(A888="","",(B888*$B$8)) | D888: =IF(A888="","", $B$5) | E888: =IF(D888="","",(D888-C888)) | F888: =IF(A888="","", B888-E888) | G888: =IF(A888="","", (G887+C888)) | H888: =IF(A888="","",(H887+E888))
...

Sheet Assignment6 (Back Office)
A3: Annuity 1
A4: Cashflow | B4: ='Assignment6 (User Interface)'!B5 -> 10000
A5: Annuity Interest | B5: ='Assignment6 (User Interface)'!B6 -> 0.02
A6: Annuity increase interest | B6: ='Assignment6 (User Interface)'!B7 -> 0.05
A7: k | B7: ='Assignment6 (User Interface)'!B8 -> 4
A8: m | B8: ='Assignment6 (User Interface)'!B9 -> 10
A9: Future Value | B9: ='Assignment6 (User Interface)'!B10 -> 106347.05 | G9: Annuity 1
A10: Present Value | B10: ='Assignment6 (User Interface)'!B11 -> 322222 | G10: part1 | H10: part2 | I10: part3 | J10: fv | K10: PV | L10: x-using FV | M10: X-using PV
F11: Arrears | G11: =((((1+B5)^B7)-1)/B5) -> 4.121608 | H11: =((1+B5)^(B7*B8)) - ((1+B6)^B8) -> 0.57914504 | I11: =((1+B5)^(B7))-(1+B6) -> 0.03243216 | J11: =G11*(H11/I11)*B4 -> 736000.57 | K11: =B9*(1+B6)^(-B7*B8) -> 15106.139 | L11: =J11*I11/(G11*H11) -> 10000 | M11: =K11*((1+$B$6)^($B$7*$B$8))*I11/(G11*H11) -> 1444.9316
F12: Advance | G12: =((((1+B5)^B7)-1)/B5) -> 4.121608 | H12: =(1+B5)^(B7*B8)-(1+B6)^(B8) -> 0.57914504 | I12: =(1+B5)^(B7)-(1+B6) -> 0.03243216 | J12: =G12*(H12/I12)*(B4*(1+B5)) -> 750720.58 | K12: =B9*(1+B6)^-(B7*B8) -> 15106.139 | L12: =J12*I12/(G12*H12) -> 10200 | M12: =K12*((1+$B$6)^($B$7*$B$8))*I12/(G12*H12) -> 1444.9316
A17: Annuity 2
A18: Cashflow | B18: ='Assignment6 (User Interface)'!J5 -> 400
A19: Annuity Interest | B19: ='Assignment6 (User Interface)'!J6 -> 0.01
A20: Annuity Increase Interest | B20: ='Assignment6 (User Interface)'!J7 -> 0.04
A21: k | B21: ='Assignment6 (User Interface)'!J8 -> 12
A22: m | B22: ='Assignment6 (User Interface)'!J9 -> 10
A23: Future Value | B23: ='Assignment6 (User Interface)'!J10 -> 106347.05 | G23: Annuity 2
A24: Present Value | B24: ='Assignment6 (User Interface)'!J11 -> 322222 | G24: part1 | H24: part2 | I24: part3 | J24: fv | K24: PV | L24: x-uninf FV | M24: X-using PV
F25: Arrears | G25: =((((1+B19)^B21)-1)/B19) -> 12.682503 | H25: =((1+B19)^(B21*B22)) - ((1+B20)^B22) -> 1.8201426 | I25: =((1+B19)^(B21))-(1+B20) -> 0.08682503 | J25: =(G25*(H25/I25))*B18 -> 106347.05 | K25: =B23*(1+B20)^(-B21*B22) -> 961.00297 | L25: =J25*I25/(G25*H25) -> 400 | M25: =K25*((1+B20)^(B21*B22))*I25/(G25*H25) -> 400.00001
F26: Advance | G26: =((((1+B19)^B21)-1)/B19) -> 12.682503 | H26: =(1+B19)^(B21*B22)-(1+B20)^(B22) -> 1.8201426 | I26: =(1+B19)^(B21)-(1+B20) -> 0.08682503 | J26: =G26*(H26/I26)*(B18*(1+B19)) -> 107410.52 | K26: =B23*(1+B20)^-(B21*B22) -> 961.00297 | L26: =J26*I26/(G26*H26) -> 404 | M26: =K26*((1+B20)^(B21*B22))*I26/(G26*H26) -> 400.00001

Sheet Assignment6 (User Interface)
A1: INCREASING ANNUITIES
Z2: Arrears | AA2: Future Value
A3: ANUUITY 1 | I3: ANNUITY 2 | Z3: Advance | AA3: Present Value
A4: GIVENS | D4: UNKOWNS | I4: GIVENS | L4: UNKOWNS | AA4: Cashflow-using FV
A5: Cashflow | B5: 10000 | D5: Annuity type | E5: Arrears | I5: Cashflow | J5: 400 | L5: Annuity type | M5: Advance | AA5: Cashflow-using PV
A6: Annuity Interest | B6: 0.02 | I6: Annuity Interest | J6: 0.01
A7: Annuity increase interest | B7: 0.05 | D7: Annuity | E7: Future Value | I7: Annuity increase interest | J7: 0.04 | L7: Annuity | M7: Cashflow-using PV
A8: k | B8: 4 | I8: k | J8: 12
A9: m | B9: 10 | D9: Value | E9: =IF(AND(E5=Z2,E7=AA2),'Assignment6 (Back Office)'!J11,IF(AND(E5=Z2,E7=AA3),'Assignment6 (Back Office)'!K11,IF(AND(E5=Z2,E7=AA4),'Assignment6 (Back Office)'!L11,IF(AND(E5=Z2,E7=AA5),'Assignment6 (Back Office)'!M11,IF(AND(E5=Z3,E7=AA2),'Assignment6 (Back Office)'!J12,IF(AND(E5=Z3,E7=AA3),'Assignment6 (Back Office)'!K12,IF(AND(E5=Z3,E7=AA4),'Assignment6 (Back Office)'!L12,IF(AND(E5=Z3,E7=AA5),'Assignment6 (Back Office)'!M12,"More to be done")))))))) -> 736000.57 | I9: m | J9: 10 | L9: Value | M9: =IF(AND(M5=Z2,M7=AA2),'Assignment6 (Back Office)'!J25,IF(AND(M5=Z2,M7=AA3),'Assignment6 (Back Office)'!K25,IF(AND(M5=Z2,M7=AA4),'Assignment6 (Back Office)'!L25,IF(AND(M5=Z2,M7=AA5),'Assignment6 (Back Office)'!M25,IF(AND(M5=Z3,M7=AA2),'Assignment6 (Back Office)'!J26,IF(AND(M5=Z3,M7=AA3),'Assignment6 (Back Office)'!K26,IF(AND(M5=Z3,M7=AA4),'Assignment6 (Back Office)'!L26,IF(AND(M5=Z3,M7=AA5),'Assignment6 (Back Office)'!M26,"More work to be done")))))))) -> 400.00001
A10: Future Value | B10: 106347.05 | I10: Future Value | J10: 106347.05
A11: Present Value | B11: 322222 | I11: Present Value | J11: 322222
A13: Interest Conversion:
A15: Single Investment
A17: Home
A19: GRAPH COMPARISONS

Sheet Single + Increasing Annuity
A1: INCREASING ANNUITIES (Investments and Withdrawals) + Single Payments
A2: Investment | I2: Withdrawals / Loan
A3: GIVENS | D3: UNKOWNS | I3: GIVENS | L3: UNKOWNS | Q3: Investment | S3: Future Value
A4: Single Investment Amount | I4: Loan/Balance | Q4: Loan/Withdrawal | S4: Present Value
A5: Cashflow | D5: Unkown Value | E5: Future Value | I5: Cashflow | L5: Unkown Value | M5: Last balance | S5: Capital
A6: Annuity Interest | I6: Annuity Interest | Q6: Initial Single Investment | S6: Interest at k perion
A7: Annuity increase interest | I7: Annuity increase interest | Q7: Payment | S7: Total Interest
A8: Period type | I8: Period type | Q8: Present Value | S8: Interest from K to T period
A9: Years of investment | D9: Value | E9: =IF(E5=Q6,'Single + Increasing Annuity(Bac'!G18,IF(E5=Q7,'Single + Increasing Annuity(Bac'!G19,IF(E5=Q8,'Single + Increasing Annuity(Bac'!G22,IF(E5=Q9,'Single + Increasing Annuity(Bac'!G23,IF(E5=Q10,'Single + Increasing Annuity(Bac'!G24))))) -> #N/A | I9: Years of investment | L9: Value | M9: =IF(M5=S12,'Single + Increasing Annuity(Bac'!G4,IF(M5=S13,'Single + Increasing Annuity(Bac'!G5,IF(M5=S14,'Single + Increasing Annuity(Bac'!G7,IF(M5=S15,'Single + Increasing Annuity(Bac'!G8,IF(M5=S16,'Single + Increasing Annuity(Bac'!G9,IF(M5=S17,'Single + Increasing Annuity(Bac'!G10,IF(M5=S18,'Single + Increasing Annuity(Bac'!G11,IF(M5=S19,'Single + Increasing Annuity(Bac'!G12,IF(M5=S20,'Single + Increasing Annuity(Bac'!G13, IF(M5=S21, 'Single + Increasing Annuity(Bac'!G14, IF(M5=S22, 'Single + Increasing Annuity(Bac'!G15))))))))))) -> #N/A | Q9: Total Interest | S9: Capital from K to T period
A10: Future Value | I10: Future Value | Q10: Future Value
A11: Present Value | D11: Real Future Value | E11: =IF(E5=Q10, E9*(1+5%)^(-B9), "") -> #N/A | I11: Present Value
I12: Period (Start) | S12: Loan amount
A13: Interest Conversion: | I13: Period (End) | S13: Payment
I14: Specific interest/ capital at period K | S14: Balance at specific period
A15: Single Investment | I15: Balance at specific period | S15: Interest component of payment k
S16: Capital component of payment k
S17: Interest from payment X1 to X2
A18: Home | S18: Capital from payment X1 to X2
S19: Last payment
S20: Total Interest
S21: Total Capital
S22: Last balance

Sheet Single + Increasing Annuity(Bac
A3: Investment | G3: LOANS / WITHDRAWALS
A4: Single Investment Amount | B4: ='Single + Increasing Annuity'!B4 -> 0 | F4: Loan amount | G4: =B24 + B19*(((1+B20)^(B22*B23) - (1+B21)^(B23*B22))/(B20-B21)) -> #DIV/0!
A5: Cashflow | B5: ='Single + Increasing Annuity'!B5 -> 0 | F5: Payment | G5: =(-B24 +B18*(1+B20)^(B22*B23))/(((1+B20)^(B22*B23) - (1+B21)^(B22*B23))/(B20-B21)) -> #DIV/0!
A6: Annuity Interest | B6: ='Single + Increasing Annuity'!B6 -> 0
A7: Annuity increase interest | B7: ='Single + Increasing Annuity'!B7 -> 0 | F7: Balance at specific time of the year | G7: =VLOOKUP(B29, A31:H636,2, FALSE) -> #N/A
A8: Period type | B8: ='Single + Increasing Annuity'!B8 -> 0 | F8: Interest component of payment k | G8: =VLOOKUP(B28, A31:H636,7, FALSE) -> #N/A
A9: Years of investment | B9: ='Single + Increasing Annuity'!B9 -> 0 | F9: Capital component of payment k | G9: =VLOOKUP(B28, A31:H636,5, FALSE) -> #N/A
A10: Future Value | B10: 1135009.3 | F10: Interest from payment X1 to X2 | G10: =SUM(INDEX(C31:C611, MATCH(B26, A31:A611, 0)) : INDEX(C31:C611, MATCH(B27, A31:A611, 0))) -> #N/A
A11: Present Value | B11: ='Single + Increasing Annuity'!B11 -> 0 | F11: Capital from payment X1 to X2 | G11: =SUM(INDEX(E31:E611, MATCH(B26, A31:A611, 0)) : INDEX(E31:E611, MATCH(B27, A31:A611, 0))) -> #N/A
F12: Last payment | G12: {=LOOKUP(2, 1/(B32:B611), B32:B611)} -> #N/A
F13: Total Interest | G13: {=LOOKUP(2, 1/(G32:G611), G32:G611)} -> #N/A
F14: Total Capital | G14: {=LOOKUP(2, 1/(H32:H611), H32:H611)} -> #N/A
F15: Last balance | G15: {=LOOKUP(2, 1/(F32:F611), F32:F611)} -> #N/A
A17: Loans/Withdrawls | G17: INVESTMENTS
A18: Loan / Balance | B18: ='Single + Increasing Annuity'!J4 -> 0 | F18: Initial Single Investment | G18: =(B10-B5*(((1+B6)^(B8*B9)-(1+B7)^(B9*B8)/B6-B7))/((1+B6)^(B8*B9))) -> #DIV/0!
A19: Cashflow | B19: ='Single + Increasing Annuity'!J5 -> 0 | F19: Payment | G19: =(B10 - B4*(1+B6)^(B8*B9))/(((1+B6)^(B8*B9) - (1+B7)^(B8*B9))/(B6 - B7)) -> #DIV/0!
A20: Annuity Interest | B20: ='Single + Increasing Annuity'!J6 -> 0
A21: Annuity increase interest | B21: ='Single + Increasing Annuity'!J7 -> 0
A22: Period type | B22: ='Single + Increasing Annuity'!J8 -> 0 | F22: Present Value | G22: =B10*(1+B6)^(-B8*B9) -> 1135009.3
A23: Years of investment | B23: ='Single + Increasing Annuity'!J9 -> 0 | F23: Total Interest | G23: {=LOOKUP(2, 1/(Q32:Q611), Q32:Q611)} -> #N/A
A24: Future Value | B24: 0 | F24: Future Value | G24: {=LOOKUP(2, 1/(P32:P611), P32:P611)} -> #N/A
A25: Present Value | B25: ='Single + Increasing Annuity'!J11 -> 0
A26: Period (Start) | B26: ='Single + Increasing Annuity'!J12 -> 0
A27: Period (End) | B27: ='Single + Increasing Annuity'!J13 -> 0
A28: Specific Interest/Capital at K | B28: ='Single + Increasing Annuity'!J14 -> 0
A29: Balance at specific period | B29: ='Single + Increasing Annuity'!J15 -> 0
A30: Amortization table (Withdrawals) | L30: Amortization table (Advance)
A31: Period | B31: Balance at Start | C31: Interest | D31: Payment | E31: Capital | F31: Balance at end | G31: Interest so far | H31: Capital so far | L31: Period | M31: Balance at Start | N31: Interest | O31: Payment | P31: Balance at end | Q31: Interest so far
A32: 1 | B32: =B18 -> 0 | C32: =$B$20*B32 -> 0 | D32: =$B$19 -> 0 | E32: =D32-C32 -> 0 | F32: =B32-E32 -> 0 | G32: =C32 -> 0 | H32: =E32 -> 0 | L32: 1 | M32: =B4 -> 0 | N32: =$B$6 *M32 -> 0 | O32: =B5 -> 0 | P32: =M32+N32+O32 -> 0 | Q32: =N32 -> 0
A33: =IF(A32<($B$22*$B$23),A32+1,"") | B33: =IF(A33="","",F32) | C33: =IF(A33="","",(B33*$B$20)) | D33: =IF(A33="","", D32*(1+$B$21)) | E33: =IF(D33="","",(D33-C33)) | F33: =IF(A33="","", B33-E33) | G33: =IF(A33="","", (G32+C33)) | H33: =IF(A33="","",(H32+E33)) | L33: =IF(L32<($B$8*$B$9),L32+1,"") | M33: =IF(L33="","",P32) | N33: =IF(L33="","",(M33 *$B$6)) | O33: =IF(L33="","",O32*(1+$B$7)) | P33: =IF(L33="","", M33+N33+O33) | Q33: =IF(L33="","", (Q32+N33))
A34: =IF(A33<($B$22*$B$23),A33+1,"") | B34: =IF(A34="","",F33) | C34: =IF(A34="","",(B34*$B$20)) | D34: =IF(A34="","", D33*(1+$B$21)) | E34: =IF(D34="","",(D34-C34)) | F34: =IF(A34="","", B34-E34) | G34: =IF(A34="","", (G33+C34)) | H34: =IF(A34="","",(H33+E34)) | L34: =IF(L33<($B$8*$B$9),L33+1,"") | M34: =IF(L34="","",P33) | N34: =IF(L34="","",(M34 *$B$6)) | O34: =IF(L34="","",O33*(1+$B$7)) | P34: =IF(L34="","", M34+N34+O34) | Q34: =IF(L34="","", (Q33+N34))
A35: =IF(A34<($B$22*$B$23),A34+1,"") | B35: =IF(A35="","",F34) | C35: =IF(A35="","",(B35*$B$20)) | D35: =IF(A35="","", D34*(1+$B$21)) | E35: =IF(D35="","",(D35-C35)) | F35: =IF(A35="","", B35-E35) | G35: =IF(A35="","", (G34+C35)) | H35: =IF(A35="","",(H34+E35)) | L35: =IF(L34<($B$8*$B$9),L34+1,"") | M35: =IF(L35="","",P34) | N35: =IF(L35="","",(M35 *$B$6)) | O35: =IF(L35="","",O34*(1+$B$7)) | P35: =IF(L35="","", M35+N35+O35) | Q35: =IF(L35="","", (Q34+N35))
A36: =IF(A35<($B$22*$B$23),A35+1,"") | B36: =IF(A36="","",F35) | C36: =IF(A36="","",(B36*$B$20)) | D36: =IF(A36="","", D35*(1+$B$21)) | E36: =IF(D36="","",(D36-C36)) | F36: =IF(A36="","", B36-E36) | G36: =IF(A36="","", (G35+C36)) | H36: =IF(A36="","",(H35+E36)) | L36: =IF(L35<($B$8*$B$9),L35+1,"") | M36: =IF(L36="","",P35) | N36: =IF(L36="","",(M36 *$B$6)) | O36: =IF(L36="","",O35*(1+$B$7)) | P36: =IF(L36="","", M36+N36+O36) | Q36: =IF(L36="","", (Q35+N36))
A37: =IF(A36<($B$22*$B$23),A36+1,"") | B37: =IF(A37="","",F36) | C37: =IF(A37="","",(B37*$B$20)) | D37: =IF(A37="","", D36*(1+$B$21)) | E37: =IF(D37="","",(D37-C37)) | F37: =IF(A37="","", B37-E37) | G37: =IF(A37="","", (G36+C37)) | H37: =IF(A37="","",(H36+E37)) | L37: =IF(L36<($B$8*$B$9),L36+1,"") | M37: =IF(L37="","",P36) | N37: =IF(L37="","",(M37 *$B$6)) | O37: =IF(L37="","",O36*(1+$B$7)) | P37: =IF(L37="","", M37+N37+O37) | Q37: =IF(L37="","", (Q36+N37))
A38: =IF(A37<($B$22*$B$23),A37+1,"") | B38: =IF(A38="","",F37) | C38: =IF(A38="","",(B38*$B$20)) | D38: =IF(A38="","", D37*(1+$B$21)) | E38: =IF(D38="","",(D38-C38)) | F38: =IF(A38="","", B38-E38) | G38: =IF(A38="","", (G37+C38)) | H38: =IF(A38="","",(H37+E38)) | L38: =IF(L37<($B$8*$B$9),L37+1,"") | M38: =IF(L38="","",P37) | N38: =IF(L38="","",(M38 *$B$6)) | O38: =IF(L38="","",O37*(1+$B$7)) | P38: =IF(L38="","", M38+N38+O38) | Q38: =IF(L38="","", (Q37+N38))
A39: =IF(A38<($B$22*$B$23),A38+1,"") | B39: =IF(A39="","",F38) | C39: =IF(A39="","",(B39*$B$20)) | D39: =IF(A39="","", D38*(1+$B$21)) | E39: =IF(D39="","",(D39-C39)) | F39: =IF(A39="","", B39-E39) | G39: =IF(A39="","", (G38+C39)) | H39: =IF(A39="","",(H38+E39)) | L39: =IF(L38<($B$8*$B$9),L38+1,"") | M39: =IF(L39="","",P38) | N39: =IF(L39="","",(M39 *$B$6)) | O39: =IF(L39="","",O38*(1+$B$7)) | P39: =IF(L39="","", M39+N39+O39) | Q39: =IF(L39="","", (Q38+N39))
A40: =IF(A39<($B$22*$B$23),A39+1,"") | B40: =IF(A40="","",F39) | C40: =IF(A40="","",(B40*$B$20)) | D40: =IF(A40="","", D39*(1+$B$21)) | E40: =IF(D40="","",(D40-C40)) | F40: =IF(A40="","", B40-E40) | G40: =IF(A40="","", (G39+C40)) | H40: =IF(A40="","",(H39+E40)) | L40: =IF(L39<($B$8*$B$9),L39+1,"") | M40: =IF(L40="","",P39) | N40: =IF(L40="","",(M40 *$B$6)) | O40: =IF(L40="","",O39*(1+$B$7)) | P40: =IF(L40="","", M40+N40+O40) | Q40: =IF(L40="","", (Q39+N40))
A41: =IF(A40<($B$22*$B$23),A40+1,"") | B41: =IF(A41="","",F40) | C41: =IF(A41="","",(B41*$B$20)) | D41: =IF(A41="","", D40*(1+$B$21)) | E41: =IF(D41="","",(D41-C41)) | F41: =IF(A41="","", B41-E41) | G41: =IF(A41="","", (G40+C41)) | H41: =IF(A41="","",(H40+E41)) | L41: =IF(L40<($B$8*$B$9),L40+1,"") | M41: =IF(L41="","",P40) | N41: =IF(L41="","",(M41 *$B$6)) | O41: =IF(L41="","",O40*(1+$B$7)) | P41: =IF(L41="","", M41+N41+O41) | Q41: =IF(L41="","", (Q40+N41))
A42: =IF(A41<($B$22*$B$23),A41+1,"") | B42: =IF(A42="","",F41) | C42: =IF(A42="","",(B42*$B$20)) | D42: =IF(A42="","", D41*(1+$B$21)) | E42: =IF(D42="","",(D42-C42)) | F42: =IF(A42="","", B42-E42) | G42: =IF(A42="","", (G41+C42)) | H42: =IF(A42="","",(H41+E42)) | L42: =IF(L41<($B$8*$B$9),L41+1,"") | M42: =IF(L42="","",P41) | N42: =IF(L42="","",(M42 *$B$6)) | O42: =IF(L42="","",O41*(1+$B$7)) | P42: =IF(L42="","", M42+N42+O42) | Q42: =IF(L42="","", (Q41+N42))
A43: =IF(A42<($B$22*$B$23),A42+1,"") | B43: =IF(A43="","",F42) | C43: =IF(A43="","",(B43*$B$20)) | D43: =IF(A43="","", D42*(1+$B$21)) | E43: =IF(D43="","",(D43-C43)) | F43: =IF(A43="","", B43-E43) | G43: =IF(A43="","", (G42+C43)) | H43: =IF(A43="","",(H42+E43)) | L43: =IF(L42<($B$8*$B$9),L42+1,"") | M43: =IF(L43="","",P42) | N43: =IF(L43="","",(M43 *$B$6)) | O43: =IF(L43="","",O42*(1+$B$7)) | P43: =IF(L43="","", M43+N43+O43) | Q43: =IF(L43="","", (Q42+N43))
A44: =IF(A43<($B$22*$B$23),A43+1,"") | B44: =IF(A44="","",F43) | C44: =IF(A44="","",(B44*$B$20)) | D44: =IF(A44="","", D43*(1+$B$21)) | E44: =IF(D44="","",(D44-C44)) | F44: =IF(A44="","", B44-E44) | G44: =IF(A44="","", (G43+C44)) | H44: =IF(A44="","",(H43+E44)) | L44: =IF(L43<($B$8*$B$9),L43+1,"") | M44: =IF(L44="","",P43) | N44: =IF(L44="","",(M44 *$B$6)) | O44: =IF(L44="","",O43*(1+$B$7)) | P44: =IF(L44="","", M44+N44+O44) | Q44: =IF(L44="","", (Q43+N44))
... A638: =IF(A637<($B$22*$B$23),A637+1,"") | B638: =IF(A638="","",F637) | C638: =IF(A638="","",(B638*$B$20)) | D638: =IF(A638="","", D637*(1+$B$21)) | E638: =IF(D638="","",(D638-C638)) | F638: =IF(A638="","", B638-E638) | G638: =IF(A638="","", (G637+C638)) | H638: =IF(A638="","",(H637+E638)) | L638: =IF(L637<($B$8*$B$9),L637+1,"") | M638: =IF(L638="","",P637) | N638: =IF(L638="","",(M638 *$B$6)) | O638: =IF(L638="","",O637*(1+$B$7)) | P638: =IF(L638="","", M638+N638+O638) | Q638: =IF(L638="","", (Q637+N638))
L639: =IF(L638<($B$8*$B$9),L638+1,"") | M639: =IF(L639="","",P638) | N639: =IF(L639="","",(M639 *$B$6)) | O639: =IF(L639="","",O638*(1+$B$7)) | P639: =IF(L639="","", M639+N639+O639) | Q639: =IF(L639="","", (Q638+N639))
L640: =IF(L639<($B$8*$B$9),L639+1,"") | M640: =IF(L640="","",P639) | N640: =IF(L640="","",(M640 *$B$6)) | O640: =IF(L640="","",O639*(1+$B$7)) | P640: =IF(L640="","", M640+N640+O640) | Q640: =IF(L640="","", (Q639+N640))
L641: =IF(L640<($B$8*$B$9),L640+1,"") | M641: =IF(L641="","",P640) | N641: =IF(L641="","",(M641 *$B$6)) | O641: =IF(L641="","",O640*(1+$B$7)) | P641: =IF(L641="","", M641+N641+O641) | Q641: =IF(L641="","", (Q640+N641))
L642: =IF(L641<($B$8*$B$9),L641+1,"") | M642: =IF(L642="","",P641) | N642: =IF(L642="","",(M642 *$B$6)) | O642: =IF(L642="","",O641*(1+$B$7)) | P642: =IF(L642="","", M642+N642+O642) | Q642: =IF(L642="","", (Q641+N642))
L643: =IF(L642<($B$8*$B$9),L642+1,"") | M643: =IF(L643="","",P642) | N643: =IF(L643="","",(M643 *$B$6)) | O643: =IF(L643="","",O642*(1+$B$7)) | P643: =IF(L643="","", M643+N643+O643) | Q643: =IF(L643="","", (Q642+N643))
L644: =IF(L643<($B$8*$B$9),L643+1,"") | M644: =IF(L644="","",P643) | N644: =IF(L644="","",(M644 *$B$6)) | O644: =IF(L644="","",O643*(1+$B$7)) | P644: =IF(L644="","", M644+N644+O644) | Q644: =IF(L644="","", (Q643+N644))
L645: =IF(L644<($B$8*$B$9),L644+1,"") | M645: =IF(L645="","",P644) | N645: =IF(L645="","",(M645 *$B$6)) | O645: =IF(L645="","",O644*(1+$B$7)) | P645: =IF(L645="","", M645+N645+O645) | Q645: =IF(L645="","", (Q644+N645))
L646: =IF(L645<($B$8*$B$9),L645+1,"") | M646: =IF(L646="","",P645) | N646: =IF(L646="","",(M646 *$B$6)) | O646: =IF(L646="","",O645*(1+$B$7)) | P646: =IF(L646="","", M646+N646+O646) | Q646: =IF(L646="","", (Q645+N646))
L647: =IF(L646<($B$8*$B$9),L646+1,"") | M647: =IF(L647="","",P646) | N647: =IF(L647="","",(M647 *$B$6)) | O647: =IF(L647="","",O646*(1+$B$7)) | P647: =IF(L647="","", M647+N647+O647) | Q647: =IF(L647="","", (Q646+N647))
L648: =IF(L647<($B$8*$B$9),L647+1,"") | M648: =IF(L648="","",P647) | N648: =IF(L648="","",(M648 *$B$6)) | O648: =IF(L648="","",O647*(1+$B$7)) | P648: =IF(L648="","", M648+N648+O648) | Q648: =IF(L648="","", (Q647+N648))
L649: =IF(L648<($B$8*$B$9),L648+1,"") | M649: =IF(L649="","",P648) | N649: =IF(L649="","",(M649 *$B$6)) | O649: =IF(L649="","",O648*(1+$B$7)) | P649: =IF(L649="","", M649+N649+O649) | Q649: =IF(L649="","", (Q648+N649))
L650: =IF(L649<($B$8*$B$9),L649+1,"") | M650: =IF(L650="","",P649) | N650: =IF(L650="","",(M650 *$B$6)) | O650: =IF(L650="","",O649*(1+$B$7)) | P650: =IF(L650="","", M650+N650+O650) | Q650: =IF(L650="","", (Q649+N650))
... L732: =IF(L731<($B$8*$B$9),L731+1,"") | M732: =IF(L732="","",P731) | N732: =IF(L732="","",(M732 *$B$6)) | O732: =IF(L732="","",O731*(1+$B$7)) | P732: =IF(L732="","", M732+N732+O732) | Q732: =IF(L732="","", (Q731+N732))
L733: =IF(L732<($B$8*$B$9),L732+1,"") | M733: =IF(L733="","",P732) | N733: =IF(L733="","",(M733 *$B$6)) | O733: =IF(L733="","",O732*(1+$B$7)) | P733: =IF(L733="","", M733-#REF!) | Q733: =IF(L733="","", (Q732+N733))
L734: =IF(L733<($B$8*$B$9),L733+1,"") | M734: =IF(L734="","",P733) | N734: =IF(L734="","",(M734 *$B$6)) | O734: =IF(L734="","",O733*(1+$B$7)) | P734: =IF(L734="","", M734-#REF!) | Q734: =IF(L734="","", (Q733+N734))
L735: =IF(L734<($B$8*$B$9),L734+1,"") | M735: =IF(L735="","",P734) | N735: =IF(L735="","",(M735 *$B$6)) | O735: =IF(L735="","",O734*(1+$B$7)) | P735: =IF(L735="","", M735-#REF!) | Q735: =IF(L735="","", (Q734+N735))
L736: =IF(L735<($B$8*$B$9),L735+1,"") | M736: =IF(L736="","",P735) | N736: =IF(L736="","",(M736 *$B$6)) | O736: =IF(L736="","",O735*(1+$B$7)) | P736: =IF(L736="","", M736-#REF!) | Q736: =IF(L736="","", (Q735+N736))
L737: =IF(L736<($B$8*$B$9),L736+1,"") | M737: =IF(L737="","",P736) | N737: =IF(L737="","",(M737 *$B$6)) | O737: =IF(L737="","",O736*(1+$B$7)) | P737: =IF(L737="","", M737-#REF!) | Q737: =IF(L737="","", (Q736+N737))
L738: =IF(L737<($B$8*$B$9),L737+1,"") | M738: =IF(L738="","",P737) | N738: =IF(L738="","",(M738 *$B$6)) | O738: =IF(L738="","",O737*(1+$B$7)) | P738: =IF(L738="","", M738-#REF!) | Q738: =IF(L738="","", (Q737+N738))
L739: =IF(L738<($B$8*$B$9),L738+1,"") | M739: =IF(L739="","",P738) | N739: =IF(L739="","",(M739 *$B$6)) | O739: =IF(L739="","",O738*(1+$B$7)) | P739: =IF(L739="","", M739-#REF!) | Q739: =IF(L739="","", (Q738+N739))
L740: =IF(L739<($B$8*$B$9),L739+1,"") | M740: =IF(L740="","",P739) | N740: =IF(L740="","",(M740 *$B$6)) | O740: =IF(L740="","",O739*(1+$B$7)) | P740: =IF(L740="","", M740-#REF!) | Q740: =IF(L740="","", (Q739+N740))
L741: =IF(L740<($B$8*$B$9),L740+1,"") | M741: =IF(L741="","",P740) | N741: =IF(L741="","",(M741 *$B$6)) | O741: =IF(L741="","",O740*(1+$B$7)) | P741: =IF(L741="","", M741-#REF!) | Q741: =IF(L741="","", (Q740+N741))
L742: =IF(L741<($B$8*$B$9),L741+1,"") | M742: =IF(L742="","",P741) | N742: =IF(L742="","",(M742 *$B$6)) | O742: =IF(L742="","",O741*(1+$B$7)) | P742: =IF(L742="","", M742-#REF!) | Q742: =IF(L742="","", (Q741+N742))
L743: =IF(L742<($B$8*$B$9),L742+1,"") | M743: =IF(L743="","",P742) | N743: =IF(L743="","",(M743 *$B$6)) | O743: =IF(L743="","",O742*(1+$B$7)) | P743: =IF(L743="","", M743-#REF!) | Q743: =IF(L743="","", (Q742+N743))
L744: =IF(L743<($B$8*$B$9),L743+1,"") | M744: =IF(L744="","",P743) | N744: =IF(L744="","",(M744 *$B$6)) | O744: =IF(L744="","",O743*(1+$B$7)) | P744: =IF(L744="","", M744-#REF!) | Q744: =IF(L744="","", (Q743+N744))
... L887: =IF(L886<($B$8*$B$9),L886+1,"") | M887: =IF(L887="","",P886) | N887: =IF(L887="","",(M887 *$B$6)) | O887: =IF(L887="","",O886*(1+$B$7)) | P887: =IF(L887="","", M887-#REF!) | Q887: =IF(L887="","", (Q886+N887))
L888: =IF(L887<($B$8*$B$9),L887+1,"") | M888: =IF(L888="","",P887) | N888: =IF(L888="","",(M888 *$B$6)) | O888: =IF(L888="","",O887*(1+$B$7)) | P888: =IF(L888="","", M888-#REF!) | Q888: =IF(L888="","", (Q887+N888)) | R888: =IF(L888="","",(R887+#REF!))
L889: =IF(L888<($B$8*$B$9),L888+1,"") | M889: =IF(L889="","",P888) | N889: =IF(L889="","",(M889 *$B$6)) | O889: =IF(L889="","",O888*(1+$B$7)) | P889: =IF(L889="","", M889-#REF!) | Q889: =IF(L889="","", (Q888+N889)) | R889: =IF(L889="","",(R888+#REF!))
L890: =IF(L889<($B$8*$B$9),L889+1,"") | M890: =IF(L890="","",P889) | N890: =IF(L890="","",(M890 *$B$6)) | O890: =IF(L890="","",O889*(1+$B$7)) | P890: =IF(L890="","", M890-#REF!) | Q890: =IF(L890="","", (Q889+N890)) | R890: =IF(L890="","",(R889+#REF!))
